Workbook

Sheet ProfitLoss
A1: Fall | C1: 2025 | D1: . | Q1: asdasd | R1: =$A$1&" "&$C$1 -> Fall 2025
B2: Income | C2: =IF($A$1="Spring", "January", IF($A$1="Fall", "July", 0)) -> July | D2: =IF($A$1="Spring", "February", IF($A$1="Fall", "August", 0)) -> August | E2: =IF($A$1="Spring", "March", IF($A$1="Fall", "September", 0)) -> September | F2: =IF($A$1="Spring", "April", IF($A$1="Fall", "October", 0)) -> October | G2: =IF($A$1="Spring", "May", IF($A$1="Fall", "November", 0)) -> November | H2: =IF($A$1="Spring", "June", IF($A$1="Fall", "December", 0)) -> December | I2: =$A$1&" Total" -> Fall Total | K2: Expenses | L2: =IF($A$1="Spring", "January", IF($A$1="Fall", "July", 0)) -> July | M2: =IF($A$1="Spring", "February", IF($A$1="Fall", "August", 0)) -> August | N2: =IF($A$1="Spring", "March", IF($A$1="Fall", "September", 0)) -> September | O2: =IF($A$1="Spring", "April", IF($A$1="Fall", "October", 0)) -> October | P2: =IF($A$1="Spring", "May", IF($A$1="Fall", "November", 0)) -> November | Q2: =IF($A$1="Spring", "June", IF($A$1="Fall", "December", 0)) -> December | R2: =$A$1&" Total" -> Fall Total | T2: asdad | U2: Semester Totals:
A3: Total Montly Income | C3: =C$4+C$10+C$17+C$24+C$31 -> 0 | D3: =D$4+D$10+D$17+D$24+D$31 -> 799.77 | E3: =E$4+E$10+E$17+E$24+E$31 -> 787.13 | F3: =F$4+F$10+F$17+F$24+F$31 -> 57.82 | G3: =G$4+G$10+G$17+G$24+G$31 -> 0 | H3: =H$4+H$10+H$17+H$24+H$31 -> 0 | I3: =I$4+I$10+I$17+I$24+I$31 -> 1644.72 | K3: Monthly Profit | L3: =C3-L4 -> -329.31 | M3: =D3-M4 -> 522.71 | N3: =E3-N4 -> 100.1 | O3: =F3-O4 -> -62.97 | P3: =G3-P4 -> 0 | Q3: =H3-Q4 -> 0 | R3: =I3-R4 -> 230.53 | T3: ="Income for "&$A$1&" of "& $C$1&":" -> Income for Fall of 2025: | V3: =SUM($I$4,$I$10,$I$17,$I$24,$I$31) -> 1644.72
A4: Member dues | B4: Monthly totals: | C4: =sum(C$5:C$9) -> 0 | D4: =sum(D$5:D$9) -> 465 | E4: =sum(E$5:E$9) -> 640 | F4: =sum(F$5:F$9) -> 0 | G4: =sum(G$5:G$9) -> 0 | H4: =sum(H$5:H$9) -> 0 | I4: =SUM(C4:H4) -> 1105 | K4: Monthly totals: | L4: =sum(L$5:L$10) -> 329.31 | M4: =sum(M$5:M$10) -> 277.06 | N4: =sum(N$5:N$10) -> 687.03 | O4: =sum(O$5:O$10) -> 120.79 | P4: =sum(P$5:P$10) -> 0 | Q4: =sum(Q$5:Q$10) -> 0 | R4: =SUM(L4:Q4) -> 1414.19 | T4: ="Expenses for "&$A$1&" of "& $C$1&":" -> Expenses for Fall of 2025: | V4: =$R$4 -> 1414.19
B5: Paypal | C5: {=INDEX(IncomeCalcs!$K$2:$O$254,MATCH(DATEVALUE(MATCH(C$2,{"January","February","March","April","May","June","July","August","September","October","November","December"},0) & "/1/" &$C$1),IncomeCalcs!$J$2:$J37,0),MATCH($B5,IncomeCalcs!$K$2:$O$2,0))} -> 0 | D5: {=INDEX(IncomeCalcs!$K$2:$O$254,MATCH(DATEVALUE(MATCH(D$2,{"January","February","March","April","May","June","July","August","September","October","November","December"},0) & "/1/" &$C$1),IncomeCalcs!$J$2:$J37,0),MATCH($B5,IncomeCalcs!$K$2:$O$2,0))} -> 75 | E5: {=INDEX(IncomeCalcs!$K$2:$O$254,MATCH(DATEVALUE(MATCH(E$2,{"January","February","March","April","May","June","July","August","September","October","November","December"},0) & "/1/" &$C$1),IncomeCalcs!$J$2:$J37,0),MATCH($B5,IncomeCalcs!$K$2:$O$2,0))} -> 130 | F5: {=INDEX(IncomeCalcs!$K$2:$O$254,MATCH(DATEVALUE(MATCH(F$2,{"January","February","March","April","May","June","July","August","September","October","November","December"},0) & "/1/" &$C$1),IncomeCalcs!$J$2:$J37,0),MATCH($B5,IncomeCalcs!$K$2:$O$2,0))} -> 0 | G5: {=INDEX(IncomeCalcs!$K$2:$O$254,MATCH(DATEVALUE(MATCH(G$2,{"January","February","March","April","May","June","July","August","September","October","November","December"},0) & "/1/" &$C$1),IncomeCalcs!$J$2:$J37,0),MATCH($B5,IncomeCalcs!$K$2:$O$2,0))} -> 0 | H5: {=INDEX(IncomeCalcs!$K$2:$O$254,MATCH(DATEVALUE(MATCH(H$2,{"January","February","March","April","May","June","July","August","September","October","November","December"},0) & "/1/" &$C$1),IncomeCalcs!$J$2:$J37,0),MATCH($B5,IncomeCalcs!$K$2:$O$2,0))} -> 0 | I5: =SUM(C5:H5) -> 205 | K5: Vet Bills | L5: =SUMIFS(Expenses!$F$4:$F37,Expenses!$E$4:$E37,$K5,Expenses!$B$4:$B37,L$2,Expenses!$C$4:$C37,$C$1) -> 0 | M5: =SUMIFS(Expenses!$F$4:$F37,Expenses!$E$4:$E37,$K5,Expenses!$B$4:$B37,M$2,Expenses!$C$4:$C37,$C$1) -> 0 | N5: =SUMIFS(Expenses!$F$4:$F37,Expenses!$E$4:$E37,$K5,Expenses!$B$4:$B37,N$2,Expenses!$C$4:$C37,$C$1) -> 414 | O5: =SUMIFS(Expenses!$F$4:$F37,Expenses!$E$4:$E37,$K5,Expenses!$B$4:$B37,O$2,Expenses!$C$4:$C37,$C$1) -> 0 | P5: =SUMIFS(Expenses!$F$4:$F37,Expenses!$E$4:$E37,$K5,Expenses!$B$4:$B37,P$2,Expenses!$C$4:$C37,$C$1) -> 0 | Q5: =SUMIFS(Expenses!$F$4:$F37,Expenses!$E$4:$E37,$K5,Expenses!$B$4:$B37,Q$2,Expenses!$C$4:$C37,$C$1) -> 0 | R5: =SUM(L5:Q5) -> 414 | T5: ="Profit for "&$A$1&" of "& $C$1&":" -> Profit for Fall of 2025: | V5: =V3-V4 -> 230.53
B6: Cashapp | C6: {=INDEX(IncomeCalcs!$K$2:$O$254,MATCH(DATEVALUE(MATCH(C$2,{"January","February","March","April","May","June","July","August","September","October","November","December"},0) & "/1/" &$C$1),IncomeCalcs!$J$2:$J37,0),MATCH($B6,IncomeCalcs!$K$2:$O$2,0))} -> 0 | D6: {=INDEX(IncomeCalcs!$K$2:$O$254,MATCH(DATEVALUE(MATCH(D$2,{"January","February","March","April","May","June","July","August","September","October","November","December"},0) & "/1/" &$C$1),IncomeCalcs!$J$2:$J37,0),MATCH($B6,IncomeCalcs!$K$2:$O$2,0))} -> 105 | E6: {=INDEX(IncomeCalcs!$K$2:$O$254,MATCH(DATEVALUE(MATCH(E$2,{"January","February","March","April","May","June","July","August","September","October","November","December"},0) & "/1/" &$C$1),IncomeCalcs!$J$2:$J37,0),MATCH($B6,IncomeCalcs!$K$2:$O$2,0))} -> 195 | F6: {=INDEX(IncomeCalcs!$K$2:$O$254,MATCH(DATEVALUE(MATCH(F$2,{"January","February","March","April","May","June","July","August","September","October","November","December"},0) & "/1/" &$C$1),IncomeCalcs!$J$2:$J37,0),MATCH($B6,IncomeCalcs!$K$2:$O$2,0))} -> 0 | G6: {=INDEX(IncomeCalcs!$K$2:$O$254,MATCH(DATEVALUE(MATCH(G$2,{"January","February","March","April","May","June","July","August","September","October","November","December"},0) & "/1/" &$C$1),IncomeCalcs!$J$2:$J37,0),MATCH($B6,IncomeCalcs!$K$2:$O$2,0))} -> 0 | H6: {=INDEX(IncomeCalcs!$K$2:$O$254,MATCH(DATEVALUE(MATCH(H$2,{"January","February","March","April","May","June","July","August","September","October","November","December"},0) & "/1/" &$C$1),IncomeCalcs!$J$2:$J37,0),MATCH($B6,IncomeCalcs!$K$2:$O$2,0))} -> 0 | I6: =SUM(C6:H6) -> 300 | K6: Food | L6: =SUMIFS(Expenses!$F$4:$F37,Expenses!$E$4:$E37,$K6,Expenses!$B$4:$B37,L$2,Expenses!$C$4:$C37,$C$1) -> 74.92 | M6: =SUMIFS(Expenses!$F$4:$F37,Expenses!$E$4:$E37,$K6,Expenses!$B$4:$B37,M$2,Expenses!$C$4:$C37,$C$1) -> 42.2 | N6: =SUMIFS(Expenses!$F$4:$F37,Expenses!$E$4:$E37,$K6,Expenses!$B$4:$B37,N$2,Expenses!$C$4:$C37,$C$1) -> 43.28 | O6: =SUMIFS(Expenses!$F$4:$F37,Expenses!$E$4:$E37,$K6,Expenses!$B$4:$B37,O$2,Expenses!$C$4:$C37,$C$1) -> 89.91 | P6: =SUMIFS(Expenses!$F$4:$F37,Expenses!$E$4:$E37,$K6,Expenses!$B$4:$B37,P$2,Expenses!$C$4:$C37,$C$1) -> 0 | Q6: =SUMIFS(Expenses!$F$4:$F37,Expenses!$E$4:$E37,$K6,Expenses!$B$4:$B37,Q$2,Expenses!$C$4:$C37,$C$1) -> 0 | R6: =SUM(L6:Q6) -> 250.31
B7: Venmo | C7: {=INDEX(IncomeCalcs!$K$2:$O$254,MATCH(DATEVALUE(MATCH(C$2,{"January","February","March","April","May","June","July","August","September","October","November","December"},0) & "/1/" &$C$1),IncomeCalcs!$J$2:$J37,0),MATCH($B7,IncomeCalcs!$K$2:$O$2,0))} -> 0 | D7: {=INDEX(IncomeCalcs!$K$2:$O$254,MATCH(DATEVALUE(MATCH(D$2,{"January","February","March","April","May","June","July","August","September","October","November","December"},0) & "/1/" &$C$1),IncomeCalcs!$J$2:$J37,0),MATCH($B7,IncomeCalcs!$K$2:$O$2,0))} -> 180 | E7: {=INDEX(IncomeCalcs!$K$2:$O$254,MATCH(DATEVALUE(MATCH(E$2,{"January","February","March","April","May","June","July","August","September","October","November","December"},0) & "/1/" &$C$1),IncomeCalcs!$J$2:$J37,0),MATCH($B7,IncomeCalcs!$K$2:$O$2,0))} -> 60 | F7: {=INDEX(IncomeCalcs!$K$2:$O$254,MATCH(DATEVALUE(MATCH(F$2,{"January","February","March","April","May","June","July","August","September","October","November","December"},0) & "/1/" &$C$1),IncomeCalcs!$J$2:$J37,0),MATCH($B7,IncomeCalcs!$K$2:$O$2,0))} -> 0 | G7: {=INDEX(IncomeCalcs!$K$2:$O$254,MATCH(DATEVALUE(MATCH(G$2,{"January","February","March","April","May","June","July","August","September","October","November","December"},0) & "/1/" &$C$1),IncomeCalcs!$J$2:$J37,0),MATCH($B7,IncomeCalcs!$K$2:$O$2,0))} -> 0 | H7: {=INDEX(IncomeCalcs!$K$2:$O$254,MATCH(DATEVALUE(MATCH(H$2,{"January","February","March","April","May","June","July","August","September","October","November","December"},0) & "/1/" &$C$1),IncomeCalcs!$J$2:$J37,0),MATCH($B7,IncomeCalcs!$K$2:$O$2,0))} -> 0 | I7: =SUM(C7:H7) -> 240 | K7: Storage Unit Fee | L7: =SUMIFS(Expenses!$F$4:$F37,Expenses!$E$4:$E37,$K7,Expenses!$B$4:$B37,L$2,Expenses!$C$4:$C37,$C$1) -> 162 | M7: =SUMIFS(Expenses!$F$4:$F37,Expenses!$E$4:$E37,$K7,Expenses!$B$4:$B37,M$2,Expenses!$C$4:$C37,$C$1) -> 54 | N7: =SUMIFS(Expenses!$F$4:$F37,Expenses!$E$4:$E37,$K7,Expenses!$B$4:$B37,N$2,Expenses!$C$4:$C37,$C$1) -> 54 | O7: =SUMIFS(Expenses!$F$4:$F37,Expenses!$E$4:$E37,$K7,Expenses!$B$4:$B37,O$2,Expenses!$C$4:$C37,$C$1) -> 0 | P7: =SUMIFS(Expenses!$F$4:$F37,Expenses!$E$4:$E37,$K7,Expenses!$B$4:$B37,P$2,Expenses!$C$4:$C37,$C$1) -> 0 | Q7: =SUMIFS(Expenses!$F$4:$F37,Expenses!$E$4:$E37,$K7,Expenses!$B$4:$B37,Q$2,Expenses!$C$4:$C37,$C$1) -> 0 | R7: =SUM(L7:Q7) -> 270
B8: Cash | C8: {=INDEX(IncomeCalcs!$K$2:$O$254,MATCH(DATEVALUE(MATCH(C$2,{"January","February","March","April","May","June","July","August","September","October","November","December"},0) & "/1/" &$C$1),IncomeCalcs!$J$2:$J37,0),MATCH($B8,IncomeCalcs!$K$2:$O$2,0))} -> 0 | D8: {=INDEX(IncomeCalcs!$K$2:$O$254,MATCH(DATEVALUE(MATCH(D$2,{"January","February","March","April","May","June","July","August","September","October","November","December"},0) & "/1/" &$C$1),IncomeCalcs!$J$2:$J37,0),MATCH($B8,IncomeCalcs!$K$2:$O$2,0))} -> 105 | E8: {=INDEX(IncomeCalcs!$K$2:$O$254,MATCH(DATEVALUE(MATCH(E$2,{"January","February","March","April","May","June","July","August","September","October","November","December"},0) & "/1/" &$C$1),IncomeCalcs!$J$2:$J37,0),MATCH($B8,IncomeCalcs!$K$2:$O$2,0))} -> 255 | F8: {=INDEX(IncomeCalcs!$K$2:$O$254,MATCH(DATEVALUE(MATCH(F$2,{"January","February","March","April","May","June","July","August","September","October","November","December"},0) & "/1/" &$C$1),IncomeCalcs!$J$2:$J37,0),MATCH($B8,IncomeCalcs!$K$2:$O$2,0))} -> 0 | G8: {=INDEX(IncomeCalcs!$K$2:$O$254,MATCH(DATEVALUE(MATCH(G$2,{"January","February","March","April","May","June","July","August","September","October","November","December"},0) & "/1/" &$C$1),IncomeCalcs!$J$2:$J37,0),MATCH($B8,IncomeCalcs!$K$2:$O$2,0))} -> 0 | H8: {=INDEX(IncomeCalcs!$K$2:$O$254,MATCH(DATEVALUE(MATCH(H$2,{"January","February","March","April","May","June","July","August","September","October","November","December"},0) & "/1/" &$C$1),IncomeCalcs!$J$2:$J37,0),MATCH($B8,IncomeCalcs!$K$2:$O$2,0))} -> 0 | I8: =SUM(C8:H8) -> 360 | K8: Website Fee | L8: =SUMIFS(Expenses!$F$4:$F37,Expenses!$E$4:$E37,$K8,Expenses!$B$4:$B37,L$2,Expenses!$C$4:$C37,$C$1) -> 51.96 | M8: =SUMIFS(Expenses!$F$4:$F37,Expenses!$E$4:$E37,$K8,Expenses!$B$4:$B37,M$2,Expenses!$C$4:$C37,$C$1) -> 74.8 | N8: =SUMIFS(Expenses!$F$4:$F37,Expenses!$E$4:$E37,$K8,Expenses!$B$4:$B37,N$2,Expenses!$C$4:$C37,$C$1) -> 25.98 | O8: =SUMIFS(Expenses!$F$4:$F37,Expenses!$E$4:$E37,$K8,Expenses!$B$4:$B37,O$2,Expenses!$C$4:$C37,$C$1) -> 0 | P8: =SUMIFS(Expenses!$F$4:$F37,Expenses!$E$4:$E37,$K8,Expenses!$B$4:$B37,P$2,Expenses!$C$4:$C37,$C$1) -> 0 | Q8: =SUMIFS(Expenses!$F$4:$F37,Expenses!$E$4:$E37,$K8,Expenses!$B$4:$B37,Q$2,Expenses!$C$4:$C37,$C$1) -> 0 | R8: =SUM(L8:Q8) -> 152.74
B9: Zelle | C9: {=INDEX(IncomeCalcs!$K$2:$O$254,MATCH(DATEVALUE(MATCH(C$2,{"January","February","March","April","May","June","July","August","September","October","November","December"},0) & "/1/" &$C$1),IncomeCalcs!$J$2:$J37,0),MATCH($B9,IncomeCalcs!$K$2:$O$2,0))} -> 0 | D9: {=INDEX(IncomeCalcs!$K$2:$O$254,MATCH(DATEVALUE(MATCH(D$2,{"January","February","March","April","May","June","July","August","September","October","November","December"},0) & "/1/" &$C$1),IncomeCalcs!$J$2:$J37,0),MATCH($B9,IncomeCalcs!$K$2:$O$2,0))} -> 0 | E9: {=INDEX(IncomeCalcs!$K$2:$O$254,MATCH(DATEVALUE(MATCH(E$2,{"January","February","March","April","May","June","July","August","September","October","November","December"},0) & "/1/" &$C$1),IncomeCalcs!$J$2:$J37,0),MATCH($B9,IncomeCalcs!$K$2:$O$2,0))} -> 0 | F9: {=INDEX(IncomeCalcs!$K$2:$O$254,MATCH(DATEVALUE(MATCH(F$2,{"January","February","March","April","May","June","July","August","September","October","November","December"},0) & "/1/" &$C$1),IncomeCalcs!$J$2:$J37,0),MATCH($B9,IncomeCalcs!$K$2:$O$2,0))} -> 0 | G9: {=INDEX(IncomeCalcs!$K$2:$O$254,MATCH(DATEVALUE(MATCH(G$2,{"January","February","March","April","May","June","July","August","September","October","November","December"},0) & "/1/" &$C$1),IncomeCalcs!$J$2:$J37,0),MATCH($B9,IncomeCalcs!$K$2:$O$2,0))} -> 0 | H9: {=INDEX(IncomeCalcs!$K$2:$O$254,MATCH(DATEVALUE(MATCH(H$2,{"January","February","March","April","May","June","July","August","September","October","November","December"},0) & "/1/" &$C$1),IncomeCalcs!$J$2:$J37,0),MATCH($B9,IncomeCalcs!$K$2:$O$2,0))} -> 0 | I9: =SUM(C9:H9) -> 0 | K9: Supplies | L9: =SUMIFS(Expenses!$F$4:$F37,Expenses!$E$4:$E37,$K9,Expenses!$B$4:$B37,L$2,Expenses!$C$4:$C37,$C$1) -> 0 | M9: =SUMIFS(Expenses!$F$4:$F37,Expenses!$E$4:$E37,$K9,Expenses!$B$4:$B37,M$2,Expenses!$C$4:$C37,$C$1) -> 58.44 | N9: =SUMIFS(Expenses!$F$4:$F37,Expenses!$E$4:$E37,$K9,Expenses!$B$4:$B37,N$2,Expenses!$C$4:$C37,$C$1) -> 142.25 | O9: =SUMIFS(Expenses!$F$4:$F37,Expenses!$E$4:$E37,$K9,Expenses!$B$4:$B37,O$2,Expenses!$C$4:$C37,$C$1) -> 0 | P9: =SUMIFS(Expenses!$F$4:$F37,Expenses!$E$4:$E37,$K9,Expenses!$B$4:$B37,P$2,Expenses!$C$4:$C37,$C$1) -> 0 | Q9: =SUMIFS(Expenses!$F$4:$F37,Expenses!$E$4:$E37,$K9,Expenses!$B$4:$B37,Q$2,Expenses!$C$4:$C37,$C$1) -> 0 | R9: =SUM(L9:Q9) -> 200.69
A10: Food/goods Fundraisers | B10: Monthly totals: | C10: =sum(C$11:C$16) -> 0 | D10: =sum(D$11:D$16) -> 258 | E10: =sum(E$11:E$16) -> 106 | F10: =sum(F$11:F$16) -> 0 | G10: =sum(G$11:G$16) -> 0 | H10: =sum(H$11:H$16) -> 0 | I10: =SUM(C10:H10) -> 364 | K10: Misc/Reimbursement | L10: =SUMIFS(Expenses!$F$4:$F37,Expenses!$E$4:$E37,$K10,Expenses!$B$4:$B37,L$2,Expenses!$C$4:$C37,$C$1) -> 40.43 | M10: =SUMIFS(Expenses!$F$4:$F37,Expenses!$E$4:$E37,$K10,Expenses!$B$4:$B37,M$2,Expenses!$C$4:$C37,$C$1) -> 47.62 | N10: =SUMIFS(Expenses!$F$4:$F37,Expenses!$E$4:$E37,$K10,Expenses!$B$4:$B37,N$2,Expenses!$C$4:$C37,$C$1) -> 7.52 | O10: =SUMIFS(Expenses!$F$4:$F37,Expenses!$E$4:$E37,$K10,Expenses!$B$4:$B37,O$2,Expenses!$C$4:$C37,$C$1) -> 30.88 | P10: =SUMIFS(Expenses!$F$4:$F37,Expenses!$E$4:$E37,$K10,Expenses!$B$4:$B37,P$2,Expenses!$C$4:$C37,$C$1) -> 0 | Q10: =SUMIFS(Expenses!$F$4:$F37,Expenses!$E$4:$E37,$K10,Expenses!$B$4:$B37,Q$2,Expenses!$C$4:$C37,$C$1) -> 0 | R10: =SUM(L10:Q10) -> 126.45
B11: Paypal | C11: {=INDEX(IncomeCalcs!$X$2:$AC$254,MATCH(DATEVALUE(MATCH(C$2,{"January","February","March","April","May","June","July","August","September","October","November","December"},0) & "/1/" &$C$1),IncomeCalcs!$W$2:$W37,0),MATCH($B11,IncomeCalcs!$X$2:$AC$2,0))} -> 0 | D11: {=INDEX(IncomeCalcs!$X$2:$AC$254,MATCH(DATEVALUE(MATCH(D$2,{"January","February","March","April","May","June","July","August","September","October","November","December"},0) & "/1/" &$C$1),IncomeCalcs!$W$2:$W37,0),MATCH($B11,IncomeCalcs!$X$2:$AC$2,0))} -> 10 | E11: {=INDEX(IncomeCalcs!$X$2:$AC$254,MATCH(DATEVALUE(MATCH(E$2,{"January","February","March","April","May","June","July","August","September","October","November","December"},0) & "/1/" &$C$1),IncomeCalcs!$W$2:$W37,0),MATCH($B11,IncomeCalcs!$X$2:$AC$2,0))} -> 0 | F11: {=INDEX(IncomeCalcs!$X$2:$AC$254,MATCH(DATEVALUE(MATCH(F$2,{"January","February","March","April","May","June","July","August","September","October","November","December"},0) & "/1/" &$C$1),IncomeCalcs!$W$2:$W37,0),MATCH($B11,IncomeCalcs!$X$2:$AC$2,0))} -> 0 | G11: {=INDEX(IncomeCalcs!$X$2:$AC$254,MATCH(DATEVALUE(MATCH(G$2,{"January","February","March","April","May","June","July","August","September","October","November","December"},0) & "/1/" &$C$1),IncomeCalcs!$W$2:$W37,0),MATCH($B11,IncomeCalcs!$X$2:$AC$2,0))} -> 0 | H11: {=INDEX(IncomeCalcs!$X$2:$AC$254,MATCH(DATEVALUE(MATCH(H$2,{"January","February","March","April","May","June","July","August","September","October","November","December"},0) & "/1/" &$C$1),IncomeCalcs!$W$2:$W37,0),MATCH($B11,IncomeCalcs!$X$2:$AC$2,0))} -> 0 | I11: =SUM(C11:H11) -> 10
B12: Cashapp | C12: {=INDEX(IncomeCalcs!$X$2:$AC$254,MATCH(DATEVALUE(MATCH(C$2,{"January","February","March","April","May","June","July","August","September","October","November","December"},0) & "/1/" &$C$1),IncomeCalcs!$W$2:$W37,0),MATCH($B12,IncomeCalcs!$X$2:$AC$2,0))} -> 0 | D12: {=INDEX(IncomeCalcs!$X$2:$AC$254,MATCH(DATEVALUE(MATCH(D$2,{"January","February","March","April","May","June","July","August","September","October","November","December"},0) & "/1/" &$C$1),IncomeCalcs!$W$2:$W37,0),MATCH($B12,IncomeCalcs!$X$2:$AC$2,0))} -> 53 | E12: {=INDEX(IncomeCalcs!$X$2:$AC$254,MATCH(DATEVALUE(MATCH(E$2,{"January","February","March","April","May","June","July","August","September","October","November","December"},0) & "/1/" &$C$1),IncomeCalcs!$W$2:$W37,0),MATCH($B12,IncomeCalcs!$X$2:$AC$2,0))} -> 75 | F12: {=INDEX(IncomeCalcs!$X$2:$AC$254,MATCH(DATEVALUE(MATCH(F$2,{"January","February","March","April","May","June","July","August","September","October","November","December"},0) & "/1/" &$C$1),IncomeCalcs!$W$2:$W37,0),MATCH($B12,IncomeCalcs!$X$2:$AC$2,0))} -> 0 | G12: {=INDEX(IncomeCalcs!$X$2:$AC$254,MATCH(DATEVALUE(MATCH(G$2,{"January","February","March","April","May","June","July","August","September","October","November","December"},0) & "/1/" &$C$1),IncomeCalcs!$W$2:$W37,0),MATCH($B12,IncomeCalcs!$X$2:$AC$2,0))} -> 0 | H12: {=INDEX(IncomeCalcs!$X$2:$AC$254,MATCH(DATEVALUE(MATCH(H$2,{"January","February","March","April","May","June","July","August","September","October","November","December"},0) & "/1/" &$C$1),IncomeCalcs!$W$2:$W37,0),MATCH($B12,IncomeCalcs!$X$2:$AC$2,0))} -> 0 | I12: =SUM(C12:H12) -> 128
B13: Venmo | C13: {=INDEX(IncomeCalcs!$X$2:$AC$254,MATCH(DATEVALUE(MATCH(C$2,{"January","February","March","April","May","June","July","August","September","October","November","December"},0) & "/1/" &$C$1),IncomeCalcs!$W$2:$W37,0),MATCH($B13,IncomeCalcs!$X$2:$AC$2,0))} -> 0 | D13: {=INDEX(IncomeCalcs!$X$2:$AC$254,MATCH(DATEVALUE(MATCH(D$2,{"January","February","March","April","May","June","July","August","September","October","November","December"},0) & "/1/" &$C$1),IncomeCalcs!$W$2:$W37,0),MATCH($B13,IncomeCalcs!$X$2:$AC$2,0))} -> 195 | E13: {=INDEX(IncomeCalcs!$X$2:$AC$254,MATCH(DATEVALUE(MATCH(E$2,{"January","February","March","April","May","June","July","August","September","October","November","December"},0) & "/1/" &$C$1),IncomeCalcs!$W$2:$W37,0),MATCH($B13,IncomeCalcs!$X$2:$AC$2,0))} -> 31 | F13: {=INDEX(IncomeCalcs!$X$2:$AC$254,MATCH(DATEVALUE(MATCH(F$2,{"January","February","March","April","May","June","July","August","September","October","November","December"},0) & "/1/" &$C$1),IncomeCalcs!$W$2:$W37,0),MATCH($B13,IncomeCalcs!$X$2:$AC$2,0))} -> 0 | G13: {=INDEX(IncomeCalcs!$X$2:$AC$254,MATCH(DATEVALUE(MATCH(G$2,{"January","February","March","April","May","June","July","August","September","October","November","December"},0) & "/1/" &$C$1),IncomeCalcs!$W$2:$W37,0),MATCH($B13,IncomeCalcs!$X$2:$AC$2,0))} -> 0 | H13: {=INDEX(IncomeCalcs!$X$2:$AC$254,MATCH(DATEVALUE(MATCH(H$2,{"January","February","March","April","May","June","July","August","September","October","November","December"},0) & "/1/" &$C$1),IncomeCalcs!$W$2:$W37,0),MATCH($B13,IncomeCalcs!$X$2:$AC$2,0))} -> 0 | I13: =SUM(C13:H13) -> 226
B14: Cash | C14: {=INDEX(IncomeCalcs!$X$2:$AC$254,MATCH(DATEVALUE(MATCH(C$2,{"January","February","March","April","May","June","July","August","September","October","November","December"},0) & "/1/" &$C$1),IncomeCalcs!$W$2:$W37,0),MATCH($B14,IncomeCalcs!$X$2:$AC$2,0))} -> 0 | D14: {=INDEX(IncomeCalcs!$X$2:$AC$254,MATCH(DATEVALUE(MATCH(D$2,{"January","February","March","April","May","June","July","August","September","October","November","December"},0) & "/1/" &$C$1),IncomeCalcs!$W$2:$W37,0),MATCH($B14,IncomeCalcs!$X$2:$AC$2,0))} -> 0 | E14: {=INDEX(IncomeCalcs!$X$2:$AC$254,MATCH(DATEVALUE(MATCH(E$2,{"January","February","March","April","May","June","July","August","September","October","November","December"},0) & "/1/" &$C$1),IncomeCalcs!$W$2:$W37,0),MATCH($B14,IncomeCalcs!$X$2:$AC$2,0))} -> 0 | F14: {=INDEX(IncomeCalcs!$X$2:$AC$254,MATCH(DATEVALUE(MATCH(F$2,{"January","February","March","April","May","June","July","August","September","October","November","December"},0) & "/1/" &$C$1),IncomeCalcs!$W$2:$W37,0),MATCH($B14,IncomeCalcs!$X$2:$AC$2,0))} -> 0 | G14: {=INDEX(IncomeCalcs!$X$2:$AC$254,MATCH(DATEVALUE(MATCH(G$2,{"January","February","March","April","May","June","July","August","September","October","November","December"},0) & "/1/" &$C$1),IncomeCalcs!$W$2:$W37,0),MATCH($B14,IncomeCalcs!$X$2:$AC$2,0))} -> 0 | H14: {=INDEX(IncomeCalcs!$X$2:$AC$254,MATCH(DATEVALUE(MATCH(H$2,{"January","February","March","April","May","June","July","August","September","October","November","December"},0) & "/1/" &$C$1),IncomeCalcs!$W$2:$W37,0),MATCH($B14,IncomeCalcs!$X$2:$AC$2,0))} -> 0 | I14: =SUM(C14:H14) -> 0
B15: Zelle | C15: {=INDEX(IncomeCalcs!$X$2:$AC$254,MATCH(DATEVALUE(MATCH(C$2,{"January","February","March","April","May","June","July","August","September","October","November","December"},0) & "/1/" &$C$1),IncomeCalcs!$W$2:$W37,0),MATCH($B15,IncomeCalcs!$X$2:$AC$2,0))} -> 0 | D15: {=INDEX(IncomeCalcs!$X$2:$AC$254,MATCH(DATEVALUE(MATCH(D$2,{"January","February","March","April","May","June","July","August","September","October","November","December"},0) & "/1/" &$C$1),IncomeCalcs!$W$2:$W37,0),MATCH($B15,IncomeCalcs!$X$2:$AC$2,0))} -> 0 | E15: {=INDEX(IncomeCalcs!$X$2:$AC$254,MATCH(DATEVALUE(MATCH(E$2,{"January","February","March","April","May","June","July","August","September","October","November","December"},0) & "/1/" &$C$1),IncomeCalcs!$W$2:$W37,0),MATCH($B15,IncomeCalcs!$X$2:$AC$2,0))} -> 0 | F15: {=INDEX(IncomeCalcs!$X$2:$AC$254,MATCH(DATEVALUE(MATCH(F$2,{"January","February","March","April","May","June","July","August","September","October","November","December"},0) & "/1/" &$C$1),IncomeCalcs!$W$2:$W37,0),MATCH($B15,IncomeCalcs!$X$2:$AC$2,0))} -> 0 | G15: {=INDEX(IncomeCalcs!$X$2:$AC$254,MATCH(DATEVALUE(MATCH(G$2,{"January","February","March","April","May","June","July","August","September","October","November","December"},0) & "/1/" &$C$1),IncomeCalcs!$W$2:$W37,0),MATCH($B15,IncomeCalcs!$X$2:$AC$2,0))} -> 0 | H15: {=INDEX(IncomeCalcs!$X$2:$AC$254,MATCH(DATEVALUE(MATCH(H$2,{"January","February","March","April","May","June","July","August","September","October","November","December"},0) & "/1/" &$C$1),IncomeCalcs!$W$2:$W37,0),MATCH($B15,IncomeCalcs!$X$2:$AC$2,0))} -> 0 | I15: =SUM(C15:H15) -> 0
B16: GoFundMe | C16: {=INDEX(IncomeCalcs!$X$2:$AC$254,MATCH(DATEVALUE(MATCH(C$2,{"January","February","March","April","May","June","July","August","September","October","November","December"},0) & "/1/" &$C$1),IncomeCalcs!$W$2:$W37,0),MATCH($B16,IncomeCalcs!$X$2:$AC$2,0))} -> 0 | D16: {=INDEX(IncomeCalcs!$X$2:$AC$254,MATCH(DATEVALUE(MATCH(D$2,{"January","February","March","April","May","June","July","August","September","October","November","December"},0) & "/1/" &$C$1),IncomeCalcs!$W$2:$W37,0),MATCH($B16,IncomeCalcs!$X$2:$AC$2,0))} -> 0 | E16: {=INDEX(IncomeCalcs!$X$2:$AC$254,MATCH(DATEVALUE(MATCH(E$2,{"January","February","March","April","May","June","July","August","September","October","November","December"},0) & "/1/" &$C$1),IncomeCalcs!$W$2:$W37,0),MATCH($B16,IncomeCalcs!$X$2:$AC$2,0))} -> 0 | F16: {=INDEX(IncomeCalcs!$X$2:$AC$254,MATCH(DATEVALUE(MATCH(F$2,{"January","February","March","April","May","June","July","August","September","October","November","December"},0) & "/1/" &$C$1),IncomeCalcs!$W$2:$W37,0),MATCH($B16,IncomeCalcs!$X$2:$AC$2,0))} -> 0 | G16: {=INDEX(IncomeCalcs!$X$2:$AC$254,MATCH(DATEVALUE(MATCH(G$2,{"January","February","March","April","May","June","July","August","September","October","November","December"},0) & "/1/" &$C$1),IncomeCalcs!$W$2:$W37,0),MATCH($B16,IncomeCalcs!$X$2:$AC$2,0))} -> 0 | H16: {=INDEX(IncomeCalcs!$X$2:$AC$254,MATCH(DATEVALUE(MATCH(H$2,{"January","February","March","April","May","June","July","August","September","October","November","December"},0) & "/1/" &$C$1),IncomeCalcs!$W$2:$W37,0),MATCH($B16,IncomeCalcs!$X$2:$AC$2,0))} -> 0 | I16: =SUM(C16:H16) -> 0
A17: Other Fundraisers | B17: Monthly totals: | C17: =sum(C$18:C$23) -> 0 | D17: =sum(D$18:D$23) -> 0 | E17: =sum(E$18:E$23) -> 0 | F17: =sum(F$18:F$23) -> 3 | G17: =sum(G$18:G$23) -> 0 | H17: =sum(H$18:H$23) -> 0 | I17: =SUM(C17:H17) -> 3
B18: Paypal | C18: {=INDEX(IncomeCalcs!$AF$2:$AK$254,MATCH(DATEVALUE(MATCH(C$2,{"January","February","March","April","May","June","July","August","September","October","November","December"},0) & "/1/" &$C$1),IncomeCalcs!$AE$2:$AE37,0),MATCH($B18,IncomeCalcs!$AF$2:$AK$2,0))} -> 0 | D18: {=INDEX(IncomeCalcs!$AF$2:$AK$254,MATCH(DATEVALUE(MATCH(D$2,{"January","February","March","April","May","June","July","August","September","October","November","December"},0) & "/1/" &$C$1),IncomeCalcs!$AE$2:$AE37,0),MATCH($B18,IncomeCalcs!$AF$2:$AK$2,0))} -> 0 | E18: {=INDEX(IncomeCalcs!$AF$2:$AK$254,MATCH(DATEVALUE(MATCH(E$2,{"January","February","March","April","May","June","July","August","September","October","November","December"},0) & "/1/" &$C$1),IncomeCalcs!$AE$2:$AE37,0),MATCH($B18,IncomeCalcs!$AF$2:$AK$2,0))} -> 0 | F18: {=INDEX(IncomeCalcs!$AF$2:$AK$254,MATCH(DATEVALUE(MATCH(F$2,{"January","February","March","April","May","June","July","August","September","October","November","December"},0) & "/1/" &$C$1),IncomeCalcs!$AE$2:$AE37,0),MATCH($B18,IncomeCalcs!$AF$2:$AK$2,0))} -> 0 | G18: {=INDEX(IncomeCalcs!$AF$2:$AK$254,MATCH(DATEVALUE(MATCH(G$2,{"January","February","March","April","May","June","July","August","September","October","November","December"},0) & "/1/" &$C$1),IncomeCalcs!$AE$2:$AE37,0),MATCH($B18,IncomeCalcs!$AF$2:$AK$2,0))} -> 0 | H18: {=INDEX(IncomeCalcs!$AF$2:$AK$254,MATCH(DATEVALUE(MATCH(H$2,{"January","February","March","April","May","June","July","August","September","October","November","December"},0) & "/1/" &$C$1),IncomeCalcs!$AE$2:$AE37,0),MATCH($B18,IncomeCalcs!$AF$2:$AK$2,0))} -> 0 | I18: =SUM(C18:H18) -> 0
B19: Cashapp | C19: {=INDEX(IncomeCalcs!$AF$2:$AK$254,MATCH(DATEVALUE(MATCH(C$2,{"January","February","March","April","May","June","July","August","September","October","November","December"},0) & "/1/" &$C$1),IncomeCalcs!$AE$2:$AE37,0),MATCH($B19,IncomeCalcs!$AF$2:$AK$2,0))} -> 0 | D19: {=INDEX(IncomeCalcs!$AF$2:$AK$254,MATCH(DATEVALUE(MATCH(D$2,{"January","February","March","April","May","June","July","August","September","October","November","December"},0) & "/1/" &$C$1),IncomeCalcs!$AE$2:$AE37,0),MATCH($B19,IncomeCalcs!$AF$2:$AK$2,0))} -> 0 | E19: {=INDEX(IncomeCalcs!$AF$2:$AK$254,MATCH(DATEVALUE(MATCH(E$2,{"January","February","March","April","May","June","July","August","September","October","November","December"},0) & "/1/" &$C$1),IncomeCalcs!$AE$2:$AE37,0),MATCH($B19,IncomeCalcs!$AF$2:$AK$2,0))} -> 0 | F19: {=INDEX(IncomeCalcs!$AF$2:$AK$254,MATCH(DATEVALUE(MATCH(F$2,{"January","February","March","April","May","June","July","August","September","October","November","December"},0) & "/1/" &$C$1),IncomeCalcs!$AE$2:$AE37,0),MATCH($B19,IncomeCalcs!$AF$2:$AK$2,0))} -> 0 | G19: {=INDEX(IncomeCalcs!$AF$2:$AK$254,MATCH(DATEVALUE(MATCH(G$2,{"January","February","March","April","May","June","July","August","September","October","November","December"},0) & "/1/" &$C$1),IncomeCalcs!$AE$2:$AE37,0),MATCH($B19,IncomeCalcs!$AF$2:$AK$2,0))} -> 0 | H19: {=INDEX(IncomeCalcs!$AF$2:$AK$254,MATCH(DATEVALUE(MATCH(H$2,{"January","February","March","April","May","June","July","August","September","October","November","December"},0) & "/1/" &$C$1),IncomeCalcs!$AE$2:$AE37,0),MATCH($B19,IncomeCalcs!$AF$2:$AK$2,0))} -> 0 | I19: =SUM(C19:H19) -> 0
B20: Venmo | C20: {=INDEX(IncomeCalcs!$AF$2:$AK$254,MATCH(DATEVALUE(MATCH(C$2,{"January","February","March","April","May","June","July","August","September","October","November","December"},0) & "/1/" &$C$1),IncomeCalcs!$AE$2:$AE37,0),MATCH($B20,IncomeCalcs!$AF$2:$AK$2,0))} -> 0 | D20: {=INDEX(IncomeCalcs!$AF$2:$AK$254,MATCH(DATEVALUE(MATCH(D$2,{"January","February","March","April","May","June","July","August","September","October","November","December"},0) & "/1/" &$C$1),IncomeCalcs!$AE$2:$AE37,0),MATCH($B20,IncomeCalcs!$AF$2:$AK$2,0))} -> 0 | E20: {=INDEX(IncomeCalcs!$AF$2:$AK$254,MATCH(DATEVALUE(MATCH(E$2,{"January","February","March","April","May","June","July","August","September","October","November","December"},0) & "/1/" &$C$1),IncomeCalcs!$AE$2:$AE37,0),MATCH($B20,IncomeCalcs!$AF$2:$AK$2,0))} -> 0 | F20: {=INDEX(IncomeCalcs!$AF$2:$AK$254,MATCH(DATEVALUE(MATCH(F$2,{"January","February","March","April","May","June","July","August","September","October","November","December"},0) & "/1/" &$C$1),IncomeCalcs!$AE$2:$AE37,0),MATCH($B20,IncomeCalcs!$AF$2:$AK$2,0))} -> 3 | G20: {=INDEX(IncomeCalcs!$AF$2:$AK$254,MATCH(DATEVALUE(MATCH(G$2,{"January","February","March","April","May","June","July","August","September","October","November","December"},0) & "/1/" &$C$1),IncomeCalcs!$AE$2:$AE37,0),MATCH($B20,IncomeCalcs!$AF$2:$AK$2,0))} -> 0 | H20: {=INDEX(IncomeCalcs!$AF$2:$AK$254,MATCH(DATEVALUE(MATCH(H$2,{"January","February","March","April","May","June","July","August","September","October","November","December"},0) & "/1/" &$C$1),IncomeCalcs!$AE$2:$AE37,0),MATCH($B20,IncomeCalcs!$AF$2:$AK$2,0))} -> 0 | I20: =SUM(C20:H20) -> 3
B21: Cash | C21: {=INDEX(IncomeCalcs!$AF$2:$AK$254,MATCH(DATEVALUE(MATCH(C$2,{"January","February","March","April","May","June","July","August","September","October","November","December"},0) & "/1/" &$C$1),IncomeCalcs!$AE$2:$AE37,0),MATCH($B21,IncomeCalcs!$AF$2:$AK$2,0))} -> 0 | D21: {=INDEX(IncomeCalcs!$AF$2:$AK$254,MATCH(DATEVALUE(MATCH(D$2,{"January","February","March","April","May","June","July","August","September","October","November","December"},0) & "/1/" &$C$1),IncomeCalcs!$AE$2:$AE37,0),MATCH($B21,IncomeCalcs!$AF$2:$AK$2,0))} -> 0 | E21: {=INDEX(IncomeCalcs!$AF$2:$AK$254,MATCH(DATEVALUE(MATCH(E$2,{"January","February","March","April","May","June","July","August","September","October","November","December"},0) & "/1/" &$C$1),IncomeCalcs!$AE$2:$AE37,0),MATCH($B21,IncomeCalcs!$AF$2:$AK$2,0))} -> 0 | F21: {=INDEX(IncomeCalcs!$AF$2:$AK$254,MATCH(DATEVALUE(MATCH(F$2,{"January","February","March","April","May","June","July","August","September","October","November","December"},0) & "/1/" &$C$1),IncomeCalcs!$AE$2:$AE37,0),MATCH($B21,IncomeCalcs!$AF$2:$AK$2,0))} -> 0 | G21: {=INDEX(IncomeCalcs!$AF$2:$AK$254,MATCH(DATEVALUE(MATCH(G$2,{"January","February","March","April","May","June","July","August","September","October","November","December"},0) & "/1/" &$C$1),IncomeCalcs!$AE$2:$AE37,0),MATCH($B21,IncomeCalcs!$AF$2:$AK$2,0))} -> 0 | H21: {=INDEX(IncomeCalcs!$AF$2:$AK$254,MATCH(DATEVALUE(MATCH(H$2,{"January","February","March","April","May","June","July","August","September","October","November","December"},0) & "/1/" &$C$1),IncomeCalcs!$AE$2:$AE37,0),MATCH($B21,IncomeCalcs!$AF$2:$AK$2,0))} -> 0 | I21: =SUM(C21:H21) -> 0
B22: Zelle | C22: {=INDEX(IncomeCalcs!$AF$2:$AK$254,MATCH(DATEVALUE(MATCH(C$2,{"January","February","March","April","May","June","July","August","September","October","November","December"},0) & "/1/" &$C$1),IncomeCalcs!$AE$2:$AE37,0),MATCH($B22,IncomeCalcs!$AF$2:$AK$2,0))} -> 0 | D22: {=INDEX(IncomeCalcs!$AF$2:$AK$254,MATCH(DATEVALUE(MATCH(D$2,{"January","February","March","April","May","June","July","August","September","October","November","December"},0) & "/1/" &$C$1),IncomeCalcs!$AE$2:$AE37,0),MATCH($B22,IncomeCalcs!$AF$2:$AK$2,0))} -> 0 | E22: {=INDEX(IncomeCalcs!$AF$2:$AK$254,MATCH(DATEVALUE(MATCH(E$2,{"January","February","March","April","May","June","July","August","September","October","November","December"},0) & "/1/" &$C$1),IncomeCalcs!$AE$2:$AE37,0),MATCH($B22,IncomeCalcs!$AF$2:$AK$2,0))} -> 0 | F22: {=INDEX(IncomeCalcs!$AF$2:$AK$254,MATCH(DATEVALUE(MATCH(F$2,{"January","February","March","April","May","June","July","August","September","October","November","December"},0) & "/1/" &$C$1),IncomeCalcs!$AE$2:$AE37,0),MATCH($B22,IncomeCalcs!$AF$2:$AK$2,0))} -> 0 | G22: {=INDEX(IncomeCalcs!$AF$2:$AK$254,MATCH(DATEVALUE(MATCH(G$2,{"January","February","March","April","May","June","July","August","September","October","November","December"},0) & "/1/" &$C$1),IncomeCalcs!$AE$2:$AE37,0),MATCH($B22,IncomeCalcs!$AF$2:$AK$2,0))} -> 0 | H22: {=INDEX(IncomeCalcs!$AF$2:$AK$254,MATCH(DATEVALUE(MATCH(H$2,{"January","February","March","April","May","June","July","August","September","October","November","December"},0) & "/1/" &$C$1),IncomeCalcs!$AE$2:$AE37,0),MATCH($B22,IncomeCalcs!$AF$2:$AK$2,0))} -> 0 | I22: =SUM(C22:H22) -> 0
B23: GoFundMe | C23: {=INDEX(IncomeCalcs!$AF$2:$AK$254,MATCH(DATEVALUE(MATCH(C$2,{"January","February","March","April","May","June","July","August","September","October","November","December"},0) & "/1/" &$C$1),IncomeCalcs!$AE$2:$AE37,0),MATCH($B23,IncomeCalcs!$AF$2:$AK$2,0))} -> 0 | D23: {=INDEX(IncomeCalcs!$AF$2:$AK$254,MATCH(DATEVALUE(MATCH(D$2,{"January","February","March","April","May","June","July","August","September","October","November","December"},0) & "/1/" &$C$1),IncomeCalcs!$AE$2:$AE37,0),MATCH($B23,IncomeCalcs!$AF$2:$AK$2,0))} -> 0 | E23: {=INDEX(IncomeCalcs!$AF$2:$AK$254,MATCH(DATEVALUE(MATCH(E$2,{"January","February","March","April","May","June","July","August","September","October","November","December"},0) & "/1/" &$C$1),IncomeCalcs!$AE$2:$AE37,0),MATCH($B23,IncomeCalcs!$AF$2:$AK$2,0))} -> 0 | F23: {=INDEX(IncomeCalcs!$AF$2:$AK$254,MATCH(DATEVALUE(MATCH(F$2,{"January","February","March","April","May","June","July","August","September","October","November","December"},0) & "/1/" &$C$1),IncomeCalcs!$AE$2:$AE37,0),MATCH($B23,IncomeCalcs!$AF$2:$AK$2,0))} -> 0 | G23: {=INDEX(IncomeCalcs!$AF$2:$AK$254,MATCH(DATEVALUE(MATCH(G$2,{"January","February","March","April","May","June","July","August","September","October","November","December"},0) & "/1/" &$C$1),IncomeCalcs!$AE$2:$AE37,0),MATCH($B23,IncomeCalcs!$AF$2:$AK$2,0))} -> 0 | H23: {=INDEX(IncomeCalcs!$AF$2:$AK$254,MATCH(DATEVALUE(MATCH(H$2,{"January","February","March","April","May","June","July","August","September","October","November","December"},0) & "/1/" &$C$1),IncomeCalcs!$AE$2:$AE37,0),MATCH($B23,IncomeCalcs!$AF$2:$AK$2,0))} -> 0 | I23: =SUM(C23:H23) -> 0
A24: Donations | B24: Monthly totals: | C24: =sum(C$25:C$30) -> 0 | D24: =sum(D$25:D$30) -> 76.77 | E24: =sum(E$25:E$30) -> 41.13 | F24: =sum(F$25:F$30) -> 54.82 | G24: =sum(G$25:G$30) -> 0 | H24: =sum(H$25:H$30) -> 0 | I24: =SUM(C24:H24) -> 172.72
B25: Paypal | C25: {=INDEX(IncomeCalcs!$AN$2:$AS$254,MATCH(DATEVALUE(MATCH(C$2,{"January","February","March","April","May","June","July","August","September","October","November","December"},0) & "/1/" &$C$1),IncomeCalcs!$AM$2:$AM37,0),MATCH($B11,IncomeCalcs!$AN$2:$AS$2,0))} -> 0 | D25: {=INDEX(IncomeCalcs!$AN$2:$AS$254,MATCH(DATEVALUE(MATCH(D$2,{"January","February","March","April","May","June","July","August","September","October","November","December"},0) & "/1/" &$C$1),IncomeCalcs!$AM$2:$AM37,0),MATCH($B11,IncomeCalcs!$AN$2:$AS$2,0))} -> 61.77 | E25: {=INDEX(IncomeCalcs!$AN$2:$AS$254,MATCH(DATEVALUE(MATCH(E$2,{"January","February","March","April","May","June","July","August","September","October","November","December"},0) & "/1/" &$C$1),IncomeCalcs!$AM$2:$AM37,0),MATCH($B11,IncomeCalcs!$AN$2:$AS$2,0))} -> 38.13 | F25: {=INDEX(IncomeCalcs!$AN$2:$AS$254,MATCH(DATEVALUE(MATCH(F$2,{"January","February","March","April","May","June","July","August","September","October","November","December"},0) & "/1/" &$C$1),IncomeCalcs!$AM$2:$AM37,0),MATCH($B11,IncomeCalcs!$AN$2:$AS$2,0))} -> 5.82 | G25: {=INDEX(IncomeCalcs!$AN$2:$AS$254,MATCH(DATEVALUE(MATCH(G$2,{"January","February","March","April","May","June","July","August","September","October","November","December"},0) & "/1/" &$C$1),IncomeCalcs!$AM$2:$AM37,0),MATCH($B11,IncomeCalcs!$AN$2:$AS$2,0))} -> 0 | H25: {=INDEX(IncomeCalcs!$AN$2:$AS$254,MATCH(DATEVALUE(MATCH(H$2,{"January","February","March","April","May","June","July","August","September","October","November","December"},0) & "/1/" &$C$1),IncomeCalcs!$AM$2:$AM37,0),MATCH($B11,IncomeCalcs!$AN$2:$AS$2,0))} -> 0 | I25: =SUM(C25:H25) -> 105.72
B26: Cashapp | C26: {=INDEX(IncomeCalcs!$AN$2:$AS$254,MATCH(DATEVALUE(MATCH(C$2,{"January","February","March","April","May","June","July","August","September","October","November","December"},0) & "/1/" &$C$1),IncomeCalcs!$AM$2:$AM37,0),MATCH($B12,IncomeCalcs!$AN$2:$AS$2,0))} -> 0 | D26: {=INDEX(IncomeCalcs!$AN$2:$AS$254,MATCH(DATEVALUE(MATCH(D$2,{"January","February","March","April","May","June","July","August","September","October","November","December"},0) & "/1/" &$C$1),IncomeCalcs!$AM$2:$AM37,0),MATCH($B12,IncomeCalcs!$AN$2:$AS$2,0))} -> 10 | E26: {=INDEX(IncomeCalcs!$AN$2:$AS$254,MATCH(DATEVALUE(MATCH(E$2,{"January","February","March","April","May","June","July","August","September","October","November","December"},0) & "/1/" &$C$1),IncomeCalcs!$AM$2:$AM37,0),MATCH($B12,IncomeCalcs!$AN$2:$AS$2,0))} -> 3 | F26: {=INDEX(IncomeCalcs!$AN$2:$AS$254,MATCH(DATEVALUE(MATCH(F$2,{"January","February","March","April","May","June","July","August","September","October","November","December"},0) & "/1/" &$C$1),IncomeCalcs!$AM$2:$AM37,0),MATCH($B12,IncomeCalcs!$AN$2:$AS$2,0))} -> 0 | G26: {=INDEX(IncomeCalcs!$AN$2:$AS$254,MATCH(DATEVALUE(MATCH(G$2,{"January","February","March","April","May","June","July","August","September","October","November","December"},0) & "/1/" &$C$1),IncomeCalcs!$AM$2:$AM37,0),MATCH($B12,IncomeCalcs!$AN$2:$AS$2,0))} -> 0 | H26: {=INDEX(IncomeCalcs!$AN$2:$AS$254,MATCH(DATEVALUE(MATCH(H$2,{"January","February","March","April","May","June","July","August","September","October","November","December"},0) & "/1/" &$C$1),IncomeCalcs!$AM$2:$AM37,0),MATCH($B12,IncomeCalcs!$AN$2:$AS$2,0))} -> 0 | I26: =SUM(C26:H26) -> 13
B27: Venmo | C27: {=INDEX(IncomeCalcs!$AN$2:$AS$254,MATCH(DATEVALUE(MATCH(C$2,{"January","February","March","April","May","June","July","August","September","October","November","December"},0) & "/1/" &$C$1),IncomeCalcs!$AM$2:$AM37,0),MATCH($B13,IncomeCalcs!$AN$2:$AS$2,0))} -> 0 | D27: {=INDEX(IncomeCalcs!$AN$2:$AS$254,MATCH(DATEVALUE(MATCH(D$2,{"January","February","March","April","May","June","July","August","September","October","November","December"},0) & "/1/" &$C$1),IncomeCalcs!$AM$2:$AM37,0),MATCH($B13,IncomeCalcs!$AN$2:$AS$2,0))} -> 5 | E27: {=INDEX(IncomeCalcs!$AN$2:$AS$254,MATCH(DATEVALUE(MATCH(E$2,{"January","February","March","April","May","June","July","August","September","October","November","December"},0) & "/1/" &$C$1),IncomeCalcs!$AM$2:$AM37,0),MATCH($B13,IncomeCalcs!$AN$2:$AS$2,0))} -> 0 | F27: {=INDEX(IncomeCalcs!$AN$2:$AS$254,MATCH(DATEVALUE(MATCH(F$2,{"January","February","March","April","May","June","July","August","September","October","November","December"},0) & "/1/" &$C$1),IncomeCalcs!$AM$2:$AM37,0),MATCH($B13,IncomeCalcs!$AN$2:$AS$2,0))} -> 49 | G27: {=INDEX(IncomeCalcs!$AN$2:$AS$254,MATCH(DATEVALUE(MATCH(G$2,{"January","February","March","April","May","June","July","August","September","October","November","December"},0) & "/1/" &$C$1),IncomeCalcs!$AM$2:$AM37,0),MATCH($B13,IncomeCalcs!$AN$2:$AS$2,0))} -> 0 | H27: {=INDEX(IncomeCalcs!$AN$2:$AS$254,MATCH(DATEVALUE(MATCH(H$2,{"January","February","March","April","May","June","July","August","September","October","November","December"},0) & "/1/" &$C$1),IncomeCalcs!$AM$2:$AM37,0),MATCH($B13,IncomeCalcs!$AN$2:$AS$2,0))} -> 0 | I27: =SUM(C27:H27) -> 54
B28: Cash$ | C28: {=INDEX(IncomeCalcs!$AN$2:$AS$254,MATCH(DATEVALUE(MATCH(C$2,{"January","February","March","April","May","June","July","August","September","October","November","December"},0) & "/1/" &$C$1),IncomeCalcs!$AM$2:$AM37,0),MATCH($B14,IncomeCalcs!$AN$2:$AS$2,0))} -> 0 | D28: {=INDEX(IncomeCalcs!$AN$2:$AS$254,MATCH(DATEVALUE(MATCH(D$2,{"January","February","March","April","May","June","July","August","September","October","November","December"},0) & "/1/" &$C$1),IncomeCalcs!$AM$2:$AM37,0),MATCH($B14,IncomeCalcs!$AN$2:$AS$2,0))} -> 0 | E28: {=INDEX(IncomeCalcs!$AN$2:$AS$254,MATCH(DATEVALUE(MATCH(E$2,{"January","February","March","April","May","June","July","August","September","October","November","December"},0) & "/1/" &$C$1),IncomeCalcs!$AM$2:$AM37,0),MATCH($B14,IncomeCalcs!$AN$2:$AS$2,0))} -> 0 | F28: {=INDEX(IncomeCalcs!$AN$2:$AS$254,MATCH(DATEVALUE(MATCH(F$2,{"January","February","March","April","May","June","July","August","September","October","November","December"},0) & "/1/" &$C$1),IncomeCalcs!$AM$2:$AM37,0),MATCH($B14,IncomeCalcs!$AN$2:$AS$2,0))} -> 0 | G28: {=INDEX(IncomeCalcs!$AN$2:$AS$254,MATCH(DATEVALUE(MATCH(G$2,{"January","February","March","April","May","June","July","August","September","October","November","December"},0) & "/1/" &$C$1),IncomeCalcs!$AM$2:$AM37,0),MATCH($B14,IncomeCalcs!$AN$2:$AS$2,0))} -> 0 | H28: {=INDEX(IncomeCalcs!$AN$2:$AS$254,MATCH(DATEVALUE(MATCH(H$2,{"January","February","March","April","May","June","July","August","September","October","November","December"},0) & "/1/" &$C$1),IncomeCalcs!$AM$2:$AM37,0),MATCH($B14,IncomeCalcs!$AN$2:$AS$2,0))} -> 0 | I28: =SUM(C28:H28) -> 0
B29: Zelle | C29: {=INDEX(IncomeCalcs!$AN$2:$AS$254,MATCH(DATEVALUE(MATCH(C$2,{"January","February","March","April","May","June","July","August","September","October","November","December"},0) & "/1/" &$C$1),IncomeCalcs!$AM$2:$AM37,0),MATCH($B15,IncomeCalcs!$AN$2:$AS$2,0))} -> 0 | D29: {=INDEX(IncomeCalcs!$AN$2:$AS$254,MATCH(DATEVALUE(MATCH(D$2,{"January","February","March","April","May","June","July","August","September","October","November","December"},0) & "/1/" &$C$1),IncomeCalcs!$AM$2:$AM37,0),MATCH($B15,IncomeCalcs!$AN$2:$AS$2,0))} -> 0 | E29: {=INDEX(IncomeCalcs!$AN$2:$AS$254,MATCH(DATEVALUE(MATCH(E$2,{"January","February","March","April","May","June","July","August","September","October","November","December"},0) & "/1/" &$C$1),IncomeCalcs!$AM$2:$AM37,0),MATCH($B15,IncomeCalcs!$AN$2:$AS$2,0))} -> 0 | F29: {=INDEX(IncomeCalcs!$AN$2:$AS$254,MATCH(DATEVALUE(MATCH(F$2,{"January","February","March","April","May","June","July","August","September","October","November","December"},0) & "/1/" &$C$1),IncomeCalcs!$AM$2:$AM37,0),MATCH($B15,IncomeCalcs!$AN$2:$AS$2,0))} -> 0 | G29: {=INDEX(IncomeCalcs!$AN$2:$AS$254,MATCH(DATEVALUE(MATCH(G$2,{"January","February","March","April","May","June","July","August","September","October","November","December"},0) & "/1/" &$C$1),IncomeCalcs!$AM$2:$AM37,0),MATCH($B15,IncomeCalcs!$AN$2:$AS$2,0))} -> 0 | H29: {=INDEX(IncomeCalcs!$AN$2:$AS$254,MATCH(DATEVALUE(MATCH(H$2,{"January","February","March","April","May","June","July","August","September","October","November","December"},0) & "/1/" &$C$1),IncomeCalcs!$AM$2:$AM37,0),MATCH($B15,IncomeCalcs!$AN$2:$AS$2,0))} -> 0 | I29: =SUM(C29:H29) -> 0
B30: GoFundMe | C30: {=INDEX(IncomeCalcs!$AN$2:$AS$254,MATCH(DATEVALUE(MATCH(C$2,{"January","February","March","April","May","June","July","August","September","October","November","December"},0) & "/1/" &$C$1),IncomeCalcs!$AM$2:$AM37,0),MATCH($B16,IncomeCalcs!$AN$2:$AS$2,0))} -> 0 | D30: {=INDEX(IncomeCalcs!$AN$2:$AS$254,MATCH(DATEVALUE(MATCH(D$2,{"January","February","March","April","May","June","July","August","September","October","November","December"},0) & "/1/" &$C$1),IncomeCalcs!$AM$2:$AM37,0),MATCH($B16,IncomeCalcs!$AN$2:$AS$2,0))} -> 0 | E30: {=INDEX(IncomeCalcs!$AN$2:$AS$254,MATCH(DATEVALUE(MATCH(E$2,{"January","February","March","April","May","June","July","August","September","October","November","December"},0) & "/1/" &$C$1),IncomeCalcs!$AM$2:$AM37,0),MATCH($B16,IncomeCalcs!$AN$2:$AS$2,0))} -> 0 | F30: {=INDEX(IncomeCalcs!$AN$2:$AS$254,MATCH(DATEVALUE(MATCH(F$2,{"January","February","March","April","May","June","July","August","September","October","November","December"},0) & "/1/" &$C$1),IncomeCalcs!$AM$2:$AM37,0),MATCH($B16,IncomeCalcs!$AN$2:$AS$2,0))} -> 0 | G30: {=INDEX(IncomeCalcs!$AN$2:$AS$254,MATCH(DATEVALUE(MATCH(G$2,{"January","February","March","April","May","June","July","August","September","October","November","December"},0) & "/1/" &$C$1),IncomeCalcs!$AM$2:$AM37,0),MATCH($B16,IncomeCalcs!$AN$2:$AS$2,0))} -> 0 | H30: {=INDEX(IncomeCalcs!$AN$2:$AS$254,MATCH(DATEVALUE(MATCH(H$2,{"January","February","March","April","May","June","July","August","September","October","November","December"},0) & "/1/" &$C$1),IncomeCalcs!$AM$2:$AM37,0),MATCH($B16,IncomeCalcs!$AN$2:$AS$2,0))} -> 0 | I30: =SUM(C30:H30) -> 0
A31: Adoption fees | B31: Monthly totals: | C31: =sum(C$32:C$37) -> 0 | D31: =sum(D$32:D$37) -> 0 | E31: =sum(E$32:E$37) -> 0 | F31: =sum(F$32:F$37) -> 0 | G31: =sum(G$32:G$37) -> 0 | H31: =sum(H$32:H$37) -> 0 | I31: =SUM(C31:H31) -> 0
B32: Paypal | C32: {=INDEX(IncomeCalcs!$AV$2:$BA$254,MATCH(DATEVALUE(MATCH(C$2,{"January","February","March","April","May","June","July","August","September","October","November","December"},0) & "/1/" &$C$1),IncomeCalcs!$AU$2:$AU37,0),MATCH($B11,IncomeCalcs!$AV$2:$BA$2,0))} -> 0 | D32: {=INDEX(IncomeCalcs!$AV$2:$BA$254,MATCH(DATEVALUE(MATCH(D$2,{"January","February","March","April","May","June","July","August","September","October","November","December"},0) & "/1/" &$C$1),IncomeCalcs!$AU$2:$AU37,0),MATCH($B11,IncomeCalcs!$AV$2:$BA$2,0))} -> 0 | E32: {=INDEX(IncomeCalcs!$AV$2:$BA$254,MATCH(DATEVALUE(MATCH(E$2,{"January","February","March","April","May","June","July","August","September","October","November","December"},0) & "/1/" &$C$1),IncomeCalcs!$AU$2:$AU37,0),MATCH($B11,IncomeCalcs!$AV$2:$BA$2,0))} -> 0 | F32: {=INDEX(IncomeCalcs!$AV$2:$BA$254,MATCH(DATEVALUE(MATCH(F$2,{"January","February","March","April","May","June","July","August","September","October","November","December"},0) & "/1/" &$C$1),IncomeCalcs!$AU$2:$AU37,0),MATCH($B11,IncomeCalcs!$AV$2:$BA$2,0))} -> 0 | G32: {=INDEX(IncomeCalcs!$AV$2:$BA$254,MATCH(DATEVALUE(MATCH(G$2,{"January","February","March","April","May","June","July","August","September","October","November","December"},0) & "/1/" &$C$1),IncomeCalcs!$AU$2:$AU37,0),MATCH($B11,IncomeCalcs!$AV$2:$BA$2,0))} -> 0 | H32: {=INDEX(IncomeCalcs!$AV$2:$BA$254,MATCH(DATEVALUE(MATCH(H$2,{"January","February","March","April","May","June","July","August","September","October","November","December"},0) & "/1/" &$C$1),IncomeCalcs!$AU$2:$AU37,0),MATCH($B11,IncomeCalcs!$AV$2:$BA$2,0))} -> 0 | I32: =SUM(C32:H32) -> 0
B33: Cashapp | C33: {=INDEX(IncomeCalcs!$AV$2:$BA$254,MATCH(DATEVALUE(MATCH(C$2,{"January","February","March","April","May","June","July","August","September","October","November","December"},0) & "/1/" &$C$1),IncomeCalcs!$AU$2:$AU37,0),MATCH($B12,IncomeCalcs!$AV$2:$BA$2,0))} -> 0 | D33: {=INDEX(IncomeCalcs!$AV$2:$BA$254,MATCH(DATEVALUE(MATCH(D$2,{"January","February","March","April","May","June","July","August","September","October","November","December"},0) & "/1/" &$C$1),IncomeCalcs!$AU$2:$AU37,0),MATCH($B12,IncomeCalcs!$AV$2:$BA$2,0))} -> 0 | E33: {=INDEX(IncomeCalcs!$AV$2:$BA$254,MATCH(DATEVALUE(MATCH(E$2,{"January","February","March","April","May","June","July","August","September","October","November","December"},0) & "/1/" &$C$1),IncomeCalcs!$AU$2:$AU37,0),MATCH($B12,IncomeCalcs!$AV$2:$BA$2,0))} -> 0 | F33: {=INDEX(IncomeCalcs!$AV$2:$BA$254,MATCH(DATEVALUE(MATCH(F$2,{"January","February","March","April","May","June","July","August","September","October","November","December"},0) & "/1/" &$C$1),IncomeCalcs!$AU$2:$AU37,0),MATCH($B12,IncomeCalcs!$AV$2:$BA$2,0))} -> 0 | G33: {=INDEX(IncomeCalcs!$AV$2:$BA$254,MATCH(DATEVALUE(MATCH(G$2,{"January","February","March","April","May","June","July","August","September","October","November","December"},0) & "/1/" &$C$1),IncomeCalcs!$AU$2:$AU37,0),MATCH($B12,IncomeCalcs!$AV$2:$BA$2,0))} -> 0 | H33: {=INDEX(IncomeCalcs!$AV$2:$BA$254,MATCH(DATEVALUE(MATCH(H$2,{"January","February","March","April","May","June","July","August","September","October","November","December"},0) & "/1/" &$C$1),IncomeCalcs!$AU$2:$AU37,0),MATCH($B12,IncomeCalcs!$AV$2:$BA$2,0))} -> 0 | I33: =SUM(C33:H33) -> 0
B34: Venmo | C34: {=INDEX(IncomeCalcs!$AV$2:$BA$254,MATCH(DATEVALUE(MATCH(C$2,{"January","February","March","April","May","June","July","August","September","October","November","December"},0) & "/1/" &$C$1),IncomeCalcs!$AU$2:$AU37,0),MATCH($B13,IncomeCalcs!$AV$2:$BA$2,0))} -> 0 | D34: {=INDEX(IncomeCalcs!$AV$2:$BA$254,MATCH(DATEVALUE(MATCH(D$2,{"January","February","March","April","May","June","July","August","September","October","November","December"},0) & "/1/" &$C$1),IncomeCalcs!$AU$2:$AU37,0),MATCH($B13,IncomeCalcs!$AV$2:$BA$2,0))} -> 0 | E34: {=INDEX(IncomeCalcs!$AV$2:$BA$254,MATCH(DATEVALUE(MATCH(E$2,{"January","February","March","April","May","June","July","August","September","October","November","December"},0) & "/1/" &$C$1),IncomeCalcs!$AU$2:$AU37,0),MATCH($B13,IncomeCalcs!$AV$2:$BA$2,0))} -> 0 | F34: {=INDEX(IncomeCalcs!$AV$2:$BA$254,MATCH(DATEVALUE(MATCH(F$2,{"January","February","March","April","May","June","July","August","September","October","November","December"},0) & "/1/" &$C$1),IncomeCalcs!$AU$2:$AU37,0),MATCH($B13,IncomeCalcs!$AV$2:$BA$2,0))} -> 0 | G34: {=INDEX(IncomeCalcs!$AV$2:$BA$254,MATCH(DATEVALUE(MATCH(G$2,{"January","February","March","April","May","June","July","August","September","October","November","December"},0) & "/1/" &$C$1),IncomeCalcs!$AU$2:$AU37,0),MATCH($B13,IncomeCalcs!$AV$2:$BA$2,0))} -> 0 | H34: {=INDEX(IncomeCalcs!$AV$2:$BA$254,MATCH(DATEVALUE(MATCH(H$2,{"January","February","March","April","May","June","July","August","September","October","November","December"},0) & "/1/" &$C$1),IncomeCalcs!$AU$2:$AU37,0),MATCH($B13,IncomeCalcs!$AV$2:$BA$2,0))} -> 0 | I34: =SUM(C34:H34) -> 0
B35: Cash$ | C35: {=INDEX(IncomeCalcs!$AV$2:$BA$254,MATCH(DATEVALUE(MATCH(C$2,{"January","February","March","April","May","June","July","August","September","October","November","December"},0) & "/1/" &$C$1),IncomeCalcs!$AU$2:$AU37,0),MATCH($B14,IncomeCalcs!$AV$2:$BA$2,0))} -> 0 | D35: {=INDEX(IncomeCalcs!$AV$2:$BA$254,MATCH(DATEVALUE(MATCH(D$2,{"January","February","March","April","May","June","July","August","September","October","November","December"},0) & "/1/" &$C$1),IncomeCalcs!$AU$2:$AU37,0),MATCH($B14,IncomeCalcs!$AV$2:$BA$2,0))} -> 0 | E35: {=INDEX(IncomeCalcs!$AV$2:$BA$254,MATCH(DATEVALUE(MATCH(E$2,{"January","February","March","April","May","June","July","August","September","October","November","December"},0) & "/1/" &$C$1),IncomeCalcs!$AU$2:$AU37,0),MATCH($B14,IncomeCalcs!$AV$2:$BA$2,0))} -> 0 | F35: {=INDEX(IncomeCalcs!$AV$2:$BA$254,MATCH(DATEVALUE(MATCH(F$2,{"January","February","March","April","May","June","July","August","September","October","November","December"},0) & "/1/" &$C$1),IncomeCalcs!$AU$2:$AU37,0),MATCH($B14,IncomeCalcs!$AV$2:$BA$2,0))} -> 0 | G35: {=INDEX(IncomeCalcs!$AV$2:$BA$254,MATCH(DATEVALUE(MATCH(G$2,{"January","February","March","April","May","June","July","August","September","October","November","December"},0) & "/1/" &$C$1),IncomeCalcs!$AU$2:$AU37,0),MATCH($B14,IncomeCalcs!$AV$2:$BA$2,0))} -> 0 | H35: {=INDEX(IncomeCalcs!$AV$2:$BA$254,MATCH(DATEVALUE(MATCH(H$2,{"January","February","March","April","May","June","July","August","September","October","November","December"},0) & "/1/" &$C$1),IncomeCalcs!$AU$2:$AU37,0),MATCH($B14,IncomeCalcs!$AV$2:$BA$2,0))} -> 0 | I35: =SUM(C35:H35) -> 0
B36: Zelle | C36: {=INDEX(IncomeCalcs!$AV$2:$BA$254,MATCH(DATEVALUE(MATCH(C$2,{"January","February","March","April","May","June","July","August","September","October","November","December"},0) & "/1/" &$C$1),IncomeCalcs!$AU$2:$AU37,0),MATCH($B15,IncomeCalcs!$AV$2:$BA$2,0))} -> 0 | D36: {=INDEX(IncomeCalcs!$AV$2:$BA$254,MATCH(DATEVALUE(MATCH(D$2,{"January","February","March","April","May","June","July","August","September","October","November","December"},0) & "/1/" &$C$1),IncomeCalcs!$AU$2:$AU37,0),MATCH($B15,IncomeCalcs!$AV$2:$BA$2,0))} -> 0 | E36: {=INDEX(IncomeCalcs!$AV$2:$BA$254,MATCH(DATEVALUE(MATCH(E$2,{"January","February","March","April","May","June","July","August","September","October","November","December"},0) & "/1/" &$C$1),IncomeCalcs!$AU$2:$AU37,0),MATCH($B15,IncomeCalcs!$AV$2:$BA$2,0))} -> 0 | F36: {=INDEX(IncomeCalcs!$AV$2:$BA$254,MATCH(DATEVALUE(MATCH(F$2,{"January","February","March","April","May","June","July","August","September","October","November","December"},0) & "/1/" &$C$1),IncomeCalcs!$AU$2:$AU37,0),MATCH($B15,IncomeCalcs!$AV$2:$BA$2,0))} -> 0 | G36: {=INDEX(IncomeCalcs!$AV$2:$BA$254,MATCH(DATEVALUE(MATCH(G$2,{"January","February","March","April","May","June","July","August","September","October","November","December"},0) & "/1/" &$C$1),IncomeCalcs!$AU$2:$AU37,0),MATCH($B15,IncomeCalcs!$AV$2:$BA$2,0))} -> 0 | H36: {=INDEX(IncomeCalcs!$AV$2:$BA$254,MATCH(DATEVALUE(MATCH(H$2,{"January","February","March","April","May","June","July","August","September","October","November","December"},0) & "/1/" &$C$1),IncomeCalcs!$AU$2:$AU37,0),MATCH($B15,IncomeCalcs!$AV$2:$BA$2,0))} -> 0 | I36: =SUM(C36:H36) -> 0
B37: GoFundMe | C37: {=INDEX(IncomeCalcs!$AV$2:$BA$254,MATCH(DATEVALUE(MATCH(C$2,{"January","February","March","April","May","June","July","August","September","October","November","December"},0) & "/1/" &$C$1),IncomeCalcs!$AU$2:$AU37,0),MATCH($B16,IncomeCalcs!$AV$2:$BA$2,0))} -> 0 | D37: {=INDEX(IncomeCalcs!$AV$2:$BA$254,MATCH(DATEVALUE(MATCH(D$2,{"January","February","March","April","May","June","July","August","September","October","November","December"},0) & "/1/" &$C$1),IncomeCalcs!$AU$2:$AU37,0),MATCH($B16,IncomeCalcs!$AV$2:$BA$2,0))} -> 0 | E37: {=INDEX(IncomeCalcs!$AV$2:$BA$254,MATCH(DATEVALUE(MATCH(E$2,{"January","February","March","April","May","June","July","August","September","October","November","December"},0) & "/1/" &$C$1),IncomeCalcs!$AU$2:$AU37,0),MATCH($B16,IncomeCalcs!$AV$2:$BA$2,0))} -> 0 | F37: {=INDEX(IncomeCalcs!$AV$2:$BA$254,MATCH(DATEVALUE(MATCH(F$2,{"January","February","March","April","May","June","July","August","September","October","November","December"},0) & "/1/" &$C$1),IncomeCalcs!$AU$2:$AU37,0),MATCH($B16,IncomeCalcs!$AV$2:$BA$2,0))} -> 0 | G37: {=INDEX(IncomeCalcs!$AV$2:$BA$254,MATCH(DATEVALUE(MATCH(G$2,{"January","February","March","April","May","June","July","August","September","October","November","December"},0) & "/1/" &$C$1),IncomeCalcs!$AU$2:$AU37,0),MATCH($B16,IncomeCalcs!$AV$2:$BA$2,0))} -> 0 | H37: {=INDEX(IncomeCalcs!$AV$2:$BA$254,MATCH(DATEVALUE(MATCH(H$2,{"January","February","March","April","May","June","July","August","September","October","November","December"},0) & "/1/" &$C$1),IncomeCalcs!$AU$2:$AU37,0),MATCH($B16,IncomeCalcs!$AV$2:$BA$2,0))} -> 0 | I37: =SUM(C37:H37) -> 0

Sheet Membership Application List
A1: Membership Application List
A2: Original form linked here: https://docs.google.com/spreadsheets/d/18RaQw448NnENcNftounuam8eQyPVXS6StgZUz-RLzHA/edit?usp=sharing
A3: Date | B3: Mavorgs Invite | C3: Semester | D3: Email | E3: Full Name | F3: Discord Username | G3: Payment Username | H3: Phone Number | I3: Membership Type | J3: Dues Or Donation | K3: Discount (Social Media) | L3: Paid Where? | M3: Donation? | N3: Verified? | O3: Committee Interests | P3: Images (Proof of payment) | Q3: Officer Notes
A4: =IFERROR(__xludf.DUMMYFUNCTION("IMPORTRANGE(""18RaQw448NnENcNftounuam8eQyPVXS6StgZUz-RLzHA/edit#gid=259554390"",""UTA Cat Coalition Membership Application!A2:A999"")"),44586.73601363426) -> 44586.736 | B4: TRUE | C4: =IF(A4<>"", IFERROR(IF(MONTH(A4) < 6, "Spring ", "Fall ") & IF(MONTH(A4) < 6, YEAR(A4), YEAR(A4) + IF(MONTH(A4) = 12, 1, 0)), ""), "") -> Spring 2022 | D4: =IFERROR(__xludf.DUMMYFUNCTION("ARRAYFORMULA(IF(LEN(IMPORTRANGE(""18RaQw448NnENcNftounuam8eQyPVXS6StgZUz-RLzHA"", ""UTA Cat Coalition Membership Application!B2:B999"")), HYPERLINK(""mailto:"" & IMPORTRANGE(""18RaQw448NnENcNftounuam8eQyPVXS6StgZUz-RLzHA"", ""UTA Cat Coalition Membership "&"Application!B2:B999""), IMPORTRANGE(""18RaQw448NnENcNftounuam8eQyPVXS6StgZUz-RLzHA"", ""UTA Cat Coalition Membership Application!B2:B999"")), """"))"),"jxc7884@mavs.uta.edu") -> jxc7884@mavs.uta.edu | E4: =IFERROR(__xludf.DUMMYFUNCTION("IMPORTRANGE(""18RaQw448NnENcNftounuam8eQyPVXS6StgZUz-RLzHA/edit#gid=259554390"",""UTA Cat Coalition Membership Application!C2:C999"")"),"Jocelyn Clark") -> Jocelyn Clark | F4: =IFERROR(__xludf.DUMMYFUNCTION("IMPORTRANGE(""18RaQw448NnENcNftounuam8eQyPVXS6StgZUz-RLzHA/edit#gid=259554390"",""UTA Cat Coalition Membership Application!D2:D999"")"),"Joce#6921") -> Joce#6921 | G4: =IFERROR(__xludf.DUMMYFUNCTION("IMPORTRANGE(""18RaQw448NnENcNftounuam8eQyPVXS6StgZUz-RLzHA/edit#gid=259554390"",""UTA Cat Coalition Membership Application!M2:M999"")"),"") | H4: =IFERROR(__xludf.DUMMYFUNCTION("ARRAYFORMULA(IF(LEN(IMPORTRANGE(""18RaQw448NnENcNftounuam8eQyPVXS6StgZUz-RLzHA"", ""UTA Cat Coalition Membership Application!E2:E999"")), ""("" & MID(SUBSTITUTE(SUBSTITUTE(SUBSTITUTE(IMPORTRANGE(""18RaQw448NnENcNftounuam8eQyPVXS6StgZUz-RLzHA"", ""UTA Cat "&"Coalition Membership Application!E2:E999""), ""("", """"), "")"", """"), ""-"", """"), 1, 3) & "") "" & MID(SUBSTITUTE(SUBSTITUTE(SUBSTITUTE(IMPORTRANGE(""18RaQw448NnENcNftounuam8eQyPVXS6StgZUz-RLzHA"", ""UTA Cat Coalition Membership Application!E2:E999"""&"), ""("", """"), "")"", """"), ""-"", """"), 4, 3) & ""-"" & MID(SUBSTITUTE(SUBSTITUTE(SUBSTITUTE(IMPORTRANGE(""18RaQw448NnENcNftounuam8eQyPVXS6StgZUz-RLzHA"", ""UTA Cat Coalition Membership Application!E2:E999""), ""("", """"), "")"", """"), ""-"", """")"&", 7, 4), """"))"),"(956) 701-9964") -> (956) 701-9964 | I4: =IFERROR(__xludf.DUMMYFUNCTION("ARRAYFORMULA(SUBSTITUTE(SUBSTITUTE(SUBSTITUTE(IMPORTRANGE(""18RaQw448NnENcNftounuam8eQyPVXS6StgZUz-RLzHA"", ""UTA Cat Coalition Membership Application!G2:G999""), ""Student Member"", ""Student""), ""Community Member"", ""Community Member""), ""UTA Faculty"&" and Staff"", ""UTA Faculty""))"),"Student") -> Student | J4: =IFERROR(__xludf.DUMMYFUNCTION("ARRAYFORMULA(IF(ROW(I4:I1003)<=92, IF(IMPORTRANGE(""18RaQw448NnENcNftounuam8eQyPVXS6StgZUz-RLzHA"", ""UTA Cat Coalition Membership Application!H2:H"") = ""$15 and Submit Payment Verification on Discord"", ""$15 Donation, Discord Verification"", IF(IMPORTR"&"ANGE(""18RaQw448NnENcNftounuam8eQyPVXS6StgZUz-RLzHA"", ""UTA Cat Coalition Membership Application!H2:H"") = ""Provide Donation of Cat Food (wet or dry) and or Cat Litter; notify an officer beforehand"", ""Food/Litter Donation"", """")), IF(ISNUMBER(SEARCH"&"(""$15 and Submit Payment Verification on Discord"", IMPORTRANGE(""18RaQw448NnENcNftounuam8eQyPVXS6StgZUz-RLzHA"", ""UTA Cat Coalition Membership Application!H2:H""))), ""$15 Donation, Discord Verification"", IF(ISNUMBER(SEARCH(""Provide Donation of Cat F"&"ood (wet or dry) and or Cat Litter; notify an officer beforehand"", IMPORTRANGE(""18RaQw448NnENcNftounuam8eQyPVXS6StgZUz-RLzHA"", ""UTA Cat Coalition Membership Application!H2:H""))), ""Food/Litter Donation"", """"))))"),"$15 Donation, Discord Verification") -> $15 Donation, Discord Verification | O4: =IFERROR(__xludf.DUMMYFUNCTION("ARRAYFORMULA(IF(LEN(IMPORTRANGE(""18RaQw448NnENcNftounuam8eQyPVXS6StgZUz-RLzHA"", ""UTA Cat Coalition Membership Application!I2:I"")), SUBSTITUTE(SUBSTITUTE(SUBSTITUTE(SUBSTITUTE(SUBSTITUTE(SUBSTITUTE(SUBSTITUTE(SUBSTITUTE(IMPORTRANGE(""18RaQw448NnENcNfto"&"unuam8eQyPVXS6StgZUz-RLzHA"", ""UTA Cat Coalition Membership Application!I2:I""), ""Fundraising Committee"", ""Fundraising""), ""Public Relations Committee"", ""PR""), ""Membership Committee"", ""Membership""), ""TNR Team"", ""TNR""), ""Overnight TNR Comm"&"ittee"", ""Overnight TNR""), ""Feeding Team"", ""Feeding""), ""Fostering Committee"", ""Fostering""), ""Shelter Maintenance Team"", ""Shelter Maintenance""), """"))"),"PR, Feeding") -> PR, Feeding | P4: =IFERROR(__xludf.DUMMYFUNCTION("IFERROR( IMAGE( ""https://drive.google.com/uc?export=download&id=""&MID( IMPORTRANGE(""18RaQw448NnENcNftounuam8eQyPVXS6StgZUz-RLzHA"",""'UTA Cat Coalition Membership Application'!L""&ROW()-2) ,(FIND(""="", IMPORTRANGE(""18RaQw448NnENcNftounuam8eQyPVXS6St"&"gZUz-RLzHA"",""'UTA Cat Coalition Membership Application'!L""&ROW()-2) ))+1,LEN( IMPORTRANGE(""18RaQw448NnENcNftounuam8eQyPVXS6StgZUz-RLzHA"",""'UTA Cat Coalition Membership Application'!L""&ROW()-2) )-FIND(""="", IMPORTRANGE(""18RaQw448NnENcNftounuam8eQy"&"PVXS6StgZUz-RLzHA"",""'UTA Cat Coalition Membership Application'!L""&ROW()-2) )),1 ) , """")"),"")
A5: =IFERROR(__xludf.DUMMYFUNCTION("""COMPUTED_VALUE"""),44586.73717479166) -> 44586.737 | B5: TRUE | C5: =IF(A5<>"", IFERROR(IF(MONTH(A5) < 6, "Spring ", "Fall ") & IF(MONTH(A5) < 6, YEAR(A5), YEAR(A5) + IF(MONTH(A5) = 12, 1, 0)), ""), "") -> Spring 2022 | D5: =IFERROR(__xludf.DUMMYFUNCTION("""COMPUTED_VALUE"""),"cindylou.skipper@mavs.uta.edu") -> cindylou.skipper@mavs.uta.edu | E5: =IFERROR(__xludf.DUMMYFUNCTION("""COMPUTED_VALUE"""),"Cindy Lou Skipper") -> Cindy Lou Skipper | F5: =IFERROR(__xludf.DUMMYFUNCTION("""COMPUTED_VALUE"""),"meiyingcinskip#2026") -> meiyingcinskip#2026 | H5: =IFERROR(__xludf.DUMMYFUNCTION("""COMPUTED_VALUE"""),"(682) 551-7350") -> (682) 551-7350 | I5: =IFERROR(__xludf.DUMMYFUNCTION("""COMPUTED_VALUE"""),"Student") -> Student | J5: =IFERROR(__xludf.DUMMYFUNCTION("""COMPUTED_VALUE"""),"Food/Litter Donation") -> Food/Litter Donation | O5: =IFERROR(__xludf.DUMMYFUNCTION("""COMPUTED_VALUE"""),"none") -> none | P5: =IFERROR(__xludf.DUMMYFUNCTION("IFERROR( IMAGE( ""https://drive.google.com/uc?export=download&id=""&MID( IMPORTRANGE(""18RaQw448NnENcNftounuam8eQyPVXS6StgZUz-RLzHA"",""'UTA Cat Coalition Membership Application'!L""&ROW()-2) ,(FIND(""="", IMPORTRANGE(""18RaQw448NnENcNftounuam8eQyPVXS6St"&"gZUz-RLzHA"",""'UTA Cat Coalition Membership Application'!L""&ROW()-2) ))+1,LEN( IMPORTRANGE(""18RaQw448NnENcNftounuam8eQyPVXS6StgZUz-RLzHA"",""'UTA Cat Coalition Membership Application'!L""&ROW()-2) )-FIND(""="", IMPORTRANGE(""18RaQw448NnENcNftounuam8eQy"&"PVXS6StgZUz-RLzHA"",""'UTA Cat Coalition Membership Application'!L""&ROW()-2) )),1 ) , """")"),"")
A6: =IFERROR(__xludf.DUMMYFUNCTION("""COMPUTED_VALUE"""),44586.73839827546) -> 44586.738 | B6: TRUE | C6: =IF(A6<>"", IFERROR(IF(MONTH(A6) < 6, "Spring ", "Fall ") & IF(MONTH(A6) < 6, YEAR(A6), YEAR(A6) + IF(MONTH(A6) = 12, 1, 0)), ""), "") -> Spring 2022 | D6: =IFERROR(__xludf.DUMMYFUNCTION("""COMPUTED_VALUE"""),"arianaharbr@gmail.com") -> arianaharbr@gmail.com | E6: =IFERROR(__xludf.DUMMYFUNCTION("""COMPUTED_VALUE"""),"Ariana Harbrink") -> Ariana Harbrink | F6: =IFERROR(__xludf.DUMMYFUNCTION("""COMPUTED_VALUE"""),"arianaa#2399") -> arianaa#2399 | H6: =IFERROR(__xludf.DUMMYFUNCTION("""COMPUTED_VALUE"""),"(962) 795-1961") -> (962) 795-1961 | I6: =IFERROR(__xludf.DUMMYFUNCTION("""COMPUTED_VALUE"""),"Student") -> Student | J6: =IFERROR(__xludf.DUMMYFUNCTION("""COMPUTED_VALUE"""),"$15 Donation, Discord Verification") -> $15 Donation, Discord Verification | O6: =IFERROR(__xludf.DUMMYFUNCTION("""COMPUTED_VALUE"""),"Feeding, Shelter Maintenance, TNR, Press Secretary (officer role)") -> Feeding, Shelter Maintenance, TNR, Press Secretary (officer role) | P6: =IFERROR(__xludf.DUMMYFUNCTION("IFERROR( IMAGE( ""https://drive.google.com/uc?export=download&id=""&MID( IMPORTRANGE(""18RaQw448NnENcNftounuam8eQyPVXS6StgZUz-RLzHA"",""'UTA Cat Coalition Membership Application'!L""&ROW()-2) ,(FIND(""="", IMPORTRANGE(""18RaQw448NnENcNftounuam8eQyPVXS6St"&"gZUz-RLzHA"",""'UTA Cat Coalition Membership Application'!L""&ROW()-2) ))+1,LEN( IMPORTRANGE(""18RaQw448NnENcNftounuam8eQyPVXS6StgZUz-RLzHA"",""'UTA Cat Coalition Membership Application'!L""&ROW()-2) )-FIND(""="", IMPORTRANGE(""18RaQw448NnENcNftounuam8eQy"&"PVXS6StgZUz-RLzHA"",""'UTA Cat Coalition Membership Application'!L""&ROW()-2) )),1 ) , """")"),"")
A7: =IFERROR(__xludf.DUMMYFUNCTION("""COMPUTED_VALUE"""),44586.73946186343) -> 44586.739 | B7: TRUE | C7: =IF(A7<>"", IFERROR(IF(MONTH(A7) < 6, "Spring ", "Fall ") & IF(MONTH(A7) < 6, YEAR(A7), YEAR(A7) + IF(MONTH(A7) = 12, 1, 0)), ""), "") -> Spring 2022 | D7: =IFERROR(__xludf.DUMMYFUNCTION("""COMPUTED_VALUE"""),"jxw1244@mavs.uta.edu") -> jxw1244@mavs.uta.edu | E7: =IFERROR(__xludf.DUMMYFUNCTION("""COMPUTED_VALUE"""),"Jane Wang") -> Jane Wang | F7: =IFERROR(__xludf.DUMMYFUNCTION("""COMPUTED_VALUE"""),"Jane_IRL#7185") -> Jane_IRL#7185 | H7: =IFERROR(__xludf.DUMMYFUNCTION("""COMPUTED_VALUE"""),"") | I7: =IFERROR(__xludf.DUMMYFUNCTION("""COMPUTED_VALUE"""),"Student") -> Student | J7: =IFERROR(__xludf.DUMMYFUNCTION("""COMPUTED_VALUE"""),"$15 Donation, Discord Verification") -> $15 Donation, Discord Verification | O7: =IFERROR(__xludf.DUMMYFUNCTION("""COMPUTED_VALUE"""),"Feeding, Shelter Maintenance") -> Feeding, Shelter Maintenance | P7: =IFERROR(__xludf.DUMMYFUNCTION("IFERROR( IMAGE( ""https://drive.google.com/uc?export=download&id=""&MID( IMPORTRANGE(""18RaQw448NnENcNftounuam8eQyPVXS6StgZUz-RLzHA"",""'UTA Cat Coalition Membership Application'!L""&ROW()-2) ,(FIND(""="", IMPORTRANGE(""18RaQw448NnENcNftounuam8eQyPVXS6St"&"gZUz-RLzHA"",""'UTA Cat Coalition Membership Application'!L""&ROW()-2) ))+1,LEN( IMPORTRANGE(""18RaQw448NnENcNftounuam8eQyPVXS6StgZUz-RLzHA"",""'UTA Cat Coalition Membership Application'!L""&ROW()-2) )-FIND(""="", IMPORTRANGE(""18RaQw448NnENcNftounuam8eQy"&"PVXS6StgZUz-RLzHA"",""'UTA Cat Coalition Membership Application'!L""&ROW()-2) )),1 ) , """")"),"")
A8: =IFERROR(__xludf.DUMMYFUNCTION("""COMPUTED_VALUE"""),44586.74047921297) -> 44586.74 | B8: TRUE | C8: =IF(A8<>"", IFERROR(IF(MONTH(A8) < 6, "Spring ", "Fall ") & IF(MONTH(A8) < 6, YEAR(A8), YEAR(A8) + IF(MONTH(A8) = 12, 1, 0)), ""), "") -> Spring 2022 | D8: =IFERROR(__xludf.DUMMYFUNCTION("""COMPUTED_VALUE"""),"sydney.stumpf@mavs.uta.edu") -> sydney.stumpf@mavs.uta.edu | E8: =IFERROR(__xludf.DUMMYFUNCTION("""COMPUTED_VALUE"""),"Sydney Stumpf") -> Sydney Stumpf | F8: =IFERROR(__xludf.DUMMYFUNCTION("""COMPUTED_VALUE"""),"sydneystumpf ") -> sydneystumpf | H8: =IFERROR(__xludf.DUMMYFUNCTION("""COMPUTED_VALUE"""),"(972) 571-0727") -> (972) 571-0727 | I8: =IFERROR(__xludf.DUMMYFUNCTION("""COMPUTED_VALUE"""),"Student") -> Student | J8: =IFERROR(__xludf.DUMMYFUNCTION("""COMPUTED_VALUE"""),"$15 Donation, Discord Verification") -> $15 Donation, Discord Verification | O8: =IFERROR(__xludf.DUMMYFUNCTION("""COMPUTED_VALUE"""),"PR, Feeding") -> PR, Feeding | P8: =IFERROR(__xludf.DUMMYFUNCTION("IFERROR( IMAGE( ""https://drive.google.com/uc?export=download&id=""&MID( IMPORTRANGE(""18RaQw448NnENcNftounuam8eQyPVXS6StgZUz-RLzHA"",""'UTA Cat Coalition Membership Application'!L""&ROW()-2) ,(FIND(""="", IMPORTRANGE(""18RaQw448NnENcNftounuam8eQyPVXS6St"&"gZUz-RLzHA"",""'UTA Cat Coalition Membership Application'!L""&ROW()-2) ))+1,LEN( IMPORTRANGE(""18RaQw448NnENcNftounuam8eQyPVXS6StgZUz-RLzHA"",""'UTA Cat Coalition Membership Application'!L""&ROW()-2) )-FIND(""="", IMPORTRANGE(""18RaQw448NnENcNftounuam8eQy"&"PVXS6StgZUz-RLzHA"",""'UTA Cat Coalition Membership Application'!L""&ROW()-2) )),1 ) , """")"),"")
A9: =IFERROR(__xludf.DUMMYFUNCTION("""COMPUTED_VALUE"""),44586.76115482639) -> 44586.761 | B9: TRUE | C9: =IF(A9<>"", IFERROR(IF(MONTH(A9) < 6, "Spring ", "Fall ") & IF(MONTH(A9) < 6, YEAR(A9), YEAR(A9) + IF(MONTH(A9) = 12, 1, 0)), ""), "") -> Spring 2022 | D9: =IFERROR(__xludf.DUMMYFUNCTION("""COMPUTED_VALUE"""),"brandon.isom@mavs.uta.edu") -> brandon.isom@mavs.uta.edu | E9: =IFERROR(__xludf.DUMMYFUNCTION("""COMPUTED_VALUE"""),"Brandon C Isom") -> Brandon C Isom | F9: =IFERROR(__xludf.DUMMYFUNCTION("""COMPUTED_VALUE"""),"Imp#5991") -> Imp#5991 | H9: =IFERROR(__xludf.DUMMYFUNCTION("""COMPUTED_VALUE"""),"(469) 403-9856") -> (469) 403-9856 | I9: =IFERROR(__xludf.DUMMYFUNCTION("""COMPUTED_VALUE"""),"Student") -> Student | J9: =IFERROR(__xludf.DUMMYFUNCTION("""COMPUTED_VALUE"""),"$15 Donation, Discord Verification") -> $15 Donation, Discord Verification | O9: =IFERROR(__xludf.DUMMYFUNCTION("""COMPUTED_VALUE"""),"I'm an officer lmao") -> I'm an officer lmao | P9: =IFERROR(__xludf.DUMMYFUNCTION("IFERROR( IMAGE( ""https://drive.google.com/uc?export=download&id=""&MID( IMPORTRANGE(""18RaQw448NnENcNftounuam8eQyPVXS6StgZUz-RLzHA"",""'UTA Cat Coalition Membership Application'!L""&ROW()-2) ,(FIND(""="", IMPORTRANGE(""18RaQw448NnENcNftounuam8eQyPVXS6St"&"gZUz-RLzHA"",""'UTA Cat Coalition Membership Application'!L""&ROW()-2) ))+1,LEN( IMPORTRANGE(""18RaQw448NnENcNftounuam8eQyPVXS6StgZUz-RLzHA"",""'UTA Cat Coalition Membership Application'!L""&ROW()-2) )-FIND(""="", IMPORTRANGE(""18RaQw448NnENcNftounuam8eQy"&"PVXS6StgZUz-RLzHA"",""'UTA Cat Coalition Membership Application'!L""&ROW()-2) )),1 ) , """")"),"")
A10: =IFERROR(__xludf.DUMMYFUNCTION("""COMPUTED_VALUE"""),44586.76173496528) -> 44586.762 | B10: TRUE | C10: =IF(A10<>"", IFERROR(IF(MONTH(A10) < 6, "Spring ", "Fall ") & IF(MONTH(A10) < 6, YEAR(A10), YEAR(A10) + IF(MONTH(A10) = 12, 1, 0)), ""), "") -> Spring 2022 | D10: =IFERROR(__xludf.DUMMYFUNCTION("""COMPUTED_VALUE"""),"hbb5589@mavs.uta.edu") -> hbb5589@mavs.uta.edu | E10: =IFERROR(__xludf.DUMMYFUNCTION("""COMPUTED_VALUE"""),"Hannah Brantley") -> Hannah Brantley | F10: =IFERROR(__xludf.DUMMYFUNCTION("""COMPUTED_VALUE"""),"HannahHalp#4486") -> HannahHalp#4486 | H10: =IFERROR(__xludf.DUMMYFUNCTION("""COMPUTED_VALUE"""),"(682) 225-4460") -> (682) 225-4460 | I10: =IFERROR(__xludf.DUMMYFUNCTION("""COMPUTED_VALUE"""),"Student") -> Student | J10: =IFERROR(__xludf.DUMMYFUNCTION("""COMPUTED_VALUE"""),"$15 Donation, Discord Verification") -> $15 Donation, Discord Verification | O10: =IFERROR(__xludf.DUMMYFUNCTION("""COMPUTED_VALUE"""),"Fundraising, Feeding, Shelter Maintenance") -> Fundraising, Feeding, Shelter Maintenance | P10: =IFERROR(__xludf.DUMMYFUNCTION("IFERROR( IMAGE( ""https://drive.google.com/uc?export=download&id=""&MID( IMPORTRANGE(""18RaQw448NnENcNftounuam8eQyPVXS6StgZUz-RLzHA"",""'UTA Cat Coalition Membership Application'!L""&ROW()-2) ,(FIND(""="", IMPORTRANGE(""18RaQw448NnENcNftounuam8eQyPVXS6St"&"gZUz-RLzHA"",""'UTA Cat Coalition Membership Application'!L""&ROW()-2) ))+1,LEN( IMPORTRANGE(""18RaQw448NnENcNftounuam8eQyPVXS6StgZUz-RLzHA"",""'UTA Cat Coalition Membership Application'!L""&ROW()-2) )-FIND(""="", IMPORTRANGE(""18RaQw448NnENcNftounuam8eQy"&"PVXS6StgZUz-RLzHA"",""'UTA Cat Coalition Membership Application'!L""&ROW()-2) )),1 ) , """")"),"")
A11: =IFERROR(__xludf.DUMMYFUNCTION("""COMPUTED_VALUE"""),44586.76373172454) -> 44586.764 | B11: TRUE | C11: =IF(A11<>"", IFERROR(IF(MONTH(A11) < 6, "Spring ", "Fall ") & IF(MONTH(A11) < 6, YEAR(A11), YEAR(A11) + IF(MONTH(A11) = 12, 1, 0)), ""), "") -> Spring 2022 | D11: =IFERROR(__xludf.DUMMYFUNCTION("""COMPUTED_VALUE"""),"angelina.nguyen2@mavs.uta.edu") -> angelina.nguyen2@mavs.uta.edu | E11: =IFERROR(__xludf.DUMMYFUNCTION("""COMPUTED_VALUE"""),"Angelina Nguyen") -> Angelina Nguyen | F11: =IFERROR(__xludf.DUMMYFUNCTION("""COMPUTED_VALUE"""),"@anglii#1259") -> @anglii#1259 | H11: =IFERROR(__xludf.DUMMYFUNCTION("""COMPUTED_VALUE"""),"(682) 551-5588") -> (682) 551-5588 | I11: =IFERROR(__xludf.DUMMYFUNCTION("""COMPUTED_VALUE"""),"Student") -> Student | J11: =IFERROR(__xludf.DUMMYFUNCTION("""COMPUTED_VALUE"""),"Food/Litter Donation") -> Food/Litter Donation | O11: =IFERROR(__xludf.DUMMYFUNCTION("""COMPUTED_VALUE"""),"Feeding") -> Feeding | P11: =IFERROR(__xludf.DUMMYFUNCTION("IFERROR( IMAGE( ""https://drive.google.com/uc?export=download&id=""&MID( IMPORTRANGE(""18RaQw448NnENcNftounuam8eQyPVXS6StgZUz-RLzHA"",""'UTA Cat Coalition Membership Application'!L""&ROW()-2) ,(FIND(""="", IMPORTRANGE(""18RaQw448NnENcNftounuam8eQyPVXS6St"&"gZUz-RLzHA"",""'UTA Cat Coalition Membership Application'!L""&ROW()-2) ))+1,LEN( IMPORTRANGE(""18RaQw448NnENcNftounuam8eQyPVXS6StgZUz-RLzHA"",""'UTA Cat Coalition Membership Application'!L""&ROW()-2) )-FIND(""="", IMPORTRANGE(""18RaQw448NnENcNftounuam8eQy"&"PVXS6StgZUz-RLzHA"",""'UTA Cat Coalition Membership Application'!L""&ROW()-2) )),1 ) , """")"),"")
A12: =IFERROR(__xludf.DUMMYFUNCTION("""COMPUTED_VALUE"""),44586.80134696759) -> 44586.801 | B12: TRUE | C12: =IF(A12<>"", IFERROR(IF(MONTH(A12) < 6, "Spring ", "Fall ") & IF(MONTH(A12) < 6, YEAR(A12), YEAR(A12) + IF(MONTH(A12) = 12, 1, 0)), ""), "") -> Spring 2022 | D12: =IFERROR(__xludf.DUMMYFUNCTION("""COMPUTED_VALUE"""),"claire.harvey@mavs.uta.edu") -> claire.harvey@mavs.uta.edu | E12: =IFERROR(__xludf.DUMMYFUNCTION("""COMPUTED_VALUE"""),"Claire Harvey") -> Claire Harvey | F12: =IFERROR(__xludf.DUMMYFUNCTION("""COMPUTED_VALUE"""),"claire.harvey#8083") -> claire.harvey#8083 | H12: =IFERROR(__xludf.DUMMYFUNCTION("""COMPUTED_VALUE"""),"(205) 568-4290") -> (205) 568-4290 | I12: =IFERROR(__xludf.DUMMYFUNCTION("""COMPUTED_VALUE"""),"Student") -> Student | J12: =IFERROR(__xludf.DUMMYFUNCTION("""COMPUTED_VALUE"""),"Food/Litter Donation") -> Food/Litter Donation | O12: =IFERROR(__xludf.DUMMYFUNCTION("""COMPUTED_VALUE"""),"TNR, I can assist with transportation to vaccination clinics for fosters") -> TNR, I can assist with transportation to vaccination clinics for fosters | P12: =IFERROR(__xludf.DUMMYFUNCTION("IFERROR( IMAGE( ""https://drive.google.com/uc?export=download&id=""&MID( IMPORTRANGE(""18RaQw448NnENcNftounuam8eQyPVXS6StgZUz-RLzHA"",""'UTA Cat Coalition Membership Application'!L""&ROW()-2) ,(FIND(""="", IMPORTRANGE(""18RaQw448NnENcNftounuam8eQyPVXS6St"&"gZUz-RLzHA"",""'UTA Cat Coalition Membership Application'!L""&ROW()-2) ))+1,LEN( IMPORTRANGE(""18RaQw448NnENcNftounuam8eQyPVXS6StgZUz-RLzHA"",""'UTA Cat Coalition Membership Application'!L""&ROW()-2) )-FIND(""="", IMPORTRANGE(""18RaQw448NnENcNftounuam8eQy"&"PVXS6StgZUz-RLzHA"",""'UTA Cat Coalition Membership Application'!L""&ROW()-2) )),1 ) , """")"),"")
A13: =IFERROR(__xludf.DUMMYFUNCTION("""COMPUTED_VALUE"""),44586.80291675926) -> 44586.803 | B13: TRUE | C13: =IF(A13<>"", IFERROR(IF(MONTH(A13) < 6, "Spring ", "Fall ") & IF(MONTH(A13) < 6, YEAR(A13), YEAR(A13) + IF(MONTH(A13) = 12, 1, 0)), ""), "") -> Spring 2022 | D13: =IFERROR(__xludf.DUMMYFUNCTION("""COMPUTED_VALUE"""),"mckaylamellen@gmail.com") -> mckaylamellen@gmail.com | E13: =IFERROR(__xludf.DUMMYFUNCTION("""COMPUTED_VALUE"""),"McKayla Mellen") -> McKayla Mellen | F13: =IFERROR(__xludf.DUMMYFUNCTION("""COMPUTED_VALUE"""),"nostalgicsapphic#7354") -> nostalgicsapphic#7354 | H13: =IFERROR(__xludf.DUMMYFUNCTION("""COMPUTED_VALUE"""),"(512) 644-2879") -> (512) 644-2879 | I13: =IFERROR(__xludf.DUMMYFUNCTION("""COMPUTED_VALUE"""),"Student") -> Student | J13: =IFERROR(__xludf.DUMMYFUNCTION("""COMPUTED_VALUE"""),"$15 Donation, Discord Verification") -> $15 Donation, Discord Verification | O13: =IFERROR(__xludf.DUMMYFUNCTION("""COMPUTED_VALUE"""),"<3 yes") -> <3 yes | P13: =IFERROR(__xludf.DUMMYFUNCTION("IFERROR( IMAGE( ""https://drive.google.com/uc?export=download&id=""&MID( IMPORTRANGE(""18RaQw448NnENcNftounuam8eQyPVXS6StgZUz-RLzHA"",""'UTA Cat Coalition Membership Application'!L""&ROW()-2) ,(FIND(""="", IMPORTRANGE(""18RaQw448NnENcNftounuam8eQyPVXS6St"&"gZUz-RLzHA"",""'UTA Cat Coalition Membership Application'!L""&ROW()-2) ))+1,LEN( IMPORTRANGE(""18RaQw448NnENcNftounuam8eQyPVXS6StgZUz-RLzHA"",""'UTA Cat Coalition Membership Application'!L""&ROW()-2) )-FIND(""="", IMPORTRANGE(""18RaQw448NnENcNftounuam8eQy"&"PVXS6StgZUz-RLzHA"",""'UTA Cat Coalition Membership Application'!L""&ROW()-2) )),1 ) , """")"),"")
A14: =IFERROR(__xludf.DUMMYFUNCTION("""COMPUTED_VALUE"""),44587.77012369213) -> 44587.77 | B14: TRUE | C14: =IF(A14<>"", IFERROR(IF(MONTH(A14) < 6, "Spring ", "Fall ") & IF(MONTH(A14) < 6, YEAR(A14), YEAR(A14) + IF(MONTH(A14) = 12, 1, 0)), ""), "") -> Spring 2022 | D14: =IFERROR(__xludf.DUMMYFUNCTION("""COMPUTED_VALUE"""),"sr0365@mavs.uta.edu") -> sr0365@mavs.uta.edu | E14: =IFERROR(__xludf.DUMMYFUNCTION("""COMPUTED_VALUE"""),"Stephen Rutherford") -> Stephen Rutherford | F14: =IFERROR(__xludf.DUMMYFUNCTION("""COMPUTED_VALUE"""),"angiekin#7816") -> angiekin#7816 | H14: =IFERROR(__xludf.DUMMYFUNCTION("""COMPUTED_VALUE"""),"(210) 77-3436") -> (210) 77-3436 | I14: =IFERROR(__xludf.DUMMYFUNCTION("""COMPUTED_VALUE"""),"Student") -> Student | J14: =IFERROR(__xludf.DUMMYFUNCTION("""COMPUTED_VALUE"""),"$15 Donation, Discord Verification") -> $15 Donation, Discord Verification | O14: =IFERROR(__xludf.DUMMYFUNCTION("""COMPUTED_VALUE"""),"Feeding, Shelter Maintenance") -> Feeding, Shelter Maintenance | P14: =IFERROR(__xludf.DUMMYFUNCTION("IFERROR( IMAGE( ""https://drive.google.com/uc?export=download&id=""&MID( IMPORTRANGE(""18RaQw448NnENcNftounuam8eQyPVXS6StgZUz-RLzHA"",""'UTA Cat Coalition Membership Application'!L""&ROW()-2) ,(FIND(""="", IMPORTRANGE(""18RaQw448NnENcNftounuam8eQyPVXS6St"&"gZUz-RLzHA"",""'UTA Cat Coalition Membership Application'!L""&ROW()-2) ))+1,LEN( IMPORTRANGE(""18RaQw448NnENcNftounuam8eQyPVXS6StgZUz-RLzHA"",""'UTA Cat Coalition Membership Application'!L""&ROW()-2) )-FIND(""="", IMPORTRANGE(""18RaQw448NnENcNftounuam8eQy"&"PVXS6StgZUz-RLzHA"",""'UTA Cat Coalition Membership Application'!L""&ROW()-2) )),1 ) , """")"),"")
A15: =IFERROR(__xludf.DUMMYFUNCTION("""COMPUTED_VALUE"""),44587.89467137732) -> 44587.895 | B15: TRUE | C15: =IF(A15<>"", IFERROR(IF(MONTH(A15) < 6, "Spring ", "Fall ") & IF(MONTH(A15) < 6, YEAR(A15), YEAR(A15) + IF(MONTH(A15) = 12, 1, 0)), ""), "") -> Spring 2022 | D15: =IFERROR(__xludf.DUMMYFUNCTION("""COMPUTED_VALUE"""),"mlh5689@mavs.uta.edu") -> mlh5689@mavs.uta.edu | E15: =IFERROR(__xludf.DUMMYFUNCTION("""COMPUTED_VALUE"""),"Madison Lynn Devin Harris") -> Madison Lynn Devin Harris | F15: =IFERROR(__xludf.DUMMYFUNCTION("""COMPUTED_VALUE"""),"madison#7344") -> madison#7344 | H15: =IFERROR(__xludf.DUMMYFUNCTION("""COMPUTED_VALUE"""),"(817) 412-9816") -> (817) 412-9816 | I15: =IFERROR(__xludf.DUMMYFUNCTION("""COMPUTED_VALUE"""),"Student") -> Student | J15: =IFERROR(__xludf.DUMMYFUNCTION("""COMPUTED_VALUE"""),"$15 Donation, Discord Verification") -> $15 Donation, Discord Verification | O15: =IFERROR(__xludf.DUMMYFUNCTION("""COMPUTED_VALUE"""),":)") -> :) | P15: =IFERROR(__xludf.DUMMYFUNCTION("IFERROR( IMAGE( ""https://drive.google.com/uc?export=download&id=""&MID( IMPORTRANGE(""18RaQw448NnENcNftounuam8eQyPVXS6StgZUz-RLzHA"",""'UTA Cat Coalition Membership Application'!L""&ROW()-2) ,(FIND(""="", IMPORTRANGE(""18RaQw448NnENcNftounuam8eQyPVXS6St"&"gZUz-RLzHA"",""'UTA Cat Coalition Membership Application'!L""&ROW()-2) ))+1,LEN( IMPORTRANGE(""18RaQw448NnENcNftounuam8eQyPVXS6StgZUz-RLzHA"",""'UTA Cat Coalition Membership Application'!L""&ROW()-2) )-FIND(""="", IMPORTRANGE(""18RaQw448NnENcNftounuam8eQy"&"PVXS6StgZUz-RLzHA"",""'UTA Cat Coalition Membership Application'!L""&ROW()-2) )),1 ) , """")"),"")
A16: =IFERROR(__xludf.DUMMYFUNCTION("""COMPUTED_VALUE"""),44587.910255532406) -> 44587.91 | B16: TRUE | C16: =IF(A16<>"", IFERROR(IF(MONTH(A16) < 6, "Spring ", "Fall ") & IF(MONTH(A16) < 6, YEAR(A16), YEAR(A16) + IF(MONTH(A16) = 12, 1, 0)), ""), "") -> Spring 2022 | D16: =IFERROR(__xludf.DUMMYFUNCTION("""COMPUTED_VALUE"""),"merryann.dao@mavs.uta.edu") -> merryann.dao@mavs.uta.edu | E16: =IFERROR(__xludf.DUMMYFUNCTION("""COMPUTED_VALUE"""),"Merryann Dao") -> Merryann Dao | F16: =IFERROR(__xludf.DUMMYFUNCTION("""COMPUTED_VALUE"""),"Merryann #9331") -> Merryann #9331 | H16: =IFERROR(__xludf.DUMMYFUNCTION("""COMPUTED_VALUE"""),"(682) 407-5562") -> (682) 407-5562 | I16: =IFERROR(__xludf.DUMMYFUNCTION("""COMPUTED_VALUE"""),"Student") -> Student | J16: =IFERROR(__xludf.DUMMYFUNCTION("""COMPUTED_VALUE"""),"$15 Donation, Discord Verification") -> $15 Donation, Discord Verification | O16: =IFERROR(__xludf.DUMMYFUNCTION("""COMPUTED_VALUE"""),"PR, Feeding") -> PR, Feeding | P16: =IFERROR(__xludf.DUMMYFUNCTION("IFERROR( IMAGE( ""https://drive.google.com/uc?export=download&id=""&MID( IMPORTRANGE(""18RaQw448NnENcNftounuam8eQyPVXS6StgZUz-RLzHA"",""'UTA Cat Coalition Membership Application'!L""&ROW()-2) ,(FIND(""="", IMPORTRANGE(""18RaQw448NnENcNftounuam8eQyPVXS6St"&"gZUz-RLzHA"",""'UTA Cat Coalition Membership Application'!L""&ROW()-2) ))+1,LEN( IMPORTRANGE(""18RaQw448NnENcNftounuam8eQyPVXS6StgZUz-RLzHA"",""'UTA Cat Coalition Membership Application'!L""&ROW()-2) )-FIND(""="", IMPORTRANGE(""18RaQw448NnENcNftounuam8eQy"&"PVXS6StgZUz-RLzHA"",""'UTA Cat Coalition Membership Application'!L""&ROW()-2) )),1 ) , """")"),"")
A17: =IFERROR(__xludf.DUMMYFUNCTION("""COMPUTED_VALUE"""),44587.96563896991) -> 44587.966 | B17: TRUE | C17: =IF(A17<>"", IFERROR(IF(MONTH(A17) < 6, "Spring ", "Fall ") & IF(MONTH(A17) < 6, YEAR(A17), YEAR(A17) + IF(MONTH(A17) = 12, 1, 0)), ""), "") -> Spring 2022 | D17: =IFERROR(__xludf.DUMMYFUNCTION("""COMPUTED_VALUE"""),"rxc3131@mavs.uta.edu") -> rxc3131@mavs.uta.edu | E17: =IFERROR(__xludf.DUMMYFUNCTION("""COMPUTED_VALUE"""),"Ronak Chheda") -> Ronak Chheda | F17: =IFERROR(__xludf.DUMMYFUNCTION("""COMPUTED_VALUE"""),"roni#2072") -> roni#2072 | H17: =IFERROR(__xludf.DUMMYFUNCTION("""COMPUTED_VALUE"""),"(682) 306-2826") -> (682) 306-2826 | I17: =IFERROR(__xludf.DUMMYFUNCTION("""COMPUTED_VALUE"""),"Student") -> Student | J17: =IFERROR(__xludf.DUMMYFUNCTION("""COMPUTED_VALUE"""),"$15 Donation, Discord Verification") -> $15 Donation, Discord Verification | O17: =IFERROR(__xludf.DUMMYFUNCTION("""COMPUTED_VALUE"""),"Feeding") -> Feeding | P17: =IFERROR(__xludf.DUMMYFUNCTION("IFERROR( IMAGE( ""https://drive.google.com/uc?export=download&id=""&MID( IMPORTRANGE(""18RaQw448NnENcNftounuam8eQyPVXS6StgZUz-RLzHA"",""'UTA Cat Coalition Membership Application'!L""&ROW()-2) ,(FIND(""="", IMPORTRANGE(""18RaQw448NnENcNftounuam8eQyPVXS6St"&"gZUz-RLzHA"",""'UTA Cat Coalition Membership Application'!L""&ROW()-2) ))+1,LEN( IMPORTRANGE(""18RaQw448NnENcNftounuam8eQyPVXS6StgZUz-RLzHA"",""'UTA Cat Coalition Membership Application'!L""&ROW()-2) )-FIND(""="", IMPORTRANGE(""18RaQw448NnENcNftounuam8eQy"&"PVXS6StgZUz-RLzHA"",""'UTA Cat Coalition Membership Application'!L""&ROW()-2) )),1 ) , """")"),"")
A18: =IFERROR(__xludf.DUMMYFUNCTION("""COMPUTED_VALUE"""),44588.73501611111) -> 44588.735 | B18: TRUE | C18: =IF(A18<>"", IFERROR(IF(MONTH(A18) < 6, "Spring ", "Fall ") & IF(MONTH(A18) < 6, YEAR(A18), YEAR(A18) + IF(MONTH(A18) = 12, 1, 0)), ""), "") -> Spring 2022 | D18: =IFERROR(__xludf.DUMMYFUNCTION("""COMPUTED_VALUE"""),"axp7773@mavs.uta.edu") -> axp7773@mavs.uta.edu | E18: =IFERROR(__xludf.DUMMYFUNCTION("""COMPUTED_VALUE"""),"Alexis Pedraza") -> Alexis Pedraza | F18: =IFERROR(__xludf.DUMMYFUNCTION("""COMPUTED_VALUE"""),"☆*.｡.nyehhehheh .｡.*☆#6624") -> ☆*.｡.nyehhehheh .｡.*☆#6624 | H18: =IFERROR(__xludf.DUMMYFUNCTION("""COMPUTED_VALUE"""),"(512) 750-3148") -> (512) 750-3148 | I18: =IFERROR(__xludf.DUMMYFUNCTION("""COMPUTED_VALUE"""),"Student") -> Student | J18: =IFERROR(__xludf.DUMMYFUNCTION("""COMPUTED_VALUE"""),"$15 Donation, Discord Verification") -> $15 Donation, Discord Verification | O18: =IFERROR(__xludf.DUMMYFUNCTION("""COMPUTED_VALUE"""),"Officer lol") -> Officer lol | P18: =IFERROR(__xludf.DUMMYFUNCTION("IFERROR( IMAGE( ""https://drive.google.com/uc?export=download&id=""&MID( IMPORTRANGE(""18RaQw448NnENcNftounuam8eQyPVXS6StgZUz-RLzHA"",""'UTA Cat Coalition Membership Application'!L""&ROW()-2) ,(FIND(""="", IMPORTRANGE(""18RaQw448NnENcNftounuam8eQyPVXS6St"&"gZUz-RLzHA"",""'UTA Cat Coalition Membership Application'!L""&ROW()-2) ))+1,LEN( IMPORTRANGE(""18RaQw448NnENcNftounuam8eQyPVXS6StgZUz-RLzHA"",""'UTA Cat Coalition Membership Application'!L""&ROW()-2) )-FIND(""="", IMPORTRANGE(""18RaQw448NnENcNftounuam8eQy"&"PVXS6StgZUz-RLzHA"",""'UTA Cat Coalition Membership Application'!L""&ROW()-2) )),1 ) , """")"),"")
A19: =IFERROR(__xludf.DUMMYFUNCTION("""COMPUTED_VALUE"""),44588.81497738426) -> 44588.815 | B19: TRUE | C19: =IF(A19<>"", IFERROR(IF(MONTH(A19) < 6, "Spring ", "Fall ") & IF(MONTH(A19) < 6, YEAR(A19), YEAR(A19) + IF(MONTH(A19) = 12, 1, 0)), ""), "") -> Spring 2022 | D19: =IFERROR(__xludf.DUMMYFUNCTION("""COMPUTED_VALUE"""),"bekahgrace02@gmail.com") -> bekahgrace02@gmail.com | E19: =IFERROR(__xludf.DUMMYFUNCTION("""COMPUTED_VALUE"""),"Rebekah Pomykal ") -> Rebekah Pomykal | F19: =IFERROR(__xludf.DUMMYFUNCTION("""COMPUTED_VALUE"""),"bekah#0564") -> bekah#0564 | H19: =IFERROR(__xludf.DUMMYFUNCTION("""COMPUTED_VALUE"""),"(469) 712-6224") -> (469) 712-6224 | I19: =IFERROR(__xludf.DUMMYFUNCTION("""COMPUTED_VALUE"""),"Student") -> Student | J19: =IFERROR(__xludf.DUMMYFUNCTION("""COMPUTED_VALUE"""),"Food/Litter Donation") -> Food/Litter Donation | O19: =IFERROR(__xludf.DUMMYFUNCTION("""COMPUTED_VALUE"""),"Feeding") -> Feeding | P19: =IFERROR(__xludf.DUMMYFUNCTION("IFERROR( IMAGE( ""https://drive.google.com/uc?export=download&id=""&MID( IMPORTRANGE(""18RaQw448NnENcNftounuam8eQyPVXS6StgZUz-RLzHA"",""'UTA Cat Coalition Membership Application'!L""&ROW()-2) ,(FIND(""="", IMPORTRANGE(""18RaQw448NnENcNftounuam8eQyPVXS6St"&"gZUz-RLzHA"",""'UTA Cat Coalition Membership Application'!L""&ROW()-2) ))+1,LEN( IMPORTRANGE(""18RaQw448NnENcNftounuam8eQyPVXS6StgZUz-RLzHA"",""'UTA Cat Coalition Membership Application'!L""&ROW()-2) )-FIND(""="", IMPORTRANGE(""18RaQw448NnENcNftounuam8eQy"&"PVXS6StgZUz-RLzHA"",""'UTA Cat Coalition Membership Application'!L""&ROW()-2) )),1 ) , """")"),"")
A20: =IFERROR(__xludf.DUMMYFUNCTION("""COMPUTED_VALUE"""),44588.9274662963) -> 44588.927 | B20: TRUE | C20: =IF(A20<>"", IFERROR(IF(MONTH(A20) < 6, "Spring ", "Fall ") & IF(MONTH(A20) < 6, YEAR(A20), YEAR(A20) + IF(MONTH(A20) = 12, 1, 0)), ""), "") -> Spring 2022 | D20: =IFERROR(__xludf.DUMMYFUNCTION("""COMPUTED_VALUE"""),"jtspears2003@gmail.com") -> jtspears2003@gmail.com | E20: =IFERROR(__xludf.DUMMYFUNCTION("""COMPUTED_VALUE"""),"John (JT) Spears") -> John (JT) Spears | F20: =IFERROR(__xludf.DUMMYFUNCTION("""COMPUTED_VALUE"""),"AzureCobalt#1104") -> AzureCobalt#1104 | H20: =IFERROR(__xludf.DUMMYFUNCTION("""COMPUTED_VALUE"""),"(903) 603-8853") -> (903) 603-8853 | I20: =IFERROR(__xludf.DUMMYFUNCTION("""COMPUTED_VALUE"""),"Student") -> Student | J20: =IFERROR(__xludf.DUMMYFUNCTION("""COMPUTED_VALUE"""),"$15 Donation, Discord Verification") -> $15 Donation, Discord Verification | O20: =IFERROR(__xludf.DUMMYFUNCTION("""COMPUTED_VALUE"""),"Fundraising, Feeding") -> Fundraising, Feeding | P20: =IFERROR(__xludf.DUMMYFUNCTION("IFERROR( IMAGE( ""https://drive.google.com/uc?export=download&id=""&MID( IMPORTRANGE(""18RaQw448NnENcNftounuam8eQyPVXS6StgZUz-RLzHA"",""'UTA Cat Coalition Membership Application'!L""&ROW()-2) ,(FIND(""="", IMPORTRANGE(""18RaQw448NnENcNftounuam8eQyPVXS6St"&"gZUz-RLzHA"",""'UTA Cat Coalition Membership Application'!L""&ROW()-2) ))+1,LEN( IMPORTRANGE(""18RaQw448NnENcNftounuam8eQyPVXS6StgZUz-RLzHA"",""'UTA Cat Coalition Membership Application'!L""&ROW()-2) )-FIND(""="", IMPORTRANGE(""18RaQw448NnENcNftounuam8eQy"&"PVXS6StgZUz-RLzHA"",""'UTA Cat Coalition Membership Application'!L""&ROW()-2) )),1 ) , """")"),"")
A21: =IFERROR(__xludf.DUMMYFUNCTION("""COMPUTED_VALUE"""),44588.95508871527) -> 44588.955 | B21: TRUE | C21: =IF(A21<>"", IFERROR(IF(MONTH(A21) < 6, "Spring ", "Fall ") & IF(MONTH(A21) < 6, YEAR(A21), YEAR(A21) + IF(MONTH(A21) = 12, 1, 0)), ""), "") -> Spring 2022 | D21: =IFERROR(__xludf.DUMMYFUNCTION("""COMPUTED_VALUE"""),"lxh6870@mavs.uta.edu") -> lxh6870@mavs.uta.edu | E21: =IFERROR(__xludf.DUMMYFUNCTION("""COMPUTED_VALUE"""),"Lauren Hammond") -> Lauren Hammond | F21: =IFERROR(__xludf.DUMMYFUNCTION("""COMPUTED_VALUE"""),"HammyHammz#2102") -> HammyHammz#2102 | H21: =IFERROR(__xludf.DUMMYFUNCTION("""COMPUTED_VALUE"""),"(214) 551-9956") -> (214) 551-9956 | I21: =IFERROR(__xludf.DUMMYFUNCTION("""COMPUTED_VALUE"""),"Student") -> Student | J21: =IFERROR(__xludf.DUMMYFUNCTION("""COMPUTED_VALUE"""),"$15 Donation, Discord Verification") -> $15 Donation, Discord Verification | O21: =IFERROR(__xludf.DUMMYFUNCTION("""COMPUTED_VALUE"""),"Fundraising, Feeding") -> Fundraising, Feeding | P21: =IFERROR(__xludf.DUMMYFUNCTION("IFERROR( IMAGE( ""https://drive.google.com/uc?export=download&id=""&MID( IMPORTRANGE(""18RaQw448NnENcNftounuam8eQyPVXS6StgZUz-RLzHA"",""'UTA Cat Coalition Membership Application'!L""&ROW()-2) ,(FIND(""="", IMPORTRANGE(""18RaQw448NnENcNftounuam8eQyPVXS6St"&"gZUz-RLzHA"",""'UTA Cat Coalition Membership Application'!L""&ROW()-2) ))+1,LEN( IMPORTRANGE(""18RaQw448NnENcNftounuam8eQyPVXS6StgZUz-RLzHA"",""'UTA Cat Coalition Membership Application'!L""&ROW()-2) )-FIND(""="", IMPORTRANGE(""18RaQw448NnENcNftounuam8eQy"&"PVXS6StgZUz-RLzHA"",""'UTA Cat Coalition Membership Application'!L""&ROW()-2) )),1 ) , """")"),"")
A22: =IFERROR(__xludf.DUMMYFUNCTION("""COMPUTED_VALUE"""),44589.60046622685) -> 44589.6 | B22: TRUE | C22: =IF(A22<>"", IFERROR(IF(MONTH(A22) < 6, "Spring ", "Fall ") & IF(MONTH(A22) < 6, YEAR(A22), YEAR(A22) + IF(MONTH(A22) = 12, 1, 0)), ""), "") -> Spring 2022 | D22: =IFERROR(__xludf.DUMMYFUNCTION("""COMPUTED_VALUE"""),"lynnpnguyen1112@gmail.com") -> lynnpnguyen1112@gmail.com | E22: =IFERROR(__xludf.DUMMYFUNCTION("""COMPUTED_VALUE"""),"Lynn Nguyen") -> Lynn Nguyen | F22: =IFERROR(__xludf.DUMMYFUNCTION("""COMPUTED_VALUE"""),"p.lynn.n#9278") -> p.lynn.n#9278 | H22: =IFERROR(__xludf.DUMMYFUNCTION("""COMPUTED_VALUE"""),"(817) 673-7966") -> (817) 673-7966 | I22: =IFERROR(__xludf.DUMMYFUNCTION("""COMPUTED_VALUE"""),"Student") -> Student | J22: =IFERROR(__xludf.DUMMYFUNCTION("""COMPUTED_VALUE"""),"") | O22: =IFERROR(__xludf.DUMMYFUNCTION("""COMPUTED_VALUE"""),"PR, Feeding") -> PR, Feeding | P22: =IFERROR(__xludf.DUMMYFUNCTION("IFERROR( IMAGE( ""https://drive.google.com/uc?export=download&id=""&MID( IMPORTRANGE(""18RaQw448NnENcNftounuam8eQyPVXS6StgZUz-RLzHA"",""'UTA Cat Coalition Membership Application'!L""&ROW()-2) ,(FIND(""="", IMPORTRANGE(""18RaQw448NnENcNftounuam8eQyPVXS6St"&"gZUz-RLzHA"",""'UTA Cat Coalition Membership Application'!L""&ROW()-2) ))+1,LEN( IMPORTRANGE(""18RaQw448NnENcNftounuam8eQyPVXS6StgZUz-RLzHA"",""'UTA Cat Coalition Membership Application'!L""&ROW()-2) )-FIND(""="", IMPORTRANGE(""18RaQw448NnENcNftounuam8eQy"&"PVXS6StgZUz-RLzHA"",""'UTA Cat Coalition Membership Application'!L""&ROW()-2) )),1 ) , """")"),"")
A23: =IFERROR(__xludf.DUMMYFUNCTION("""COMPUTED_VALUE"""),44589.636209398144) -> 44589.636 | B23: TRUE | C23: =IF(A23<>"", IFERROR(IF(MONTH(A23) < 6, "Spring ", "Fall ") & IF(MONTH(A23) < 6, YEAR(A23), YEAR(A23) + IF(MONTH(A23) = 12, 1, 0)), ""), "") -> Spring 2022 | D23: =IFERROR(__xludf.DUMMYFUNCTION("""COMPUTED_VALUE"""),"sjm3161@mavs.uta.edu") -> sjm3161@mavs.uta.edu | E23: =IFERROR(__xludf.DUMMYFUNCTION("""COMPUTED_VALUE"""),"Silvia Jessica Mostacedo Marasovic") -> Silvia Jessica Mostacedo Marasovic | F23: =IFERROR(__xludf.DUMMYFUNCTION("""COMPUTED_VALUE"""),"Jessica M.#2936") -> Jessica M.#2936 | H23: =IFERROR(__xludf.DUMMYFUNCTION("""COMPUTED_VALUE"""),"(352) 363-4634") -> (352) 363-4634 | I23: =IFERROR(__xludf.DUMMYFUNCTION("""COMPUTED_VALUE"""),"Student") -> Student | J23: =IFERROR(__xludf.DUMMYFUNCTION("""COMPUTED_VALUE"""),"Food/Litter Donation") -> Food/Litter Donation | O23: =IFERROR(__xludf.DUMMYFUNCTION("""COMPUTED_VALUE"""),"Feeding, Shelter Maintenance") -> Feeding, Shelter Maintenance | P23: =IFERROR(__xludf.DUMMYFUNCTION("IFERROR( IMAGE( ""https://drive.google.com/uc?export=download&id=""&MID( IMPORTRANGE(""18RaQw448NnENcNftounuam8eQyPVXS6StgZUz-RLzHA"",""'UTA Cat Coalition Membership Application'!L""&ROW()-2) ,(FIND(""="", IMPORTRANGE(""18RaQw448NnENcNftounuam8eQyPVXS6St"&"gZUz-RLzHA"",""'UTA Cat Coalition Membership Application'!L""&ROW()-2) ))+1,LEN( IMPORTRANGE(""18RaQw448NnENcNftounuam8eQyPVXS6StgZUz-RLzHA"",""'UTA Cat Coalition Membership Application'!L""&ROW()-2) )-FIND(""="", IMPORTRANGE(""18RaQw448NnENcNftounuam8eQy"&"PVXS6StgZUz-RLzHA"",""'UTA Cat Coalition Membership Application'!L""&ROW()-2) )),1 ) , """")"),"")
A24: =IFERROR(__xludf.DUMMYFUNCTION("""COMPUTED_VALUE"""),44589.69398094907) -> 44589.694 | B24: TRUE | C24: =IF(A24<>"", IFERROR(IF(MONTH(A24) < 6, "Spring ", "Fall ") & IF(MONTH(A24) < 6, YEAR(A24), YEAR(A24) + IF(MONTH(A24) = 12, 1, 0)), ""), "") -> Spring 2022 | D24: =IFERROR(__xludf.DUMMYFUNCTION("""COMPUTED_VALUE"""),"angelina.rivera2@mavs.uta.edu") -> angelina.rivera2@mavs.uta.edu | E24: =IFERROR(__xludf.DUMMYFUNCTION("""COMPUTED_VALUE"""),"Angelina Rivera") -> Angelina Rivera | F24: =IFERROR(__xludf.DUMMYFUNCTION("""COMPUTED_VALUE"""),"AngRiv#5967") -> AngRiv#5967 | H24: =IFERROR(__xludf.DUMMYFUNCTION("""COMPUTED_VALUE"""),"(254) 205-7492") -> (254) 205-7492 | I24: =IFERROR(__xludf.DUMMYFUNCTION("""COMPUTED_VALUE"""),"Student") -> Student | J24: =IFERROR(__xludf.DUMMYFUNCTION("""COMPUTED_VALUE"""),"$15 Donation, Discord Verification") -> $15 Donation, Discord Verification | O24: =IFERROR(__xludf.DUMMYFUNCTION("""COMPUTED_VALUE"""),"Fundraising, PR, Membership, TNR, Overnight TNR, Feeding, Fostering, Shelter Maintenance") -> Fundraising, PR, Membership, TNR, Overnight TNR, Feeding, Fostering, Shelter Maintenance | P24: =IFERROR(__xludf.DUMMYFUNCTION("IFERROR( IMAGE( ""https://drive.google.com/uc?export=download&id=""&MID( IMPORTRANGE(""18RaQw448NnENcNftounuam8eQyPVXS6StgZUz-RLzHA"",""'UTA Cat Coalition Membership Application'!L""&ROW()-2) ,(FIND(""="", IMPORTRANGE(""18RaQw448NnENcNftounuam8eQyPVXS6St"&"gZUz-RLzHA"",""'UTA Cat Coalition Membership Application'!L""&ROW()-2) ))+1,LEN( IMPORTRANGE(""18RaQw448NnENcNftounuam8eQyPVXS6StgZUz-RLzHA"",""'UTA Cat Coalition Membership Application'!L""&ROW()-2) )-FIND(""="", IMPORTRANGE(""18RaQw448NnENcNftounuam8eQy"&"PVXS6StgZUz-RLzHA"",""'UTA Cat Coalition Membership Application'!L""&ROW()-2) )),1 ) , """")"),"")
A25: =IFERROR(__xludf.DUMMYFUNCTION("""COMPUTED_VALUE"""),44590.613363321754) -> 44590.613 | B25: TRUE | C25: =IF(A25<>"", IFERROR(IF(MONTH(A25) < 6, "Spring ", "Fall ") & IF(MONTH(A25) < 6, YEAR(A25), YEAR(A25) + IF(MONTH(A25) = 12, 1, 0)), ""), "") -> Spring 2022 | D25: =IFERROR(__xludf.DUMMYFUNCTION("""COMPUTED_VALUE"""),"pierson.moore@mavs.uta.edu") -> pierson.moore@mavs.uta.edu | E25: =IFERROR(__xludf.DUMMYFUNCTION("""COMPUTED_VALUE"""),"Pierson Moore") -> Pierson Moore | F25: =IFERROR(__xludf.DUMMYFUNCTION("""COMPUTED_VALUE"""),"P Raven#0012") -> P Raven#0012 | H25: =IFERROR(__xludf.DUMMYFUNCTION("""COMPUTED_VALUE"""),"(817) 965-4410") -> (817) 965-4410 | I25: =IFERROR(__xludf.DUMMYFUNCTION("""COMPUTED_VALUE"""),"Student") -> Student | J25: =IFERROR(__xludf.DUMMYFUNCTION("""COMPUTED_VALUE"""),"$15 Donation, Discord Verification") -> $15 Donation, Discord Verification | O25: =IFERROR(__xludf.DUMMYFUNCTION("""COMPUTED_VALUE"""),"not sure yet") -> not sure yet | P25: =IFERROR(__xludf.DUMMYFUNCTION("IFERROR( IMAGE( ""https://drive.google.com/uc?export=download&id=""&MID( IMPORTRANGE(""18RaQw448NnENcNftounuam8eQyPVXS6StgZUz-RLzHA"",""'UTA Cat Coalition Membership Application'!L""&ROW()-2) ,(FIND(""="", IMPORTRANGE(""18RaQw448NnENcNftounuam8eQyPVXS6St"&"gZUz-RLzHA"",""'UTA Cat Coalition Membership Application'!L""&ROW()-2) ))+1,LEN( IMPORTRANGE(""18RaQw448NnENcNftounuam8eQyPVXS6StgZUz-RLzHA"",""'UTA Cat Coalition Membership Application'!L""&ROW()-2) )-FIND(""="", IMPORTRANGE(""18RaQw448NnENcNftounuam8eQy"&"PVXS6StgZUz-RLzHA"",""'UTA Cat Coalition Membership Application'!L""&ROW()-2) )),1 ) , """")"),"")
A26: =IFERROR(__xludf.DUMMYFUNCTION("""COMPUTED_VALUE"""),44593.71188430555) -> 44593.712 | B26: TRUE | C26: =IF(A26<>"", IFERROR(IF(MONTH(A26) < 6, "Spring ", "Fall ") & IF(MONTH(A26) < 6, YEAR(A26), YEAR(A26) + IF(MONTH(A26) = 12, 1, 0)), ""), "") -> Spring 2022 | D26: =IFERROR(__xludf.DUMMYFUNCTION("""COMPUTED_VALUE"""),"mag9071@mavs.uta.edu") -> mag9071@mavs.uta.edu | E26: =IFERROR(__xludf.DUMMYFUNCTION("""COMPUTED_VALUE"""),"Mary Abby Goss") -> Mary Abby Goss | F26: =IFERROR(__xludf.DUMMYFUNCTION("""COMPUTED_VALUE"""),"Mary Abby") -> Mary Abby | H26: =IFERROR(__xludf.DUMMYFUNCTION("""COMPUTED_VALUE"""),"(512) 994-7272") -> (512) 994-7272 | I26: =IFERROR(__xludf.DUMMYFUNCTION("""COMPUTED_VALUE"""),"Student") -> Student | J26: =IFERROR(__xludf.DUMMYFUNCTION("""COMPUTED_VALUE"""),"$15 Donation, Discord Verification") -> $15 Donation, Discord Verification | O26: =IFERROR(__xludf.DUMMYFUNCTION("""COMPUTED_VALUE"""),"Fundraising") -> Fundraising | P26: =IFERROR(__xludf.DUMMYFUNCTION("IFERROR( IMAGE( ""https://drive.google.com/uc?export=download&id=""&MID( IMPORTRANGE(""18RaQw448NnENcNftounuam8eQyPVXS6StgZUz-RLzHA"",""'UTA Cat Coalition Membership Application'!L""&ROW()-2) ,(FIND(""="", IMPORTRANGE(""18RaQw448NnENcNftounuam8eQyPVXS6St"&"gZUz-RLzHA"",""'UTA Cat Coalition Membership Application'!L""&ROW()-2) ))+1,LEN( IMPORTRANGE(""18RaQw448NnENcNftounuam8eQyPVXS6StgZUz-RLzHA"",""'UTA Cat Coalition Membership Application'!L""&ROW()-2) )-FIND(""="", IMPORTRANGE(""18RaQw448NnENcNftounuam8eQy"&"PVXS6StgZUz-RLzHA"",""'UTA Cat Coalition Membership Application'!L""&ROW()-2) )),1 ) , """")"),"")
A27: =IFERROR(__xludf.DUMMYFUNCTION("""COMPUTED_VALUE"""),44593.71662423611) -> 44593.717 | B27: TRUE | C27: =IF(A27<>"", IFERROR(IF(MONTH(A27) < 6, "Spring ", "Fall ") & IF(MONTH(A27) < 6, YEAR(A27), YEAR(A27) + IF(MONTH(A27) = 12, 1, 0)), ""), "") -> Spring 2022 | D27: =IFERROR(__xludf.DUMMYFUNCTION("""COMPUTED_VALUE"""),"ryan.johnson2@mavs.uta.edu") -> ryan.johnson2@mavs.uta.edu | E27: =IFERROR(__xludf.DUMMYFUNCTION("""COMPUTED_VALUE"""),"Ryan Johnson") -> Ryan Johnson | F27: =IFERROR(__xludf.DUMMYFUNCTION("""COMPUTED_VALUE"""),"guppy#7190") -> guppy#7190 | H27: =IFERROR(__xludf.DUMMYFUNCTION("""COMPUTED_VALUE"""),"(409) 233-7926") -> (409) 233-7926 | I27: =IFERROR(__xludf.DUMMYFUNCTION("""COMPUTED_VALUE"""),"Student") -> Student | J27: =IFERROR(__xludf.DUMMYFUNCTION("""COMPUTED_VALUE"""),"$15 Donation, Discord Verification") -> $15 Donation, Discord Verification | O27: =IFERROR(__xludf.DUMMYFUNCTION("""COMPUTED_VALUE"""),"Feeding, Shelter Maintenance") -> Feeding, Shelter Maintenance | P27: =IFERROR(__xludf.DUMMYFUNCTION("IFERROR( IMAGE( ""https://drive.google.com/uc?export=download&id=""&MID( IMPORTRANGE(""18RaQw448NnENcNftounuam8eQyPVXS6StgZUz-RLzHA"",""'UTA Cat Coalition Membership Application'!L""&ROW()-2) ,(FIND(""="", IMPORTRANGE(""18RaQw448NnENcNftounuam8eQyPVXS6St"&"gZUz-RLzHA"",""'UTA Cat Coalition Membership Application'!L""&ROW()-2) ))+1,LEN( IMPORTRANGE(""18RaQw448NnENcNftounuam8eQyPVXS6StgZUz-RLzHA"",""'UTA Cat Coalition Membership Application'!L""&ROW()-2) )-FIND(""="", IMPORTRANGE(""18RaQw448NnENcNftounuam8eQy"&"PVXS6StgZUz-RLzHA"",""'UTA Cat Coalition Membership Application'!L""&ROW()-2) )),1 ) , """")"),"")
A28: =IFERROR(__xludf.DUMMYFUNCTION("""COMPUTED_VALUE"""),44593.74211875) -> 44593.742 | B28: TRUE | C28: =IF(A28<>"", IFERROR(IF(MONTH(A28) < 6, "Spring ", "Fall ") & IF(MONTH(A28) < 6, YEAR(A28), YEAR(A28) + IF(MONTH(A28) = 12, 1, 0)), ""), "") -> Spring 2022 | D28: =IFERROR(__xludf.DUMMYFUNCTION("""COMPUTED_VALUE"""),"hxg4569@mavs.uta.edu") -> hxg4569@mavs.uta.edu | E28: =IFERROR(__xludf.DUMMYFUNCTION("""COMPUTED_VALUE"""),"Ren Graham") -> Ren Graham | F28: =IFERROR(__xludf.DUMMYFUNCTION("""COMPUTED_VALUE"""),"chickenwithastick#8585") -> chickenwithastick#8585 | H28: =IFERROR(__xludf.DUMMYFUNCTION("""COMPUTED_VALUE"""),"(972) 697-3396") -> (972) 697-3396 | I28: =IFERROR(__xludf.DUMMYFUNCTION("""COMPUTED_VALUE"""),"Student") -> Student | J28: =IFERROR(__xludf.DUMMYFUNCTION("""COMPUTED_VALUE"""),"$15 Donation, Discord Verification") -> $15 Donation, Discord Verification | O28: =IFERROR(__xludf.DUMMYFUNCTION("""COMPUTED_VALUE"""),"Feeding") -> Feeding | P28: =IFERROR(__xludf.DUMMYFUNCTION("IFERROR( IMAGE( ""https://drive.google.com/uc?export=download&id=""&MID( IMPORTRANGE(""18RaQw448NnENcNftounuam8eQyPVXS6StgZUz-RLzHA"",""'UTA Cat Coalition Membership Application'!L""&ROW()-2) ,(FIND(""="", IMPORTRANGE(""18RaQw448NnENcNftounuam8eQyPVXS6St"&"gZUz-RLzHA"",""'UTA Cat Coalition Membership Application'!L""&ROW()-2) ))+1,LEN( IMPORTRANGE(""18RaQw448NnENcNftounuam8eQyPVXS6StgZUz-RLzHA"",""'UTA Cat Coalition Membership Application'!L""&ROW()-2) )-FIND(""="", IMPORTRANGE(""18RaQw448NnENcNftounuam8eQy"&"PVXS6StgZUz-RLzHA"",""'UTA Cat Coalition Membership Application'!L""&ROW()-2) )),1 ) , """")"),"")
A29: =IFERROR(__xludf.DUMMYFUNCTION("""COMPUTED_VALUE"""),44593.75425873842) -> 44593.754 | B29: TRUE | C29: =IF(A29<>"", IFERROR(IF(MONTH(A29) < 6, "Spring ", "Fall ") & IF(MONTH(A29) < 6, YEAR(A29), YEAR(A29) + IF(MONTH(A29) = 12, 1, 0)), ""), "") -> Spring 2022 | D29: =IFERROR(__xludf.DUMMYFUNCTION("""COMPUTED_VALUE"""),"jordhard@hotmail.com") -> jordhard@hotmail.com | E29: =IFERROR(__xludf.DUMMYFUNCTION("""COMPUTED_VALUE"""),"Jordan Hardin") -> Jordan Hardin | F29: =IFERROR(__xludf.DUMMYFUNCTION("""COMPUTED_VALUE"""),"Kitadan") -> Kitadan | H29: =IFERROR(__xludf.DUMMYFUNCTION("""COMPUTED_VALUE"""),"(817) 201-8529") -> (817) 201-8529 | I29: =IFERROR(__xludf.DUMMYFUNCTION("""COMPUTED_VALUE"""),"Community Member") -> Community Member | J29: =IFERROR(__xludf.DUMMYFUNCTION("""COMPUTED_VALUE"""),"Food/Litter Donation") -> Food/Litter Donation | O29: =IFERROR(__xludf.DUMMYFUNCTION("""COMPUTED_VALUE"""),"Feeding") -> Feeding | P29: =IFERROR(__xludf.DUMMYFUNCTION("IFERROR( IMAGE( ""https://drive.google.com/uc?export=download&id=""&MID( IMPORTRANGE(""18RaQw448NnENcNftounuam8eQyPVXS6StgZUz-RLzHA"",""'UTA Cat Coalition Membership Application'!L""&ROW()-2) ,(FIND(""="", IMPORTRANGE(""18RaQw448NnENcNftounuam8eQyPVXS6St"&"gZUz-RLzHA"",""'UTA Cat Coalition Membership Application'!L""&ROW()-2) ))+1,LEN( IMPORTRANGE(""18RaQw448NnENcNftounuam8eQyPVXS6StgZUz-RLzHA"",""'UTA Cat Coalition Membership Application'!L""&ROW()-2) )-FIND(""="", IMPORTRANGE(""18RaQw448NnENcNftounuam8eQy"&"PVXS6StgZUz-RLzHA"",""'UTA Cat Coalition Membership Application'!L""&ROW()-2) )),1 ) , """")"),"")
A30: =IFERROR(__xludf.DUMMYFUNCTION("""COMPUTED_VALUE"""),44593.76085103009) -> 44593.761 | B30: TRUE | C30: =IF(A30<>"", IFERROR(IF(MONTH(A30) < 6, "Spring ", "Fall ") & IF(MONTH(A30) < 6, YEAR(A30), YEAR(A30) + IF(MONTH(A30) = 12, 1, 0)), ""), "") -> Spring 2022 | D30: =IFERROR(__xludf.DUMMYFUNCTION("""COMPUTED_VALUE"""),"mel5887@mavs.uta.edu") -> mel5887@mavs.uta.edu | E30: =IFERROR(__xludf.DUMMYFUNCTION("""COMPUTED_VALUE"""),"Maclain LeMoine") -> Maclain LeMoine | F30: =IFERROR(__xludf.DUMMYFUNCTION("""COMPUTED_VALUE"""),"Hufflepuffmouse#1561") -> Hufflepuffmouse#1561 | H30: =IFERROR(__xludf.DUMMYFUNCTION("""COMPUTED_VALUE"""),"(817) 233-1119") -> (817) 233-1119 | I30: =IFERROR(__xludf.DUMMYFUNCTION("""COMPUTED_VALUE"""),"Student") -> Student | J30: =IFERROR(__xludf.DUMMYFUNCTION("""COMPUTED_VALUE"""),"Food/Litter Donation") -> Food/Litter Donation | O30: =IFERROR(__xludf.DUMMYFUNCTION("""COMPUTED_VALUE"""),"Fundraising, PR, Membership, TNR, Feeding, Shelter Maintenance") -> Fundraising, PR, Membership, TNR, Feeding, Shelter Maintenance | P30: =IFERROR(__xludf.DUMMYFUNCTION("IFERROR( IMAGE( ""https://drive.google.com/uc?export=download&id=""&MID( IMPORTRANGE(""18RaQw448NnENcNftounuam8eQyPVXS6StgZUz-RLzHA"",""'UTA Cat Coalition Membership Application'!L""&ROW()-2) ,(FIND(""="", IMPORTRANGE(""18RaQw448NnENcNftounuam8eQyPVXS6St"&"gZUz-RLzHA"",""'UTA Cat Coalition Membership Application'!L""&ROW()-2) ))+1,LEN( IMPORTRANGE(""18RaQw448NnENcNftounuam8eQyPVXS6StgZUz-RLzHA"",""'UTA Cat Coalition Membership Application'!L""&ROW()-2) )-FIND(""="", IMPORTRANGE(""18RaQw448NnENcNftounuam8eQy"&"PVXS6StgZUz-RLzHA"",""'UTA Cat Coalition Membership Application'!L""&ROW()-2) )),1 ) , """")"),"")
A31: =IFERROR(__xludf.DUMMYFUNCTION("""COMPUTED_VALUE"""),44593.76254974537) -> 44593.763 | B31: TRUE | C31: =IF(A31<>"", IFERROR(IF(MONTH(A31) < 6, "Spring ", "Fall ") & IF(MONTH(A31) < 6, YEAR(A31), YEAR(A31) + IF(MONTH(A31) = 12, 1, 0)), ""), "") -> Spring 2022 | D31: =IFERROR(__xludf.DUMMYFUNCTION("""COMPUTED_VALUE"""),"caroline.carter@mavs.uta.edu") -> caroline.carter@mavs.uta.edu | E31: =IFERROR(__xludf.DUMMYFUNCTION("""COMPUTED_VALUE"""),"Caroline Carter") -> Caroline Carter | F31: =IFERROR(__xludf.DUMMYFUNCTION("""COMPUTED_VALUE"""),"Caroline C#3300") -> Caroline C#3300 | H31: =IFERROR(__xludf.DUMMYFUNCTION("""COMPUTED_VALUE"""),"(181) 731-9650") -> (181) 731-9650 | I31: =IFERROR(__xludf.DUMMYFUNCTION("""COMPUTED_VALUE"""),"Student") -> Student | J31: =IFERROR(__xludf.DUMMYFUNCTION("""COMPUTED_VALUE"""),"Food/Litter Donation") -> Food/Litter Donation | O31: =IFERROR(__xludf.DUMMYFUNCTION("""COMPUTED_VALUE"""),"Fundraising") -> Fundraising | P31: =IFERROR(__xludf.DUMMYFUNCTION("IFERROR( IMAGE( ""https://drive.google.com/uc?export=download&id=""&MID( IMPORTRANGE(""18RaQw448NnENcNftounuam8eQyPVXS6StgZUz-RLzHA"",""'UTA Cat Coalition Membership Application'!L""&ROW()-2) ,(FIND(""="", IMPORTRANGE(""18RaQw448NnENcNftounuam8eQyPVXS6St"&"gZUz-RLzHA"",""'UTA Cat Coalition Membership Application'!L""&ROW()-2) ))+1,LEN( IMPORTRANGE(""18RaQw448NnENcNftounuam8eQyPVXS6StgZUz-RLzHA"",""'UTA Cat Coalition Membership Application'!L""&ROW()-2) )-FIND(""="", IMPORTRANGE(""18RaQw448NnENcNftounuam8eQy"&"PVXS6StgZUz-RLzHA"",""'UTA Cat Coalition Membership Application'!L""&ROW()-2) )),1 ) , """")"),"")
A32: =IFERROR(__xludf.DUMMYFUNCTION("""COMPUTED_VALUE"""),44593.90148945602) -> 44593.901 | B32: TRUE | C32: =IF(A32<>"", IFERROR(IF(MONTH(A32) < 6, "Spring ", "Fall ") & IF(MONTH(A32) < 6, YEAR(A32), YEAR(A32) + IF(MONTH(A32) = 12, 1, 0)), ""), "") -> Spring 2022 | D32: =IFERROR(__xludf.DUMMYFUNCTION("""COMPUTED_VALUE"""),"tnr1037@mavs.uta.edu") -> tnr1037@mavs.uta.edu | E32: =IFERROR(__xludf.DUMMYFUNCTION("""COMPUTED_VALUE"""),"Taryn Rila-Smith") -> Taryn Rila-Smith | F32: =IFERROR(__xludf.DUMMYFUNCTION("""COMPUTED_VALUE"""),"Rocktail1202 #8276") -> Rocktail1202 #8276 | H32: =IFERROR(__xludf.DUMMYFUNCTION("""COMPUTED_VALUE"""),"") | I32: =IFERROR(__xludf.DUMMYFUNCTION("""COMPUTED_VALUE"""),"Student") -> Student | J32: =IFERROR(__xludf.DUMMYFUNCTION("""COMPUTED_VALUE"""),"$15 Donation, Discord Verification") -> $15 Donation, Discord Verification | O32: =IFERROR(__xludf.DUMMYFUNCTION("""COMPUTED_VALUE"""),"TNR, Feeding") -> TNR, Feeding | P32: =IFERROR(__xludf.DUMMYFUNCTION("IFERROR( IMAGE( ""https://drive.google.com/uc?export=download&id=""&MID( IMPORTRANGE(""18RaQw448NnENcNftounuam8eQyPVXS6StgZUz-RLzHA"",""'UTA Cat Coalition Membership Application'!L""&ROW()-2) ,(FIND(""="", IMPORTRANGE(""18RaQw448NnENcNftounuam8eQyPVXS6St"&"gZUz-RLzHA"",""'UTA Cat Coalition Membership Application'!L""&ROW()-2) ))+1,LEN( IMPORTRANGE(""18RaQw448NnENcNftounuam8eQyPVXS6StgZUz-RLzHA"",""'UTA Cat Coalition Membership Application'!L""&ROW()-2) )-FIND(""="", IMPORTRANGE(""18RaQw448NnENcNftounuam8eQy"&"PVXS6StgZUz-RLzHA"",""'UTA Cat Coalition Membership Application'!L""&ROW()-2) )),1 ) , """")"),"")
A33: =IFERROR(__xludf.DUMMYFUNCTION("""COMPUTED_VALUE"""),44593.94484428241) -> 44593.945 | B33: TRUE | C33: =IF(A33<>"", IFERROR(IF(MONTH(A33) < 6, "Spring ", "Fall ") & IF(MONTH(A33) < 6, YEAR(A33), YEAR(A33) + IF(MONTH(A33) = 12, 1, 0)), ""), "") -> Spring 2022 | D33: =IFERROR(__xludf.DUMMYFUNCTION("""COMPUTED_VALUE"""),"ivone.adame@mavs.uta.edu") -> ivone.adame@mavs.uta.edu | E33: =IFERROR(__xludf.DUMMYFUNCTION("""COMPUTED_VALUE"""),"Ivone Adame ") -> Ivone Adame | F33: =IFERROR(__xludf.DUMMYFUNCTION("""COMPUTED_VALUE"""),"Ivone#9713") -> Ivone#9713 | H33: =IFERROR(__xludf.DUMMYFUNCTION("""COMPUTED_VALUE"""),"(214) 677-5805") -> (214) 677-5805 | I33: =IFERROR(__xludf.DUMMYFUNCTION("""COMPUTED_VALUE"""),"Student") -> Student | J33: =IFERROR(__xludf.DUMMYFUNCTION("""COMPUTED_VALUE"""),"$15 Donation, Discord Verification") -> $15 Donation, Discord Verification | O33: =IFERROR(__xludf.DUMMYFUNCTION("""COMPUTED_VALUE"""),"Fundraising, TNR") -> Fundraising, TNR | P33: =IFERROR(__xludf.DUMMYFUNCTION("IFERROR( IMAGE( ""https://drive.google.com/uc?export=download&id=""&MID( IMPORTRANGE(""18RaQw448NnENcNftounuam8eQyPVXS6StgZUz-RLzHA"",""'UTA Cat Coalition Membership Application'!L""&ROW()-2) ,(FIND(""="", IMPORTRANGE(""18RaQw448NnENcNftounuam8eQyPVXS6St"&"gZUz-RLzHA"",""'UTA Cat Coalition Membership Application'!L""&ROW()-2) ))+1,LEN( IMPORTRANGE(""18RaQw448NnENcNftounuam8eQyPVXS6StgZUz-RLzHA"",""'UTA Cat Coalition Membership Application'!L""&ROW()-2) )-FIND(""="", IMPORTRANGE(""18RaQw448NnENcNftounuam8eQy"&"PVXS6StgZUz-RLzHA"",""'UTA Cat Coalition Membership Application'!L""&ROW()-2) )),1 ) , """")"),"")
A34: =IFERROR(__xludf.DUMMYFUNCTION("""COMPUTED_VALUE"""),44593.95271618056) -> 44593.953 | B34: TRUE | C34: =IF(A34<>"", IFERROR(IF(MONTH(A34) < 6, "Spring ", "Fall ") & IF(MONTH(A34) < 6, YEAR(A34), YEAR(A34) + IF(MONTH(A34) = 12, 1, 0)), ""), "") -> Spring 2022 | D34: =IFERROR(__xludf.DUMMYFUNCTION("""COMPUTED_VALUE"""),"juliet.garrison@mavs.uta.edu") -> juliet.garrison@mavs.uta.edu | E34: =IFERROR(__xludf.DUMMYFUNCTION("""COMPUTED_VALUE"""),"Juliet Garrison") -> Juliet Garrison | F34: =IFERROR(__xludf.DUMMYFUNCTION("""COMPUTED_VALUE"""),"Juliet Garrison#0912") -> Juliet Garrison#0912 | H34: =IFERROR(__xludf.DUMMYFUNCTION("""COMPUTED_VALUE"""),"(817) 925-7078") -> (817) 925-7078 | I34: =IFERROR(__xludf.DUMMYFUNCTION("""COMPUTED_VALUE"""),"Student") -> Student | J34: =IFERROR(__xludf.DUMMYFUNCTION("""COMPUTED_VALUE"""),"$15 Donation, Discord Verification") -> $15 Donation, Discord Verification | O34: =IFERROR(__xludf.DUMMYFUNCTION("""COMPUTED_VALUE"""),"Fundraising, PR") -> Fundraising, PR | P34: =IFERROR(__xludf.DUMMYFUNCTION("IFERROR( IMAGE( ""https://drive.google.com/uc?export=download&id=""&MID( IMPORTRANGE(""18RaQw448NnENcNftounuam8eQyPVXS6StgZUz-RLzHA"",""'UTA Cat Coalition Membership Application'!L""&ROW()-2) ,(FIND(""="", IMPORTRANGE(""18RaQw448NnENcNftounuam8eQyPVXS6St"&"gZUz-RLzHA"",""'UTA Cat Coalition Membership Application'!L""&ROW()-2) ))+1,LEN( IMPORTRANGE(""18RaQw448NnENcNftounuam8eQyPVXS6StgZUz-RLzHA"",""'UTA Cat Coalition Membership Application'!L""&ROW()-2) )-FIND(""="", IMPORTRANGE(""18RaQw448NnENcNftounuam8eQy"&"PVXS6StgZUz-RLzHA"",""'UTA Cat Coalition Membership Application'!L""&ROW()-2) )),1 ) , """")"),"")
A35: =IFERROR(__xludf.DUMMYFUNCTION("""COMPUTED_VALUE"""),44599.40634184028) -> 44599.406 | B35: TRUE | C35: =IF(A35<>"", IFERROR(IF(MONTH(A35) < 6, "Spring ", "Fall ") & IF(MONTH(A35) < 6, YEAR(A35), YEAR(A35) + IF(MONTH(A35) = 12, 1, 0)), ""), "") -> Spring 2022 | D35: =IFERROR(__xludf.DUMMYFUNCTION("""COMPUTED_VALUE"""),"alyssa.gonzalez6@mavs.uta.edu") -> alyssa.gonzalez6@mavs.uta.edu | E35: =IFERROR(__xludf.DUMMYFUNCTION("""COMPUTED_VALUE"""),"Alyssa V. Gonzalez") -> Alyssa V. Gonzalez | F35: =IFERROR(__xludf.DUMMYFUNCTION("""COMPUTED_VALUE"""),"AVGforAverage#2818") -> AVGforAverage#2818 | H35: =IFERROR(__xludf.DUMMYFUNCTION("""COMPUTED_VALUE"""),"(214) 240-4043") -> (214) 240-4043 | I35: =IFERROR(__xludf.DUMMYFUNCTION("""COMPUTED_VALUE"""),"Student") -> Student | J35: =IFERROR(__xludf.DUMMYFUNCTION("""COMPUTED_VALUE"""),"$15 Donation, Discord Verification") -> $15 Donation, Discord Verification | O35: =IFERROR(__xludf.DUMMYFUNCTION("""COMPUTED_VALUE"""),"Feeding, Shelter Maintenance") -> Feeding, Shelter Maintenance | P35: =IFERROR(__xludf.DUMMYFUNCTION("IFERROR( IMAGE( ""https://drive.google.com/uc?export=download&id=""&MID( IMPORTRANGE(""18RaQw448NnENcNftounuam8eQyPVXS6StgZUz-RLzHA"",""'UTA Cat Coalition Membership Application'!L""&ROW()-2) ,(FIND(""="", IMPORTRANGE(""18RaQw448NnENcNftounuam8eQyPVXS6St"&"gZUz-RLzHA"",""'UTA Cat Coalition Membership Application'!L""&ROW()-2) ))+1,LEN( IMPORTRANGE(""18RaQw448NnENcNftounuam8eQyPVXS6StgZUz-RLzHA"",""'UTA Cat Coalition Membership Application'!L""&ROW()-2) )-FIND(""="", IMPORTRANGE(""18RaQw448NnENcNftounuam8eQy"&"PVXS6StgZUz-RLzHA"",""'UTA Cat Coalition Membership Application'!L""&ROW()-2) )),1 ) , """")"),"")
A36: =IFERROR(__xludf.DUMMYFUNCTION("""COMPUTED_VALUE"""),44600.81978478009) -> 44600.82 | B36: TRUE | C36: =IF(A36<>"", IFERROR(IF(MONTH(A36) < 6, "Spring ", "Fall ") & IF(MONTH(A36) < 6, YEAR(A36), YEAR(A36) + IF(MONTH(A36) = 12, 1, 0)), ""), "") -> Spring 2022 | D36: =IFERROR(__xludf.DUMMYFUNCTION("""COMPUTED_VALUE"""),"vgk7073@mavs.uta.edu") -> vgk7073@mavs.uta.edu | E36: =IFERROR(__xludf.DUMMYFUNCTION("""COMPUTED_VALUE"""),"Vivian Kenny") -> Vivian Kenny | F36: =IFERROR(__xludf.DUMMYFUNCTION("""COMPUTED_VALUE"""),"Vivenette#7011") -> Vivenette#7011 | H36: =IFERROR(__xludf.DUMMYFUNCTION("""COMPUTED_VALUE"""),"(214) 392-7065") -> (214) 392-7065 | I36: =IFERROR(__xludf.DUMMYFUNCTION("""COMPUTED_VALUE"""),"Student") -> Student | J36: =IFERROR(__xludf.DUMMYFUNCTION("""COMPUTED_VALUE"""),"$15 Donation, Discord Verification") -> $15 Donation, Discord Verification | O36: =IFERROR(__xludf.DUMMYFUNCTION("""COMPUTED_VALUE"""),"Fundraising, PR, Membership, Feeding") -> Fundraising, PR, Membership, Feeding | P36: =IFERROR(__xludf.DUMMYFUNCTION("IFERROR( IMAGE( ""https://drive.google.com/uc?export=download&id=""&MID( IMPORTRANGE(""18RaQw448NnENcNftounuam8eQyPVXS6StgZUz-RLzHA"",""'UTA Cat Coalition Membership Application'!L""&ROW()-2) ,(FIND(""="", IMPORTRANGE(""18RaQw448NnENcNftounuam8eQyPVXS6St"&"gZUz-RLzHA"",""'UTA Cat Coalition Membership Application'!L""&ROW()-2) ))+1,LEN( IMPORTRANGE(""18RaQw448NnENcNftounuam8eQyPVXS6StgZUz-RLzHA"",""'UTA Cat Coalition Membership Application'!L""&ROW()-2) )-FIND(""="", IMPORTRANGE(""18RaQw448NnENcNftounuam8eQy"&"PVXS6StgZUz-RLzHA"",""'UTA Cat Coalition Membership Application'!L""&ROW()-2) )),1 ) , """")"),"")
A37: =IFERROR(__xludf.DUMMYFUNCTION("""COMPUTED_VALUE"""),44600.94790083333) -> 44600.948 | B37: TRUE | C37: =IF(A37<>"", IFERROR(IF(MONTH(A37) < 6, "Spring ", "Fall ") & IF(MONTH(A37) < 6, YEAR(A37), YEAR(A37) + IF(MONTH(A37) = 12, 1, 0)), ""), "") -> Spring 2022 | D37: =IFERROR(__xludf.DUMMYFUNCTION("""COMPUTED_VALUE"""),"mls8159@mavs.uta.edu") -> mls8159@mavs.uta.edu | E37: =IFERROR(__xludf.DUMMYFUNCTION("""COMPUTED_VALUE"""),"Madeline Smith") -> Madeline Smith | F37: =IFERROR(__xludf.DUMMYFUNCTION("""COMPUTED_VALUE"""),"madeline #3044") -> madeline #3044 | H37: =IFERROR(__xludf.DUMMYFUNCTION("""COMPUTED_VALUE"""),"(847) 964-3260") -> (847) 964-3260 | I37: =IFERROR(__xludf.DUMMYFUNCTION("""COMPUTED_VALUE"""),"Student") -> Student | J37: =IFERROR(__xludf.DUMMYFUNCTION("""COMPUTED_VALUE"""),"$15 Donation, Discord Verification") -> $15 Donation, Discord Verification | O37: =IFERROR(__xludf.DUMMYFUNCTION("""COMPUTED_VALUE"""),"Feeding, Shelter Maintenance") -> Feeding, Shelter Maintenance | P37: =IFERROR(__xludf.DUMMYFUNCTION("IFERROR( IMAGE( ""https://drive.google.com/uc?export=download&id=""&MID( IMPORTRANGE(""18RaQw448NnENcNftounuam8eQyPVXS6StgZUz-RLzHA"",""'UTA Cat Coalition Membership Application'!L""&ROW()-2) ,(FIND(""="", IMPORTRANGE(""18RaQw448NnENcNftounuam8eQyPVXS6St"&"gZUz-RLzHA"",""'UTA Cat Coalition Membership Application'!L""&ROW()-2) ))+1,LEN( IMPORTRANGE(""18RaQw448NnENcNftounuam8eQyPVXS6StgZUz-RLzHA"",""'UTA Cat Coalition Membership Application'!L""&ROW()-2) )-FIND(""="", IMPORTRANGE(""18RaQw448NnENcNftounuam8eQy"&"PVXS6StgZUz-RLzHA"",""'UTA Cat Coalition Membership Application'!L""&ROW()-2) )),1 ) , """")"),"")
A38: =IFERROR(__xludf.DUMMYFUNCTION("""COMPUTED_VALUE"""),44600.97930016204) -> 44600.979 | B38: TRUE | C38: =IF(A38<>"", IFERROR(IF(MONTH(A38) < 6, "Spring ", "Fall ") & IF(MONTH(A38) < 6, YEAR(A38), YEAR(A38) + IF(MONTH(A38) = 12, 1, 0)), ""), "") -> Spring 2022 | D38: =IFERROR(__xludf.DUMMYFUNCTION("""COMPUTED_VALUE"""),"ethnica.mohanty@mavs.uta.edu") -> ethnica.mohanty@mavs.uta.edu | E38: =IFERROR(__xludf.DUMMYFUNCTION("""COMPUTED_VALUE"""),"Ethnica Mohanty") -> Ethnica Mohanty | F38: =IFERROR(__xludf.DUMMYFUNCTION("""COMPUTED_VALUE"""),"Ethnica#3603") -> Ethnica#3603 | H38: =IFERROR(__xludf.DUMMYFUNCTION("""COMPUTED_VALUE"""),"(281) 935-7860") -> (281) 935-7860 | I38: =IFERROR(__xludf.DUMMYFUNCTION("""COMPUTED_VALUE"""),"Student") -> Student | J38: =IFERROR(__xludf.DUMMYFUNCTION("""COMPUTED_VALUE"""),"$15 Donation, Discord Verification") -> $15 Donation, Discord Verification | O38: =IFERROR(__xludf.DUMMYFUNCTION("""COMPUTED_VALUE"""),"Fundraising, PR") -> Fundraising, PR | P38: =IFERROR(__xludf.DUMMYFUNCTION("IFERROR( IMAGE( ""https://drive.google.com/uc?export=download&id=""&MID( IMPORTRANGE(""18RaQw448NnENcNftounuam8eQyPVXS6StgZUz-RLzHA"",""'UTA Cat Coalition Membership Application'!L""&ROW()-2) ,(FIND(""="", IMPORTRANGE(""18RaQw448NnENcNftounuam8eQyPVXS6St"&"gZUz-RLzHA"",""'UTA Cat Coalition Membership Application'!L""&ROW()-2) ))+1,LEN( IMPORTRANGE(""18RaQw448NnENcNftounuam8eQyPVXS6StgZUz-RLzHA"",""'UTA Cat Coalition Membership Application'!L""&ROW()-2) )-FIND(""="", IMPORTRANGE(""18RaQw448NnENcNftounuam8eQy"&"PVXS6StgZUz-RLzHA"",""'UTA Cat Coalition Membership Application'!L""&ROW()-2) )),1 ) , """")"),"")
A39: =IFERROR(__xludf.DUMMYFUNCTION("""COMPUTED_VALUE"""),44601.02656430556) -> 44601.027 | B39: TRUE | C39: =IF(A39<>"", IFERROR(IF(MONTH(A39) < 6, "Spring ", "Fall ") & IF(MONTH(A39) < 6, YEAR(A39), YEAR(A39) + IF(MONTH(A39) = 12, 1, 0)), ""), "") -> Spring 2022 | D39: =IFERROR(__xludf.DUMMYFUNCTION("""COMPUTED_VALUE"""),"katherine.parks@mavs.uta.edu") -> katherine.parks@mavs.uta.edu | E39: =IFERROR(__xludf.DUMMYFUNCTION("""COMPUTED_VALUE"""),"Katherine Parks") -> Katherine Parks | F39: =IFERROR(__xludf.DUMMYFUNCTION("""COMPUTED_VALUE"""),"QuietPhoenix#5330") -> QuietPhoenix#5330 | H39: =IFERROR(__xludf.DUMMYFUNCTION("""COMPUTED_VALUE"""),"(469) 822-7849") -> (469) 822-7849 | I39: =IFERROR(__xludf.DUMMYFUNCTION("""COMPUTED_VALUE"""),"Student") -> Student | J39: =IFERROR(__xludf.DUMMYFUNCTION("""COMPUTED_VALUE"""),"$15 Donation, Discord Verification") -> $15 Donation, Discord Verification | O39: =IFERROR(__xludf.DUMMYFUNCTION("""COMPUTED_VALUE"""),"I'm not sure yet as I'd like to learn more about all the committees") -> I'm not sure yet as I'd like to learn more about all the committees | P39: =IFERROR(__xludf.DUMMYFUNCTION("IFERROR( IMAGE( ""https://drive.google.com/uc?export=download&id=""&MID( IMPORTRANGE(""18RaQw448NnENcNftounuam8eQyPVXS6StgZUz-RLzHA"",""'UTA Cat Coalition Membership Application'!L""&ROW()-2) ,(FIND(""="", IMPORTRANGE(""18RaQw448NnENcNftounuam8eQyPVXS6St"&"gZUz-RLzHA"",""'UTA Cat Coalition Membership Application'!L""&ROW()-2) ))+1,LEN( IMPORTRANGE(""18RaQw448NnENcNftounuam8eQyPVXS6StgZUz-RLzHA"",""'UTA Cat Coalition Membership Application'!L""&ROW()-2) )-FIND(""="", IMPORTRANGE(""18RaQw448NnENcNftounuam8eQy"&"PVXS6StgZUz-RLzHA"",""'UTA Cat Coalition Membership Application'!L""&ROW()-2) )),1 ) , """")"),"")
A40: =IFERROR(__xludf.DUMMYFUNCTION("""COMPUTED_VALUE"""),44601.607265081024) -> 44601.607 | B40: TRUE | C40: =IF(A40<>"", IFERROR(IF(MONTH(A40) < 6, "Spring ", "Fall ") & IF(MONTH(A40) < 6, YEAR(A40), YEAR(A40) + IF(MONTH(A40) = 12, 1, 0)), ""), "") -> Spring 2022 | D40: =IFERROR(__xludf.DUMMYFUNCTION("""COMPUTED_VALUE"""),"zaynab.shaikh@mavs.uta.edu") -> zaynab.shaikh@mavs.uta.edu | E40: =IFERROR(__xludf.DUMMYFUNCTION("""COMPUTED_VALUE"""),"Zaynab Shaikh") -> Zaynab Shaikh | F40: =IFERROR(__xludf.DUMMYFUNCTION("""COMPUTED_VALUE"""),"Icebearlikesturtles#0329") -> Icebearlikesturtles#0329 | H40: =IFERROR(__xludf.DUMMYFUNCTION("""COMPUTED_VALUE"""),"") | I40: =IFERROR(__xludf.DUMMYFUNCTION("""COMPUTED_VALUE"""),"Student") -> Student | J40: =IFERROR(__xludf.DUMMYFUNCTION("""COMPUTED_VALUE"""),"$15 Donation, Discord Verification") -> $15 Donation, Discord Verification | O40: =IFERROR(__xludf.DUMMYFUNCTION("""COMPUTED_VALUE"""),"Fundraising, Membership, Feeding") -> Fundraising, Membership, Feeding | P40: =IFERROR(__xludf.DUMMYFUNCTION("IFERROR( IMAGE( ""https://drive.google.com/uc?export=download&id=""&MID( IMPORTRANGE(""18RaQw448NnENcNftounuam8eQyPVXS6StgZUz-RLzHA"",""'UTA Cat Coalition Membership Application'!L""&ROW()-2) ,(FIND(""="", IMPORTRANGE(""18RaQw448NnENcNftounuam8eQyPVXS6St"&"gZUz-RLzHA"",""'UTA Cat Coalition Membership Application'!L""&ROW()-2) ))+1,LEN( IMPORTRANGE(""18RaQw448NnENcNftounuam8eQyPVXS6StgZUz-RLzHA"",""'UTA Cat Coalition Membership Application'!L""&ROW()-2) )-FIND(""="", IMPORTRANGE(""18RaQw448NnENcNftounuam8eQy"&"PVXS6StgZUz-RLzHA"",""'UTA Cat Coalition Membership Application'!L""&ROW()-2) )),1 ) , """")"),"")
A41: =IFERROR(__xludf.DUMMYFUNCTION("""COMPUTED_VALUE"""),44606.99112435185) -> 44606.991 | B41: TRUE | C41: =IF(A41<>"", IFERROR(IF(MONTH(A41) < 6, "Spring ", "Fall ") & IF(MONTH(A41) < 6, YEAR(A41), YEAR(A41) + IF(MONTH(A41) = 12, 1, 0)), ""), "") -> Spring 2022 | D41: =IFERROR(__xludf.DUMMYFUNCTION("""COMPUTED_VALUE"""),"jps2697@mavs.uta.edu") -> jps2697@mavs.uta.edu | E41: =IFERROR(__xludf.DUMMYFUNCTION("""COMPUTED_VALUE"""),"Joseph P. St. Jacques") -> Joseph P. St. Jacques | F41: =IFERROR(__xludf.DUMMYFUNCTION("""COMPUTED_VALUE"""),"joeystj#6236") -> joeystj#6236 | H41: =IFERROR(__xludf.DUMMYFUNCTION("""COMPUTED_VALUE"""),"(214) 642-0088") -> (214) 642-0088 | I41: =IFERROR(__xludf.DUMMYFUNCTION("""COMPUTED_VALUE"""),"Student") -> Student | J41: =IFERROR(__xludf.DUMMYFUNCTION("""COMPUTED_VALUE"""),"$15 Donation, Discord Verification") -> $15 Donation, Discord Verification | O41: =IFERROR(__xludf.DUMMYFUNCTION("""COMPUTED_VALUE"""),"TNR, Overnight TNR, Feeding, Shelter Maintenance") -> TNR, Overnight TNR, Feeding, Shelter Maintenance | P41: =IFERROR(__xludf.DUMMYFUNCTION("IFERROR( IMAGE( ""https://drive.google.com/uc?export=download&id=""&MID( IMPORTRANGE(""18RaQw448NnENcNftounuam8eQyPVXS6StgZUz-RLzHA"",""'UTA Cat Coalition Membership Application'!L""&ROW()-2) ,(FIND(""="", IMPORTRANGE(""18RaQw448NnENcNftounuam8eQyPVXS6St"&"gZUz-RLzHA"",""'UTA Cat Coalition Membership Application'!L""&ROW()-2) ))+1,LEN( IMPORTRANGE(""18RaQw448NnENcNftounuam8eQyPVXS6StgZUz-RLzHA"",""'UTA Cat Coalition Membership Application'!L""&ROW()-2) )-FIND(""="", IMPORTRANGE(""18RaQw448NnENcNftounuam8eQy"&"PVXS6StgZUz-RLzHA"",""'UTA Cat Coalition Membership Application'!L""&ROW()-2) )),1 ) , """")"),"")
A42: =IFERROR(__xludf.DUMMYFUNCTION("""COMPUTED_VALUE"""),44608.61212871528) -> 44608.612 | B42: TRUE | C42: =IF(A42<>"", IFERROR(IF(MONTH(A42) < 6, "Spring ", "Fall ") & IF(MONTH(A42) < 6, YEAR(A42), YEAR(A42) + IF(MONTH(A42) = 12, 1, 0)), ""), "") -> Spring 2022 | D42: =IFERROR(__xludf.DUMMYFUNCTION("""COMPUTED_VALUE"""),"scoen@uta.edu") -> scoen@uta.edu | E42: =IFERROR(__xludf.DUMMYFUNCTION("""COMPUTED_VALUE"""),"Shelby Coen") -> Shelby Coen | F42: =IFERROR(__xludf.DUMMYFUNCTION("""COMPUTED_VALUE"""),"shelbeelzebub#5349") -> shelbeelzebub#5349 | H42: =IFERROR(__xludf.DUMMYFUNCTION("""COMPUTED_VALUE"""),"(817) 272-2661") -> (817) 272-2661 | I42: =IFERROR(__xludf.DUMMYFUNCTION("""COMPUTED_VALUE"""),"UTA Faculty") -> UTA Faculty | J42: =IFERROR(__xludf.DUMMYFUNCTION("""COMPUTED_VALUE"""),"$15 Donation, Discord Verification") -> $15 Donation, Discord Verification | O42: =IFERROR(__xludf.DUMMYFUNCTION("""COMPUTED_VALUE"""),"PR, Membership") -> PR, Membership | P42: =IFERROR(__xludf.DUMMYFUNCTION("IFERROR( IMAGE( ""https://drive.google.com/uc?export=download&id=""&MID( IMPORTRANGE(""18RaQw448NnENcNftounuam8eQyPVXS6StgZUz-RLzHA"",""'UTA Cat Coalition Membership Application'!L""&ROW()-2) ,(FIND(""="", IMPORTRANGE(""18RaQw448NnENcNftounuam8eQyPVXS6St"&"gZUz-RLzHA"",""'UTA Cat Coalition Membership Application'!L""&ROW()-2) ))+1,LEN( IMPORTRANGE(""18RaQw448NnENcNftounuam8eQyPVXS6StgZUz-RLzHA"",""'UTA Cat Coalition Membership Application'!L""&ROW()-2) )-FIND(""="", IMPORTRANGE(""18RaQw448NnENcNftounuam8eQy"&"PVXS6StgZUz-RLzHA"",""'UTA Cat Coalition Membership Application'!L""&ROW()-2) )),1 ) , """")"),"")
A43: =IFERROR(__xludf.DUMMYFUNCTION("""COMPUTED_VALUE"""),44610.61055267361) -> 44610.611 | B43: TRUE | C43: =IF(A43<>"", IFERROR(IF(MONTH(A43) < 6, "Spring ", "Fall ") & IF(MONTH(A43) < 6, YEAR(A43), YEAR(A43) + IF(MONTH(A43) = 12, 1, 0)), ""), "") -> Spring 2022 | D43: =IFERROR(__xludf.DUMMYFUNCTION("""COMPUTED_VALUE"""),"aaa4904@mavs.uta.edu") -> aaa4904@mavs.uta.edu | E43: =IFERROR(__xludf.DUMMYFUNCTION("""COMPUTED_VALUE"""),"Anthony Aiyedun") -> Anthony Aiyedun | F43: =IFERROR(__xludf.DUMMYFUNCTION("""COMPUTED_VALUE"""),"Anth #3843") -> Anth #3843 | H43: =IFERROR(__xludf.DUMMYFUNCTION("""COMPUTED_VALUE"""),"(469) 600-6587") -> (469) 600-6587 | I43: =IFERROR(__xludf.DUMMYFUNCTION("""COMPUTED_VALUE"""),"Student") -> Student | J43: =IFERROR(__xludf.DUMMYFUNCTION("""COMPUTED_VALUE"""),"$15 Donation, Discord Verification") -> $15 Donation, Discord Verification | O43: =IFERROR(__xludf.DUMMYFUNCTION("""COMPUTED_VALUE"""),"Feeding") -> Feeding | P43: =IFERROR(__xludf.DUMMYFUNCTION("IFERROR( IMAGE( ""https://drive.google.com/uc?export=download&id=""&MID( IMPORTRANGE(""18RaQw448NnENcNftounuam8eQyPVXS6StgZUz-RLzHA"",""'UTA Cat Coalition Membership Application'!L""&ROW()-2) ,(FIND(""="", IMPORTRANGE(""18RaQw448NnENcNftounuam8eQyPVXS6St"&"gZUz-RLzHA"",""'UTA Cat Coalition Membership Application'!L""&ROW()-2) ))+1,LEN( IMPORTRANGE(""18RaQw448NnENcNftounuam8eQyPVXS6StgZUz-RLzHA"",""'UTA Cat Coalition Membership Application'!L""&ROW()-2) )-FIND(""="", IMPORTRANGE(""18RaQw448NnENcNftounuam8eQy"&"PVXS6StgZUz-RLzHA"",""'UTA Cat Coalition Membership Application'!L""&ROW()-2) )),1 ) , """")"),"")
A44: =IFERROR(__xludf.DUMMYFUNCTION("""COMPUTED_VALUE"""),44613.72720898148) -> 44613.727 | B44: TRUE | C44: =IF(A44<>"", IFERROR(IF(MONTH(A44) < 6, "Spring ", "Fall ") & IF(MONTH(A44) < 6, YEAR(A44), YEAR(A44) + IF(MONTH(A44) = 12, 1, 0)), ""), "") -> Spring 2022 | D44: =IFERROR(__xludf.DUMMYFUNCTION("""COMPUTED_VALUE"""),"kstogsdill2002@gmail.com") -> kstogsdill2002@gmail.com | E44: =IFERROR(__xludf.DUMMYFUNCTION("""COMPUTED_VALUE"""),"Kara Stogsdill") -> Kara Stogsdill | F44: =IFERROR(__xludf.DUMMYFUNCTION("""COMPUTED_VALUE"""),"wavenote#4015") -> wavenote#4015 | H44: =IFERROR(__xludf.DUMMYFUNCTION("""COMPUTED_VALUE"""),"(817) 683-9846") -> (817) 683-9846 | I44: =IFERROR(__xludf.DUMMYFUNCTION("""COMPUTED_VALUE"""),"Student") -> Student | J44: =IFERROR(__xludf.DUMMYFUNCTION("""COMPUTED_VALUE"""),"$15 Donation, Discord Verification") -> $15 Donation, Discord Verification | O44: =IFERROR(__xludf.DUMMYFUNCTION("""COMPUTED_VALUE"""),"officer ( ͡° ͜ʖ ͡°) ") -> officer ( ͡° ͜ʖ ͡°) | P44: =IFERROR(__xludf.DUMMYFUNCTION("IFERROR( IMAGE( ""https://drive.google.com/uc?export=download&id=""&MID( IMPORTRANGE(""18RaQw448NnENcNftounuam8eQyPVXS6StgZUz-RLzHA"",""'UTA Cat Coalition Membership Application'!L""&ROW()-2) ,(FIND(""="", IMPORTRANGE(""18RaQw448NnENcNftounuam8eQyPVXS6St"&"gZUz-RLzHA"",""'UTA Cat Coalition Membership Application'!L""&ROW()-2) ))+1,LEN( IMPORTRANGE(""18RaQw448NnENcNftounuam8eQyPVXS6StgZUz-RLzHA"",""'UTA Cat Coalition Membership Application'!L""&ROW()-2) )-FIND(""="", IMPORTRANGE(""18RaQw448NnENcNftounuam8eQy"&"PVXS6StgZUz-RLzHA"",""'UTA Cat Coalition Membership Application'!L""&ROW()-2) )),1 ) , """")"),"")
A45: =IFERROR(__xludf.DUMMYFUNCTION("""COMPUTED_VALUE"""),44613.72829752315) -> 44613.728 | B45: TRUE | C45: =IF(A45<>"", IFERROR(IF(MONTH(A45) < 6, "Spring ", "Fall ") & IF(MONTH(A45) < 6, YEAR(A45), YEAR(A45) + IF(MONTH(A45) = 12, 1, 0)), ""), "") -> Spring 2022 | D45: =IFERROR(__xludf.DUMMYFUNCTION("""COMPUTED_VALUE"""),"payten.belt@macs.uta.edu") -> payten.belt@macs.uta.edu | E45: =IFERROR(__xludf.DUMMYFUNCTION("""COMPUTED_VALUE"""),"Payten (Bat) Belt") -> Payten (Bat) Belt | F45: =IFERROR(__xludf.DUMMYFUNCTION("""COMPUTED_VALUE""")," Bat🖤#5142") -> Bat🖤#5142 | H45: =IFERROR(__xludf.DUMMYFUNCTION("""COMPUTED_VALUE"""),"(281) 221-0208") -> (281) 221-0208 | I45: =IFERROR(__xludf.DUMMYFUNCTION("""COMPUTED_VALUE"""),"Student") -> Student | J45: =IFERROR(__xludf.DUMMYFUNCTION("""COMPUTED_VALUE"""),"$15 Donation, Discord Verification") -> $15 Donation, Discord Verification | O45: =IFERROR(__xludf.DUMMYFUNCTION("""COMPUTED_VALUE"""),"Fostering") -> Fostering | P45: =IFERROR(__xludf.DUMMYFUNCTION("IFERROR( IMAGE( ""https://drive.google.com/uc?export=download&id=""&MID( IMPORTRANGE(""18RaQw448NnENcNftounuam8eQyPVXS6StgZUz-RLzHA"",""'UTA Cat Coalition Membership Application'!L""&ROW()-2) ,(FIND(""="", IMPORTRANGE(""18RaQw448NnENcNftounuam8eQyPVXS6St"&"gZUz-RLzHA"",""'UTA Cat Coalition Membership Application'!L""&ROW()-2) ))+1,LEN( IMPORTRANGE(""18RaQw448NnENcNftounuam8eQyPVXS6StgZUz-RLzHA"",""'UTA Cat Coalition Membership Application'!L""&ROW()-2) )-FIND(""="", IMPORTRANGE(""18RaQw448NnENcNftounuam8eQy"&"PVXS6StgZUz-RLzHA"",""'UTA Cat Coalition Membership Application'!L""&ROW()-2) )),1 ) , """")"),"")
A46: =IFERROR(__xludf.DUMMYFUNCTION("""COMPUTED_VALUE"""),44624.736503622684) -> 44624.736 | B46: TRUE | C46: =IF(A46<>"", IFERROR(IF(MONTH(A46) < 6, "Spring ", "Fall ") & IF(MONTH(A46) < 6, YEAR(A46), YEAR(A46) + IF(MONTH(A46) = 12, 1, 0)), ""), "") -> Spring 2022 | D46: =IFERROR(__xludf.DUMMYFUNCTION("""COMPUTED_VALUE"""),"bxa7089@mavs.uta.edu") -> bxa7089@mavs.uta.edu | E46: =IFERROR(__xludf.DUMMYFUNCTION("""COMPUTED_VALUE"""),"Brooke Haley Anderson") -> Brooke Haley Anderson | F46: =IFERROR(__xludf.DUMMYFUNCTION("""COMPUTED_VALUE"""),"idontlikehavingtomakeusernames#6444") -> idontlikehavingtomakeusernames#6444 | H46: =IFERROR(__xludf.DUMMYFUNCTION("""COMPUTED_VALUE"""),"(214) 287-9451") -> (214) 287-9451 | I46: =IFERROR(__xludf.DUMMYFUNCTION("""COMPUTED_VALUE"""),"Student") -> Student | J46: =IFERROR(__xludf.DUMMYFUNCTION("""COMPUTED_VALUE"""),"$15 Donation, Discord Verification") -> $15 Donation, Discord Verification | O46: =IFERROR(__xludf.DUMMYFUNCTION("""COMPUTED_VALUE"""),"Membership, TNR") -> Membership, TNR | P46: =IFERROR(__xludf.DUMMYFUNCTION("IFERROR( IMAGE( ""https://drive.google.com/uc?export=download&id=""&MID( IMPORTRANGE(""18RaQw448NnENcNftounuam8eQyPVXS6StgZUz-RLzHA"",""'UTA Cat Coalition Membership Application'!L""&ROW()-2) ,(FIND(""="", IMPORTRANGE(""18RaQw448NnENcNftounuam8eQyPVXS6St"&"gZUz-RLzHA"",""'UTA Cat Coalition Membership Application'!L""&ROW()-2) ))+1,LEN( IMPORTRANGE(""18RaQw448NnENcNftounuam8eQyPVXS6StgZUz-RLzHA"",""'UTA Cat Coalition Membership Application'!L""&ROW()-2) )-FIND(""="", IMPORTRANGE(""18RaQw448NnENcNftounuam8eQy"&"PVXS6StgZUz-RLzHA"",""'UTA Cat Coalition Membership Application'!L""&ROW()-2) )),1 ) , """")"),"")
A47: =IFERROR(__xludf.DUMMYFUNCTION("""COMPUTED_VALUE"""),44643.512073564816) -> 44643.512 | B47: TRUE | C47: =IF(A47<>"", IFERROR(IF(MONTH(A47) < 6, "Spring ", "Fall ") & IF(MONTH(A47) < 6, YEAR(A47), YEAR(A47) + IF(MONTH(A47) = 12, 1, 0)), ""), "") -> Spring 2022 | D47: =IFERROR(__xludf.DUMMYFUNCTION("""COMPUTED_VALUE"""),"jazmine.frazer@mavs.uta.edu") -> jazmine.frazer@mavs.uta.edu | E47: =IFERROR(__xludf.DUMMYFUNCTION("""COMPUTED_VALUE"""),"Jazmine Frazer") -> Jazmine Frazer | F47: =IFERROR(__xludf.DUMMYFUNCTION("""COMPUTED_VALUE"""),"Furren#9810") -> Furren#9810 | H47: =IFERROR(__xludf.DUMMYFUNCTION("""COMPUTED_VALUE"""),"(972) 802-9907") -> (972) 802-9907 | I47: =IFERROR(__xludf.DUMMYFUNCTION("""COMPUTED_VALUE"""),"Student") -> Student | J47: =IFERROR(__xludf.DUMMYFUNCTION("""COMPUTED_VALUE"""),"$15 Donation, Discord Verification") -> $15 Donation, Discord Verification | O47: =IFERROR(__xludf.DUMMYFUNCTION("""COMPUTED_VALUE"""),"Feeding") -> Feeding | P47: =IFERROR(__xludf.DUMMYFUNCTION("IFERROR( IMAGE( ""https://drive.google.com/uc?export=download&id=""&MID( IMPORTRANGE(""18RaQw448NnENcNftounuam8eQyPVXS6StgZUz-RLzHA"",""'UTA Cat Coalition Membership Application'!L""&ROW()-2) ,(FIND(""="", IMPORTRANGE(""18RaQw448NnENcNftounuam8eQyPVXS6St"&"gZUz-RLzHA"",""'UTA Cat Coalition Membership Application'!L""&ROW()-2) ))+1,LEN( IMPORTRANGE(""18RaQw448NnENcNftounuam8eQyPVXS6StgZUz-RLzHA"",""'UTA Cat Coalition Membership Application'!L""&ROW()-2) )-FIND(""="", IMPORTRANGE(""18RaQw448NnENcNftounuam8eQy"&"PVXS6StgZUz-RLzHA"",""'UTA Cat Coalition Membership Application'!L""&ROW()-2) )),1 ) , """")"),"")
A48: =IFERROR(__xludf.DUMMYFUNCTION("""COMPUTED_VALUE"""),44645.62396798611) -> 44645.624 | B48: TRUE | C48: =IF(A48<>"", IFERROR(IF(MONTH(A48) < 6, "Spring ", "Fall ") & IF(MONTH(A48) < 6, YEAR(A48), YEAR(A48) + IF(MONTH(A48) = 12, 1, 0)), ""), "") -> Spring 2022 | D48: =IFERROR(__xludf.DUMMYFUNCTION("""COMPUTED_VALUE"""),"bat4615@mavs.uta.edu") -> bat4615@mavs.uta.edu | E48: =IFERROR(__xludf.DUMMYFUNCTION("""COMPUTED_VALUE"""),"Brett Teichmann") -> Brett Teichmann | F48: =IFERROR(__xludf.DUMMYFUNCTION("""COMPUTED_VALUE"""),"Brett#2481") -> Brett#2481 | H48: =IFERROR(__xludf.DUMMYFUNCTION("""COMPUTED_VALUE"""),"(817) 564-6490") -> (817) 564-6490 | I48: =IFERROR(__xludf.DUMMYFUNCTION("""COMPUTED_VALUE"""),"Student") -> Student | J48: =IFERROR(__xludf.DUMMYFUNCTION("""COMPUTED_VALUE"""),"$15 Donation, Discord Verification") -> $15 Donation, Discord Verification | O48: =IFERROR(__xludf.DUMMYFUNCTION("""COMPUTED_VALUE"""),"Feeding") -> Feeding | P48: =IFERROR(__xludf.DUMMYFUNCTION("IFERROR( IMAGE( ""https://drive.google.com/uc?export=download&id=""&MID( IMPORTRANGE(""18RaQw448NnENcNftounuam8eQyPVXS6StgZUz-RLzHA"",""'UTA Cat Coalition Membership Application'!L""&ROW()-2) ,(FIND(""="", IMPORTRANGE(""18RaQw448NnENcNftounuam8eQyPVXS6St"&"gZUz-RLzHA"",""'UTA Cat Coalition Membership Application'!L""&ROW()-2) ))+1,LEN( IMPORTRANGE(""18RaQw448NnENcNftounuam8eQyPVXS6StgZUz-RLzHA"",""'UTA Cat Coalition Membership Application'!L""&ROW()-2) )-FIND(""="", IMPORTRANGE(""18RaQw448NnENcNftounuam8eQy"&"PVXS6StgZUz-RLzHA"",""'UTA Cat Coalition Membership Application'!L""&ROW()-2) )),1 ) , """")"),"")
A49: =IFERROR(__xludf.DUMMYFUNCTION("""COMPUTED_VALUE"""),44646.45667054398) -> 44646.457 | B49: TRUE | C49: =IF(A49<>"", IFERROR(IF(MONTH(A49) < 6, "Spring ", "Fall ") & IF(MONTH(A49) < 6, YEAR(A49), YEAR(A49) + IF(MONTH(A49) = 12, 1, 0)), ""), "") -> Spring 2022 | D49: =IFERROR(__xludf.DUMMYFUNCTION("""COMPUTED_VALUE"""),"christine.magnuson@mavs.uta.edu") -> christine.magnuson@mavs.uta.edu | E49: =IFERROR(__xludf.DUMMYFUNCTION("""COMPUTED_VALUE"""),"Christine magnuson") -> Christine magnuson | F49: =IFERROR(__xludf.DUMMYFUNCTION("""COMPUTED_VALUE"""),"Vinegarooney") -> Vinegarooney | H49: =IFERROR(__xludf.DUMMYFUNCTION("""COMPUTED_VALUE"""),"(214) 677-5719") -> (214) 677-5719 | I49: =IFERROR(__xludf.DUMMYFUNCTION("""COMPUTED_VALUE"""),"Student") -> Student | J49: =IFERROR(__xludf.DUMMYFUNCTION("""COMPUTED_VALUE"""),"$15 Donation, Discord Verification") -> $15 Donation, Discord Verification | O49: =IFERROR(__xludf.DUMMYFUNCTION("""COMPUTED_VALUE"""),"TNR, Feeding") -> TNR, Feeding | P49: =IFERROR(__xludf.DUMMYFUNCTION("IFERROR( IMAGE( ""https://drive.google.com/uc?export=download&id=""&MID( IMPORTRANGE(""18RaQw448NnENcNftounuam8eQyPVXS6StgZUz-RLzHA"",""'UTA Cat Coalition Membership Application'!L""&ROW()-2) ,(FIND(""="", IMPORTRANGE(""18RaQw448NnENcNftounuam8eQyPVXS6St"&"gZUz-RLzHA"",""'UTA Cat Coalition Membership Application'!L""&ROW()-2) ))+1,LEN( IMPORTRANGE(""18RaQw448NnENcNftounuam8eQyPVXS6StgZUz-RLzHA"",""'UTA Cat Coalition Membership Application'!L""&ROW()-2) )-FIND(""="", IMPORTRANGE(""18RaQw448NnENcNftounuam8eQy"&"PVXS6StgZUz-RLzHA"",""'UTA Cat Coalition Membership Application'!L""&ROW()-2) )),1 ) , """")"),"")
A50: =IFERROR(__xludf.DUMMYFUNCTION("""COMPUTED_VALUE"""),44651.8694080787) -> 44651.869 | B50: TRUE | C50: =IF(A50<>"", IFERROR(IF(MONTH(A50) < 6, "Spring ", "Fall ") & IF(MONTH(A50) < 6, YEAR(A50), YEAR(A50) + IF(MONTH(A50) = 12, 1, 0)), ""), "") -> Spring 2022 | D50: =IFERROR(__xludf.DUMMYFUNCTION("""COMPUTED_VALUE"""),"claire.sissons@mavs.uta.edu") -> claire.sissons@mavs.uta.edu | E50: =IFERROR(__xludf.DUMMYFUNCTION("""COMPUTED_VALUE"""),"Claire Sissons") -> Claire Sissons | F50: =IFERROR(__xludf.DUMMYFUNCTION("""COMPUTED_VALUE"""),"cms5522#4418") -> cms5522#4418 | H50: =IFERROR(__xludf.DUMMYFUNCTION("""COMPUTED_VALUE"""),"(903) 422-5526") -> (903) 422-5526 | I50: =IFERROR(__xludf.DUMMYFUNCTION("""COMPUTED_VALUE"""),"Student") -> Student | J50: =IFERROR(__xludf.DUMMYFUNCTION("""COMPUTED_VALUE"""),"Food/Litter Donation") -> Food/Litter Donation | O50: =IFERROR(__xludf.DUMMYFUNCTION("""COMPUTED_VALUE"""),"Fundraising, TNR, Shelter Maintenance") -> Fundraising, TNR, Shelter Maintenance | P50: =IFERROR(__xludf.DUMMYFUNCTION("IFERROR( IMAGE( ""https://drive.google.com/uc?export=download&id=""&MID( IMPORTRANGE(""18RaQw448NnENcNftounuam8eQyPVXS6StgZUz-RLzHA"",""'UTA Cat Coalition Membership Application'!L""&ROW()-2) ,(FIND(""="", IMPORTRANGE(""18RaQw448NnENcNftounuam8eQyPVXS6St"&"gZUz-RLzHA"",""'UTA Cat Coalition Membership Application'!L""&ROW()-2) ))+1,LEN( IMPORTRANGE(""18RaQw448NnENcNftounuam8eQyPVXS6StgZUz-RLzHA"",""'UTA Cat Coalition Membership Application'!L""&ROW()-2) )-FIND(""="", IMPORTRANGE(""18RaQw448NnENcNftounuam8eQy"&"PVXS6StgZUz-RLzHA"",""'UTA Cat Coalition Membership Application'!L""&ROW()-2) )),1 ) , """")"),"")
A51: =IFERROR(__xludf.DUMMYFUNCTION("""COMPUTED_VALUE"""),44687.716291979166) -> 44687.716 | B51: TRUE | C51: =IF(A51<>"", IFERROR(IF(MONTH(A51) < 6, "Spring ", "Fall ") & IF(MONTH(A51) < 6, YEAR(A51), YEAR(A51) + IF(MONTH(A51) = 12, 1, 0)), ""), "") -> Spring 2022 | D51: =IFERROR(__xludf.DUMMYFUNCTION("""COMPUTED_VALUE"""),"moo7465@mavs.uta.edu") -> moo7465@mavs.uta.edu | E51: =IFERROR(__xludf.DUMMYFUNCTION("""COMPUTED_VALUE"""),"Oyindamola Mariam Oyeyemi") -> Oyindamola Mariam Oyeyemi | F51: =IFERROR(__xludf.DUMMYFUNCTION("""COMPUTED_VALUE"""),"Mariam O#3790") -> Mariam O#3790 | H51: =IFERROR(__xludf.DUMMYFUNCTION("""COMPUTED_VALUE"""),"(682) 222-2298") -> (682) 222-2298 | I51: =IFERROR(__xludf.DUMMYFUNCTION("""COMPUTED_VALUE"""),"Student") -> Student | J51: =IFERROR(__xludf.DUMMYFUNCTION("""COMPUTED_VALUE"""),"$15 Donation, Discord Verification") -> $15 Donation, Discord Verification | O51: =IFERROR(__xludf.DUMMYFUNCTION("""COMPUTED_VALUE"""),"Membership, Feeding") -> Membership, Feeding | P51: =IFERROR(__xludf.DUMMYFUNCTION("IFERROR( IMAGE( ""https://drive.google.com/uc?export=download&id=""&MID( IMPORTRANGE(""18RaQw448NnENcNftounuam8eQyPVXS6StgZUz-RLzHA"",""'UTA Cat Coalition Membership Application'!L""&ROW()-2) ,(FIND(""="", IMPORTRANGE(""18RaQw448NnENcNftounuam8eQyPVXS6St"&"gZUz-RLzHA"",""'UTA Cat Coalition Membership Application'!L""&ROW()-2) ))+1,LEN( IMPORTRANGE(""18RaQw448NnENcNftounuam8eQyPVXS6StgZUz-RLzHA"",""'UTA Cat Coalition Membership Application'!L""&ROW()-2) )-FIND(""="", IMPORTRANGE(""18RaQw448NnENcNftounuam8eQy"&"PVXS6StgZUz-RLzHA"",""'UTA Cat Coalition Membership Application'!L""&ROW()-2) )),1 ) , """")"),"")
A52: =IFERROR(__xludf.DUMMYFUNCTION("""COMPUTED_VALUE"""),44713.68202766204) -> 44713.682 | B52: TRUE | C52: =IF(A52<>"", IFERROR(IF(MONTH(A52) < 6, "Spring ", "Fall ") & IF(MONTH(A52) < 6, YEAR(A52), YEAR(A52) + IF(MONTH(A52) = 12, 1, 0)), ""), "") -> Fall 2022 | D52: =IFERROR(__xludf.DUMMYFUNCTION("""COMPUTED_VALUE"""),"cjg2340@mavs.uta.edu") -> cjg2340@mavs.uta.edu | E52: =IFERROR(__xludf.DUMMYFUNCTION("""COMPUTED_VALUE"""),"Neptune Gainer") -> Neptune Gainer | F52: =IFERROR(__xludf.DUMMYFUNCTION("""COMPUTED_VALUE"""),"Sonny#4501") -> Sonny#4501 | H52: =IFERROR(__xludf.DUMMYFUNCTION("""COMPUTED_VALUE"""),"(254) 644-7896") -> (254) 644-7896 | I52: =IFERROR(__xludf.DUMMYFUNCTION("""COMPUTED_VALUE"""),"Student") -> Student | J52: =IFERROR(__xludf.DUMMYFUNCTION("""COMPUTED_VALUE"""),"$15 Donation, Discord Verification") -> $15 Donation, Discord Verification | O52: =IFERROR(__xludf.DUMMYFUNCTION("""COMPUTED_VALUE"""),"TNR, Overnight TNR") -> TNR, Overnight TNR | P52: =IFERROR(__xludf.DUMMYFUNCTION("IFERROR( IMAGE( ""https://drive.google.com/uc?export=download&id=""&MID( IMPORTRANGE(""18RaQw448NnENcNftounuam8eQyPVXS6StgZUz-RLzHA"",""'UTA Cat Coalition Membership Application'!L""&ROW()-2) ,(FIND(""="", IMPORTRANGE(""18RaQw448NnENcNftounuam8eQyPVXS6St"&"gZUz-RLzHA"",""'UTA Cat Coalition Membership Application'!L""&ROW()-2) ))+1,LEN( IMPORTRANGE(""18RaQw448NnENcNftounuam8eQyPVXS6StgZUz-RLzHA"",""'UTA Cat Coalition Membership Application'!L""&ROW()-2) )-FIND(""="", IMPORTRANGE(""18RaQw448NnENcNftounuam8eQy"&"PVXS6StgZUz-RLzHA"",""'UTA Cat Coalition Membership Application'!L""&ROW()-2) )),1 ) , """")"),"")
A53: =IFERROR(__xludf.DUMMYFUNCTION("""COMPUTED_VALUE"""),44729.5865772338) -> 44729.587 | B53: TRUE | C53: =IF(A53<>"", IFERROR(IF(MONTH(A53) < 6, "Spring ", "Fall ") & IF(MONTH(A53) < 6, YEAR(A53), YEAR(A53) + IF(MONTH(A53) = 12, 1, 0)), ""), "") -> Fall 2022 | D53: =IFERROR(__xludf.DUMMYFUNCTION("""COMPUTED_VALUE"""),"pmd1523@mavs.uta.edu") -> pmd1523@mavs.uta.edu | E53: =IFERROR(__xludf.DUMMYFUNCTION("""COMPUTED_VALUE"""),"Phillip Duling-El") -> Phillip Duling-El | F53: =IFERROR(__xludf.DUMMYFUNCTION("""COMPUTED_VALUE"""),"xoltd#7369") -> xoltd#7369 | H53: =IFERROR(__xludf.DUMMYFUNCTION("""COMPUTED_VALUE"""),"(682) 553-9121") -> (682) 553-9121 | I53: =IFERROR(__xludf.DUMMYFUNCTION("""COMPUTED_VALUE"""),"Student") -> Student | J53: =IFERROR(__xludf.DUMMYFUNCTION("""COMPUTED_VALUE"""),"$15 Donation, Discord Verification") -> $15 Donation, Discord Verification | O53: =IFERROR(__xludf.DUMMYFUNCTION("""COMPUTED_VALUE"""),"Fundraising, PR, Shelter Maintenance") -> Fundraising, PR, Shelter Maintenance | P53: =IFERROR(__xludf.DUMMYFUNCTION("IFERROR( IMAGE( ""https://drive.google.com/uc?export=download&id=""&MID( IMPORTRANGE(""18RaQw448NnENcNftounuam8eQyPVXS6StgZUz-RLzHA"",""'UTA Cat Coalition Membership Application'!L""&ROW()-2) ,(FIND(""="", IMPORTRANGE(""18RaQw448NnENcNftounuam8eQyPVXS6St"&"gZUz-RLzHA"",""'UTA Cat Coalition Membership Application'!L""&ROW()-2) ))+1,LEN( IMPORTRANGE(""18RaQw448NnENcNftounuam8eQyPVXS6StgZUz-RLzHA"",""'UTA Cat Coalition Membership Application'!L""&ROW()-2) )-FIND(""="", IMPORTRANGE(""18RaQw448NnENcNftounuam8eQy"&"PVXS6StgZUz-RLzHA"",""'UTA Cat Coalition Membership Application'!L""&ROW()-2) )),1 ) , """")"),"")
A54: =IFERROR(__xludf.DUMMYFUNCTION("""COMPUTED_VALUE"""),44754.44758806713) -> 44754.448 | B54: TRUE | C54: =IF(A54<>"", IFERROR(IF(MONTH(A54) < 6, "Spring ", "Fall ") & IF(MONTH(A54) < 6, YEAR(A54), YEAR(A54) + IF(MONTH(A54) = 12, 1, 0)), ""), "") -> Fall 2022 | D54: =IFERROR(__xludf.DUMMYFUNCTION("""COMPUTED_VALUE"""),"jxw1244@mavs.uta.edu") -> jxw1244@mavs.uta.edu | E54: =IFERROR(__xludf.DUMMYFUNCTION("""COMPUTED_VALUE"""),"Jane Wang") -> Jane Wang | F54: =IFERROR(__xludf.DUMMYFUNCTION("""COMPUTED_VALUE"""),"Jane_IRL#7185") -> Jane_IRL#7185 | H54: =IFERROR(__xludf.DUMMYFUNCTION("""COMPUTED_VALUE"""),"") | I54: =IFERROR(__xludf.DUMMYFUNCTION("""COMPUTED_VALUE"""),"Student") -> Student | J54: =IFERROR(__xludf.DUMMYFUNCTION("""COMPUTED_VALUE"""),"$15 Donation, Discord Verification") -> $15 Donation, Discord Verification | O54: =IFERROR(__xludf.DUMMYFUNCTION("""COMPUTED_VALUE"""),"TNR, Feeding") -> TNR, Feeding | P54: =IFERROR(__xludf.DUMMYFUNCTION("IFERROR( IMAGE( ""https://drive.google.com/uc?export=download&id=""&MID( IMPORTRANGE(""18RaQw448NnENcNftounuam8eQyPVXS6StgZUz-RLzHA"",""'UTA Cat Coalition Membership Application'!L""&ROW()-2) ,(FIND(""="", IMPORTRANGE(""18RaQw448NnENcNftounuam8eQyPVXS6St"&"gZUz-RLzHA"",""'UTA Cat Coalition Membership Application'!L""&ROW()-2) ))+1,LEN( IMPORTRANGE(""18RaQw448NnENcNftounuam8eQyPVXS6StgZUz-RLzHA"",""'UTA Cat Coalition Membership Application'!L""&ROW()-2) )-FIND(""="", IMPORTRANGE(""18RaQw448NnENcNftounuam8eQy"&"PVXS6StgZUz-RLzHA"",""'UTA Cat Coalition Membership Application'!L""&ROW()-2) )),1 ) , """")"),"")
A55: =IFERROR(__xludf.DUMMYFUNCTION("""COMPUTED_VALUE"""),44760.17037069444) -> 44760.17 | B55: TRUE | C55: =IF(A55<>"", IFERROR(IF(MONTH(A55) < 6, "Spring ", "Fall ") & IF(MONTH(A55) < 6, YEAR(A55), YEAR(A55) + IF(MONTH(A55) = 12, 1, 0)), ""), "") -> Fall 2022 | D55: =IFERROR(__xludf.DUMMYFUNCTION("""COMPUTED_VALUE"""),"axr5141@mavs.uta.edu") -> axr5141@mavs.uta.edu | E55: =IFERROR(__xludf.DUMMYFUNCTION("""COMPUTED_VALUE"""),"Angelica Romero") -> Angelica Romero | F55: =IFERROR(__xludf.DUMMYFUNCTION("""COMPUTED_VALUE"""),"Angiekin#7816") -> Angiekin#7816 | H55: =IFERROR(__xludf.DUMMYFUNCTION("""COMPUTED_VALUE"""),"(682) 704-7602") -> (682) 704-7602 | I55: =IFERROR(__xludf.DUMMYFUNCTION("""COMPUTED_VALUE"""),"Student") -> Student | J55: =IFERROR(__xludf.DUMMYFUNCTION("""COMPUTED_VALUE"""),"$15 Donation, Discord Verification") -> $15 Donation, Discord Verification | O55: =IFERROR(__xludf.DUMMYFUNCTION("""COMPUTED_VALUE"""),"Fundraising, Membership, Feeding, Fostering") -> Fundraising, Membership, Feeding, Fostering | P55: =IFERROR(__xludf.DUMMYFUNCTION("IFERROR( IMAGE( ""https://drive.google.com/uc?export=download&id=""&MID( IMPORTRANGE(""18RaQw448NnENcNftounuam8eQyPVXS6StgZUz-RLzHA"",""'UTA Cat Coalition Membership Application'!L""&ROW()-2) ,(FIND(""="", IMPORTRANGE(""18RaQw448NnENcNftounuam8eQyPVXS6St"&"gZUz-RLzHA"",""'UTA Cat Coalition Membership Application'!L""&ROW()-2) ))+1,LEN( IMPORTRANGE(""18RaQw448NnENcNftounuam8eQyPVXS6StgZUz-RLzHA"",""'UTA Cat Coalition Membership Application'!L""&ROW()-2) )-FIND(""="", IMPORTRANGE(""18RaQw448NnENcNftounuam8eQy"&"PVXS6StgZUz-RLzHA"",""'UTA Cat Coalition Membership Application'!L""&ROW()-2) )),1 ) , """")"),"")
A56: =IFERROR(__xludf.DUMMYFUNCTION("""COMPUTED_VALUE"""),44789.73211891204) -> 44789.732 | B56: TRUE | C56: =IF(A56<>"", IFERROR(IF(MONTH(A56) < 6, "Spring ", "Fall ") & IF(MONTH(A56) < 6, YEAR(A56), YEAR(A56) + IF(MONTH(A56) = 12, 1, 0)), ""), "") -> Fall 2022 | D56: =IFERROR(__xludf.DUMMYFUNCTION("""COMPUTED_VALUE"""),"sxz4583@mavs.uta.edu") -> sxz4583@mavs.uta.edu | E56: =IFERROR(__xludf.DUMMYFUNCTION("""COMPUTED_VALUE"""),"Sarah Zamora") -> Sarah Zamora | F56: =IFERROR(__xludf.DUMMYFUNCTION("""COMPUTED_VALUE"""),"sarahzamora #2585") -> sarahzamora #2585 | H56: =IFERROR(__xludf.DUMMYFUNCTION("""COMPUTED_VALUE"""),"(214) 500-1670") -> (214) 500-1670 | I56: =IFERROR(__xludf.DUMMYFUNCTION("""COMPUTED_VALUE"""),"Student") -> Student | J56: =IFERROR(__xludf.DUMMYFUNCTION("""COMPUTED_VALUE"""),"$15 Donation, Discord Verification") -> $15 Donation, Discord Verification | O56: =IFERROR(__xludf.DUMMYFUNCTION("""COMPUTED_VALUE"""),"Fundraising, Membership, Feeding") -> Fundraising, Membership, Feeding | P56: =IFERROR(__xludf.DUMMYFUNCTION("IFERROR( IMAGE( ""https://drive.google.com/uc?export=download&id=""&MID( IMPORTRANGE(""18RaQw448NnENcNftounuam8eQyPVXS6StgZUz-RLzHA"",""'UTA Cat Coalition Membership Application'!L""&ROW()-2) ,(FIND(""="", IMPORTRANGE(""18RaQw448NnENcNftounuam8eQyPVXS6St"&"gZUz-RLzHA"",""'UTA Cat Coalition Membership Application'!L""&ROW()-2) ))+1,LEN( IMPORTRANGE(""18RaQw448NnENcNftounuam8eQyPVXS6StgZUz-RLzHA"",""'UTA Cat Coalition Membership Application'!L""&ROW()-2) )-FIND(""="", IMPORTRANGE(""18RaQw448NnENcNftounuam8eQy"&"PVXS6StgZUz-RLzHA"",""'UTA Cat Coalition Membership Application'!L""&ROW()-2) )),1 ) , """")"),"")
A57: =IFERROR(__xludf.DUMMYFUNCTION("""COMPUTED_VALUE"""),44792.35462597222) -> 44792.355 | B57: TRUE | C57: =IF(A57<>"", IFERROR(IF(MONTH(A57) < 6, "Spring ", "Fall ") & IF(MONTH(A57) < 6, YEAR(A57), YEAR(A57) + IF(MONTH(A57) = 12, 1, 0)), ""), "") -> Fall 2022 | D57: =IFERROR(__xludf.DUMMYFUNCTION("""COMPUTED_VALUE"""),"jxc0776@mavs.uta.edu") -> jxc0776@mavs.uta.edu | E57: =IFERROR(__xludf.DUMMYFUNCTION("""COMPUTED_VALUE"""),"Jada Carey") -> Jada Carey | F57: =IFERROR(__xludf.DUMMYFUNCTION("""COMPUTED_VALUE"""),"Judy#4084") -> Judy#4084 | H57: =IFERROR(__xludf.DUMMYFUNCTION("""COMPUTED_VALUE"""),"(682) 785-9626") -> (682) 785-9626 | I57: =IFERROR(__xludf.DUMMYFUNCTION("""COMPUTED_VALUE"""),"Student") -> Student | J57: =IFERROR(__xludf.DUMMYFUNCTION("""COMPUTED_VALUE"""),"$15 Donation, Discord Verification") -> $15 Donation, Discord Verification | O57: =IFERROR(__xludf.DUMMYFUNCTION("""COMPUTED_VALUE"""),"Feeding") -> Feeding | P57: =IFERROR(__xludf.DUMMYFUNCTION("IFERROR( IMAGE( ""https://drive.google.com/uc?export=download&id=""&MID( IMPORTRANGE(""18RaQw448NnENcNftounuam8eQyPVXS6StgZUz-RLzHA"",""'UTA Cat Coalition Membership Application'!L""&ROW()-2) ,(FIND(""="", IMPORTRANGE(""18RaQw448NnENcNftounuam8eQyPVXS6St"&"gZUz-RLzHA"",""'UTA Cat Coalition Membership Application'!L""&ROW()-2) ))+1,LEN( IMPORTRANGE(""18RaQw448NnENcNftounuam8eQyPVXS6StgZUz-RLzHA"",""'UTA Cat Coalition Membership Application'!L""&ROW()-2) )-FIND(""="", IMPORTRANGE(""18RaQw448NnENcNftounuam8eQy"&"PVXS6StgZUz-RLzHA"",""'UTA Cat Coalition Membership Application'!L""&ROW()-2) )),1 ) , """")"),"")
A58: =IFERROR(__xludf.DUMMYFUNCTION("""COMPUTED_VALUE"""),44792.57267462963) -> 44792.573 | B58: TRUE | C58: =IF(A58<>"", IFERROR(IF(MONTH(A58) < 6, "Spring ", "Fall ") & IF(MONTH(A58) < 6, YEAR(A58), YEAR(A58) + IF(MONTH(A58) = 12, 1, 0)), ""), "") -> Fall 2022 | D58: =IFERROR(__xludf.DUMMYFUNCTION("""COMPUTED_VALUE"""),"ethnica.mohanty@mavs.uta.edu") -> ethnica.mohanty@mavs.uta.edu | E58: =IFERROR(__xludf.DUMMYFUNCTION("""COMPUTED_VALUE"""),"Ethnica Mohanty") -> Ethnica Mohanty | F58: =IFERROR(__xludf.DUMMYFUNCTION("""COMPUTED_VALUE"""),"Ethnica #3603") -> Ethnica #3603 | H58: =IFERROR(__xludf.DUMMYFUNCTION("""COMPUTED_VALUE"""),"(281) 935-7860") -> (281) 935-7860 | I58: =IFERROR(__xludf.DUMMYFUNCTION("""COMPUTED_VALUE"""),"Student") -> Student | J58: =IFERROR(__xludf.DUMMYFUNCTION("""COMPUTED_VALUE"""),"$15 Donation, Discord Verification") -> $15 Donation, Discord Verification | O58: =IFERROR(__xludf.DUMMYFUNCTION("""COMPUTED_VALUE"""),"Fundraising, PR, Membership") -> Fundraising, PR, Membership | P58: =IFERROR(__xludf.DUMMYFUNCTION("IFERROR( IMAGE( ""https://drive.google.com/uc?export=download&id=""&MID( IMPORTRANGE(""18RaQw448NnENcNftounuam8eQyPVXS6StgZUz-RLzHA"",""'UTA Cat Coalition Membership Application'!L""&ROW()-2) ,(FIND(""="", IMPORTRANGE(""18RaQw448NnENcNftounuam8eQyPVXS6St"&"gZUz-RLzHA"",""'UTA Cat Coalition Membership Application'!L""&ROW()-2) ))+1,LEN( IMPORTRANGE(""18RaQw448NnENcNftounuam8eQyPVXS6StgZUz-RLzHA"",""'UTA Cat Coalition Membership Application'!L""&ROW()-2) )-FIND(""="", IMPORTRANGE(""18RaQw448NnENcNftounuam8eQy"&"PVXS6StgZUz-RLzHA"",""'UTA Cat Coalition Membership Application'!L""&ROW()-2) )),1 ) , """")"),"")
A59: =IFERROR(__xludf.DUMMYFUNCTION("""COMPUTED_VALUE"""),44792.96773695602) -> 44792.968 | B59: TRUE | C59: =IF(A59<>"", IFERROR(IF(MONTH(A59) < 6, "Spring ", "Fall ") & IF(MONTH(A59) < 6, YEAR(A59), YEAR(A59) + IF(MONTH(A59) = 12, 1, 0)), ""), "") -> Fall 2022 | D59: =IFERROR(__xludf.DUMMYFUNCTION("""COMPUTED_VALUE"""),"ryan.johnson2@mavs.uta.edu") -> ryan.johnson2@mavs.uta.edu | E59: =IFERROR(__xludf.DUMMYFUNCTION("""COMPUTED_VALUE"""),"Ryan Johnson") -> Ryan Johnson | F59: =IFERROR(__xludf.DUMMYFUNCTION("""COMPUTED_VALUE"""),"guppy#7190") -> guppy#7190 | H59: =IFERROR(__xludf.DUMMYFUNCTION("""COMPUTED_VALUE"""),"(409) 466-4015") -> (409) 466-4015 | I59: =IFERROR(__xludf.DUMMYFUNCTION("""COMPUTED_VALUE"""),"Student") -> Student | J59: =IFERROR(__xludf.DUMMYFUNCTION("""COMPUTED_VALUE"""),"$15 Donation, Discord Verification") -> $15 Donation, Discord Verification | O59: =IFERROR(__xludf.DUMMYFUNCTION("""COMPUTED_VALUE"""),"TNR, Overnight TNR, Feeding, Shelter Maintenance") -> TNR, Overnight TNR, Feeding, Shelter Maintenance | P59: =IFERROR(__xludf.DUMMYFUNCTION("IFERROR( IMAGE( ""https://drive.google.com/uc?export=download&id=""&MID( IMPORTRANGE(""18RaQw448NnENcNftounuam8eQyPVXS6StgZUz-RLzHA"",""'UTA Cat Coalition Membership Application'!L""&ROW()-2) ,(FIND(""="", IMPORTRANGE(""18RaQw448NnENcNftounuam8eQyPVXS6St"&"gZUz-RLzHA"",""'UTA Cat Coalition Membership Application'!L""&ROW()-2) ))+1,LEN( IMPORTRANGE(""18RaQw448NnENcNftounuam8eQyPVXS6StgZUz-RLzHA"",""'UTA Cat Coalition Membership Application'!L""&ROW()-2) )-FIND(""="", IMPORTRANGE(""18RaQw448NnENcNftounuam8eQy"&"PVXS6StgZUz-RLzHA"",""'UTA Cat Coalition Membership Application'!L""&ROW()-2) )),1 ) , """")"),"")
A60: =IFERROR(__xludf.DUMMYFUNCTION("""COMPUTED_VALUE"""),44793.66157361111) -> 44793.662 | B60: TRUE | C60: =IF(A60<>"", IFERROR(IF(MONTH(A60) < 6, "Spring ", "Fall ") & IF(MONTH(A60) < 6, YEAR(A60), YEAR(A60) + IF(MONTH(A60) = 12, 1, 0)), ""), "") -> Fall 2022 | D60: =IFERROR(__xludf.DUMMYFUNCTION("""COMPUTED_VALUE"""),"mcm0218@mavs.uta.edu") -> mcm0218@mavs.uta.edu | E60: =IFERROR(__xludf.DUMMYFUNCTION("""COMPUTED_VALUE"""),"McKayla Mellen") -> McKayla Mellen | F60: =IFERROR(__xludf.DUMMYFUNCTION("""COMPUTED_VALUE"""),"nostalgicsapphic#7354") -> nostalgicsapphic#7354 | H60: =IFERROR(__xludf.DUMMYFUNCTION("""COMPUTED_VALUE"""),"(512) 644-2879") -> (512) 644-2879 | I60: =IFERROR(__xludf.DUMMYFUNCTION("""COMPUTED_VALUE"""),"Student") -> Student | J60: =IFERROR(__xludf.DUMMYFUNCTION("""COMPUTED_VALUE"""),"$15 Donation, Discord Verification") -> $15 Donation, Discord Verification | O60: =IFERROR(__xludf.DUMMYFUNCTION("""COMPUTED_VALUE"""),"Fundraising") -> Fundraising | P60: =IFERROR(__xludf.DUMMYFUNCTION("IFERROR( IMAGE( ""https://drive.google.com/uc?export=download&id=""&MID( IMPORTRANGE(""18RaQw448NnENcNftounuam8eQyPVXS6StgZUz-RLzHA"",""'UTA Cat Coalition Membership Application'!L""&ROW()-2) ,(FIND(""="", IMPORTRANGE(""18RaQw448NnENcNftounuam8eQyPVXS6St"&"gZUz-RLzHA"",""'UTA Cat Coalition Membership Application'!L""&ROW()-2) ))+1,LEN( IMPORTRANGE(""18RaQw448NnENcNftounuam8eQyPVXS6StgZUz-RLzHA"",""'UTA Cat Coalition Membership Application'!L""&ROW()-2) )-FIND(""="", IMPORTRANGE(""18RaQw448NnENcNftounuam8eQy"&"PVXS6StgZUz-RLzHA"",""'UTA Cat Coalition Membership Application'!L""&ROW()-2) )),1 ) , """")"),"")
A61: =IFERROR(__xludf.DUMMYFUNCTION("""COMPUTED_VALUE"""),44794.952529270835) -> 44794.953 | B61: TRUE | C61: =IF(A61<>"", IFERROR(IF(MONTH(A61) < 6, "Spring ", "Fall ") & IF(MONTH(A61) < 6, YEAR(A61), YEAR(A61) + IF(MONTH(A61) = 12, 1, 0)), ""), "") -> Fall 2022 | D61: =IFERROR(__xludf.DUMMYFUNCTION("""COMPUTED_VALUE"""),"ald2369@mavs.uta.edu") -> ald2369@mavs.uta.edu | E61: =IFERROR(__xludf.DUMMYFUNCTION("""COMPUTED_VALUE"""),"Annabelle Delpin ") -> Annabelle Delpin | F61: =IFERROR(__xludf.DUMMYFUNCTION("""COMPUTED_VALUE"""),"disneygirl1322#3591") -> disneygirl1322#3591 | H61: =IFERROR(__xludf.DUMMYFUNCTION("""COMPUTED_VALUE"""),"(817) 630-5096") -> (817) 630-5096 | I61: =IFERROR(__xludf.DUMMYFUNCTION("""COMPUTED_VALUE"""),"Student") -> Student | J61: =IFERROR(__xludf.DUMMYFUNCTION("""COMPUTED_VALUE"""),"$15 Donation, Discord Verification") -> $15 Donation, Discord Verification | O61: =IFERROR(__xludf.DUMMYFUNCTION("""COMPUTED_VALUE"""),"Feeding") -> Feeding | P61: =IFERROR(__xludf.DUMMYFUNCTION("IFERROR( IMAGE( ""https://drive.google.com/uc?export=download&id=""&MID( IMPORTRANGE(""18RaQw448NnENcNftounuam8eQyPVXS6StgZUz-RLzHA"",""'UTA Cat Coalition Membership Application'!L""&ROW()-2) ,(FIND(""="", IMPORTRANGE(""18RaQw448NnENcNftounuam8eQyPVXS6St"&"gZUz-RLzHA"",""'UTA Cat Coalition Membership Application'!L""&ROW()-2) ))+1,LEN( IMPORTRANGE(""18RaQw448NnENcNftounuam8eQyPVXS6StgZUz-RLzHA"",""'UTA Cat Coalition Membership Application'!L""&ROW()-2) )-FIND(""="", IMPORTRANGE(""18RaQw448NnENcNftounuam8eQy"&"PVXS6StgZUz-RLzHA"",""'UTA Cat Coalition Membership Application'!L""&ROW()-2) )),1 ) , """")"),"")
A62: =IFERROR(__xludf.DUMMYFUNCTION("""COMPUTED_VALUE"""),44794.97482311343) -> 44794.975 | B62: TRUE | C62: =IF(A62<>"", IFERROR(IF(MONTH(A62) < 6, "Spring ", "Fall ") & IF(MONTH(A62) < 6, YEAR(A62), YEAR(A62) + IF(MONTH(A62) = 12, 1, 0)), ""), "") -> Fall 2022 | D62: =IFERROR(__xludf.DUMMYFUNCTION("""COMPUTED_VALUE"""),"angieriver508@gmail.com") -> angieriver508@gmail.com | E62: =IFERROR(__xludf.DUMMYFUNCTION("""COMPUTED_VALUE"""),"Angelina Rivera") -> Angelina Rivera | F62: =IFERROR(__xludf.DUMMYFUNCTION("""COMPUTED_VALUE"""),"AngRiv#5947") -> AngRiv#5947 | H62: =IFERROR(__xludf.DUMMYFUNCTION("""COMPUTED_VALUE"""),"(254) 205-7492") -> (254) 205-7492 | I62: =IFERROR(__xludf.DUMMYFUNCTION("""COMPUTED_VALUE"""),"Student") -> Student | J62: =IFERROR(__xludf.DUMMYFUNCTION("""COMPUTED_VALUE"""),"$15 Donation, Discord Verification") -> $15 Donation, Discord Verification | O62: =IFERROR(__xludf.DUMMYFUNCTION("""COMPUTED_VALUE"""),"Fundraising, PR, Membership, TNR, Feeding, Shelter Maintenance") -> Fundraising, PR, Membership, TNR, Feeding, Shelter Maintenance | P62: =IFERROR(__xludf.DUMMYFUNCTION("IFERROR( IMAGE( ""https://drive.google.com/uc?export=download&id=""&MID( IMPORTRANGE(""18RaQw448NnENcNftounuam8eQyPVXS6StgZUz-RLzHA"",""'UTA Cat Coalition Membership Application'!L""&ROW()-2) ,(FIND(""="", IMPORTRANGE(""18RaQw448NnENcNftounuam8eQyPVXS6St"&"gZUz-RLzHA"",""'UTA Cat Coalition Membership Application'!L""&ROW()-2) ))+1,LEN( IMPORTRANGE(""18RaQw448NnENcNftounuam8eQyPVXS6StgZUz-RLzHA"",""'UTA Cat Coalition Membership Application'!L""&ROW()-2) )-FIND(""="", IMPORTRANGE(""18RaQw448NnENcNftounuam8eQy"&"PVXS6StgZUz-RLzHA"",""'UTA Cat Coalition Membership Application'!L""&ROW()-2) )),1 ) , """")"),"")
A63: =IFERROR(__xludf.DUMMYFUNCTION("""COMPUTED_VALUE"""),44795.00702510416) -> 44795.007 | B63: TRUE | C63: =IF(A63<>"", IFERROR(IF(MONTH(A63) < 6, "Spring ", "Fall ") & IF(MONTH(A63) < 6, YEAR(A63), YEAR(A63) + IF(MONTH(A63) = 12, 1, 0)), ""), "") -> Fall 2022 | D63: =IFERROR(__xludf.DUMMYFUNCTION("""COMPUTED_VALUE"""),"ixs2264@mavs.uta.edu") -> ixs2264@mavs.uta.edu | E63: =IFERROR(__xludf.DUMMYFUNCTION("""COMPUTED_VALUE"""),"Isabel Silva") -> Isabel Silva | F63: =IFERROR(__xludf.DUMMYFUNCTION("""COMPUTED_VALUE"""),"lemonade #1929") -> lemonade #1929 | H63: =IFERROR(__xludf.DUMMYFUNCTION("""COMPUTED_VALUE"""),"(817) 818-6106") -> (817) 818-6106 | I63: =IFERROR(__xludf.DUMMYFUNCTION("""COMPUTED_VALUE"""),"Student") -> Student | J63: =IFERROR(__xludf.DUMMYFUNCTION("""COMPUTED_VALUE"""),"$15 Donation, Discord Verification") -> $15 Donation, Discord Verification | O63: =IFERROR(__xludf.DUMMYFUNCTION("""COMPUTED_VALUE"""),"Feeding") -> Feeding | P63: =IFERROR(__xludf.DUMMYFUNCTION("IFERROR( IMAGE( ""https://drive.google.com/uc?export=download&id=""&MID( IMPORTRANGE(""18RaQw448NnENcNftounuam8eQyPVXS6StgZUz-RLzHA"",""'UTA Cat Coalition Membership Application'!L""&ROW()-2) ,(FIND(""="", IMPORTRANGE(""18RaQw448NnENcNftounuam8eQyPVXS6St"&"gZUz-RLzHA"",""'UTA Cat Coalition Membership Application'!L""&ROW()-2) ))+1,LEN( IMPORTRANGE(""18RaQw448NnENcNftounuam8eQyPVXS6StgZUz-RLzHA"",""'UTA Cat Coalition Membership Application'!L""&ROW()-2) )-FIND(""="", IMPORTRANGE(""18RaQw448NnENcNftounuam8eQy"&"PVXS6StgZUz-RLzHA"",""'UTA Cat Coalition Membership Application'!L""&ROW()-2) )),1 ) , """")"),"") | Q63: Highlighted by previous officers
A64: =IFERROR(__xludf.DUMMYFUNCTION("""COMPUTED_VALUE"""),44795.00846840278) -> 44795.008 | B64: FALSE | C64: =IF(A64<>"", IFERROR(IF(MONTH(A64) < 6, "Spring ", "Fall ") & IF(MONTH(A64) < 6, YEAR(A64), YEAR(A64) + IF(MONTH(A64) = 12, 1, 0)), ""), "") -> Fall 2022 | D64: =IFERROR(__xludf.DUMMYFUNCTION("""COMPUTED_VALUE"""),"sxg4590@mav.uta.edu") -> sxg4590@mav.uta.edu | E64: =IFERROR(__xludf.DUMMYFUNCTION("""COMPUTED_VALUE"""),"Stammy Gao") -> Stammy Gao | F64: =IFERROR(__xludf.DUMMYFUNCTION("""COMPUTED_VALUE"""),"Stamberry #2542") -> Stamberry #2542 | H64: =IFERROR(__xludf.DUMMYFUNCTION("""COMPUTED_VALUE"""),"(281) 827-3957") -> (281) 827-3957 | I64: =IFERROR(__xludf.DUMMYFUNCTION("""COMPUTED_VALUE"""),"Student") -> Student | J64: =IFERROR(__xludf.DUMMYFUNCTION("""COMPUTED_VALUE"""),"$15 Donation, Discord Verification") -> $15 Donation, Discord Verification | O64: =IFERROR(__xludf.DUMMYFUNCTION("""COMPUTED_VALUE"""),"Fundraising, PR, Feeding, I’m an artist and would be more than happy to help with designs or things to post on the instagram!") -> Fundraising, PR, Feeding, I’m an artist and would be more than happy to help with designs or things to post on the instagram! | P64: =IFERROR(__xludf.DUMMYFUNCTION("IFERROR( IMAGE( ""https://drive.google.com/uc?export=download&id=""&MID( IMPORTRANGE(""18RaQw448NnENcNftounuam8eQyPVXS6StgZUz-RLzHA"",""'UTA Cat Coalition Membership Application'!L""&ROW()-2) ,(FIND(""="", IMPORTRANGE(""18RaQw448NnENcNftounuam8eQyPVXS6St"&"gZUz-RLzHA"",""'UTA Cat Coalition Membership Application'!L""&ROW()-2) ))+1,LEN( IMPORTRANGE(""18RaQw448NnENcNftounuam8eQyPVXS6StgZUz-RLzHA"",""'UTA Cat Coalition Membership Application'!L""&ROW()-2) )-FIND(""="", IMPORTRANGE(""18RaQw448NnENcNftounuam8eQy"&"PVXS6StgZUz-RLzHA"",""'UTA Cat Coalition Membership Application'!L""&ROW()-2) )),1 ) , """")"),"")
A65: =IFERROR(__xludf.DUMMYFUNCTION("""COMPUTED_VALUE"""),44795.027411180556) -> 44795.027 | B65: TRUE | C65: =IF(A65<>"", IFERROR(IF(MONTH(A65) < 6, "Spring ", "Fall ") & IF(MONTH(A65) < 6, YEAR(A65), YEAR(A65) + IF(MONTH(A65) = 12, 1, 0)), ""), "") -> Fall 2022 | D65: =IFERROR(__xludf.DUMMYFUNCTION("""COMPUTED_VALUE"""),"sxg4590@mavs.uta.edu") -> sxg4590@mavs.uta.edu | E65: =IFERROR(__xludf.DUMMYFUNCTION("""COMPUTED_VALUE"""),"Stammy Gao") -> Stammy Gao | F65: =IFERROR(__xludf.DUMMYFUNCTION("""COMPUTED_VALUE"""),"Stamberry #2542") -> Stamberry #2542 | H65: =IFERROR(__xludf.DUMMYFUNCTION("""COMPUTED_VALUE"""),"(281) 827-3957") -> (281) 827-3957 | I65: =IFERROR(__xludf.DUMMYFUNCTION("""COMPUTED_VALUE"""),"Student") -> Student | J65: =IFERROR(__xludf.DUMMYFUNCTION("""COMPUTED_VALUE"""),"$15 Donation, Discord Verification") -> $15 Donation, Discord Verification | O65: =IFERROR(__xludf.DUMMYFUNCTION("""COMPUTED_VALUE"""),"Fundraising, PR, Feeding, I’m an artist willing to draw things for posters or for instagram!") -> Fundraising, PR, Feeding, I’m an artist willing to draw things for posters or for instagram! | P65: =IFERROR(__xludf.DUMMYFUNCTION("IFERROR( IMAGE( ""https://drive.google.com/uc?export=download&id=""&MID( IMPORTRANGE(""18RaQw448NnENcNftounuam8eQyPVXS6StgZUz-RLzHA"",""'UTA Cat Coalition Membership Application'!L""&ROW()-2) ,(FIND(""="", IMPORTRANGE(""18RaQw448NnENcNftounuam8eQyPVXS6St"&"gZUz-RLzHA"",""'UTA Cat Coalition Membership Application'!L""&ROW()-2) ))+1,LEN( IMPORTRANGE(""18RaQw448NnENcNftounuam8eQyPVXS6StgZUz-RLzHA"",""'UTA Cat Coalition Membership Application'!L""&ROW()-2) )-FIND(""="", IMPORTRANGE(""18RaQw448NnENcNftounuam8eQy"&"PVXS6StgZUz-RLzHA"",""'UTA Cat Coalition Membership Application'!L""&ROW()-2) )),1 ) , """")"),"")
A66: =IFERROR(__xludf.DUMMYFUNCTION("""COMPUTED_VALUE"""),44795.623315902776) -> 44795.623 | B66: TRUE | C66: =IF(A66<>"", IFERROR(IF(MONTH(A66) < 6, "Spring ", "Fall ") & IF(MONTH(A66) < 6, YEAR(A66), YEAR(A66) + IF(MONTH(A66) = 12, 1, 0)), ""), "") -> Fall 2022 | D66: =IFERROR(__xludf.DUMMYFUNCTION("""COMPUTED_VALUE"""),"slm8241@mavs.uta.edu") -> slm8241@mavs.uta.edu | E66: =IFERROR(__xludf.DUMMYFUNCTION("""COMPUTED_VALUE"""),"Sophia Myers") -> Sophia Myers | F66: =IFERROR(__xludf.DUMMYFUNCTION("""COMPUTED_VALUE"""),"soph #0803") -> soph #0803 | H66: =IFERROR(__xludf.DUMMYFUNCTION("""COMPUTED_VALUE"""),"(210) 51-6584") -> (210) 51-6584 | I66: =IFERROR(__xludf.DUMMYFUNCTION("""COMPUTED_VALUE"""),"Student") -> Student | J66: =IFERROR(__xludf.DUMMYFUNCTION("""COMPUTED_VALUE"""),"$15 Donation, Discord Verification") -> $15 Donation, Discord Verification | O66: =IFERROR(__xludf.DUMMYFUNCTION("""COMPUTED_VALUE"""),"Feeding") -> Feeding | P66: =IFERROR(__xludf.DUMMYFUNCTION("IFERROR( IMAGE( ""https://drive.google.com/uc?export=download&id=""&MID( IMPORTRANGE(""18RaQw448NnENcNftounuam8eQyPVXS6StgZUz-RLzHA"",""'UTA Cat Coalition Membership Application'!L""&ROW()-2) ,(FIND(""="", IMPORTRANGE(""18RaQw448NnENcNftounuam8eQyPVXS6St"&"gZUz-RLzHA"",""'UTA Cat Coalition Membership Application'!L""&ROW()-2) ))+1,LEN( IMPORTRANGE(""18RaQw448NnENcNftounuam8eQyPVXS6StgZUz-RLzHA"",""'UTA Cat Coalition Membership Application'!L""&ROW()-2) )-FIND(""="", IMPORTRANGE(""18RaQw448NnENcNftounuam8eQy"&"PVXS6StgZUz-RLzHA"",""'UTA Cat Coalition Membership Application'!L""&ROW()-2) )),1 ) , """")"),"")
A67: =IFERROR(__xludf.DUMMYFUNCTION("""COMPUTED_VALUE"""),44795.87240951389) -> 44795.872 | B67: TRUE | C67: =IF(A67<>"", IFERROR(IF(MONTH(A67) < 6, "Spring ", "Fall ") & IF(MONTH(A67) < 6, YEAR(A67), YEAR(A67) + IF(MONTH(A67) = 12, 1, 0)), ""), "") -> Fall 2022 | D67: =IFERROR(__xludf.DUMMYFUNCTION("""COMPUTED_VALUE"""),"jch0145@mavs.uta.edu") -> jch0145@mavs.uta.edu | E67: =IFERROR(__xludf.DUMMYFUNCTION("""COMPUTED_VALUE"""),"Jordan Hunter") -> Jordan Hunter | F67: =IFERROR(__xludf.DUMMYFUNCTION("""COMPUTED_VALUE"""),"spoiledstrawberrymilk #7430") -> spoiledstrawberrymilk #7430 | H67: =IFERROR(__xludf.DUMMYFUNCTION("""COMPUTED_VALUE"""),"(469) 684-5580") -> (469) 684-5580 | I67: =IFERROR(__xludf.DUMMYFUNCTION("""COMPUTED_VALUE"""),"Student") -> Student | J67: =IFERROR(__xludf.DUMMYFUNCTION("""COMPUTED_VALUE"""),"$15 Donation, Discord Verification") -> $15 Donation, Discord Verification | O67: =IFERROR(__xludf.DUMMYFUNCTION("""COMPUTED_VALUE"""),"PR, Feeding") -> PR, Feeding | P67: =IFERROR(__xludf.DUMMYFUNCTION("IFERROR( IMAGE( ""https://drive.google.com/uc?export=download&id=""&MID( IMPORTRANGE(""18RaQw448NnENcNftounuam8eQyPVXS6StgZUz-RLzHA"",""'UTA Cat Coalition Membership Application'!L""&ROW()-2) ,(FIND(""="", IMPORTRANGE(""18RaQw448NnENcNftounuam8eQyPVXS6St"&"gZUz-RLzHA"",""'UTA Cat Coalition Membership Application'!L""&ROW()-2) ))+1,LEN( IMPORTRANGE(""18RaQw448NnENcNftounuam8eQyPVXS6StgZUz-RLzHA"",""'UTA Cat Coalition Membership Application'!L""&ROW()-2) )-FIND(""="", IMPORTRANGE(""18RaQw448NnENcNftounuam8eQy"&"PVXS6StgZUz-RLzHA"",""'UTA Cat Coalition Membership Application'!L""&ROW()-2) )),1 ) , """")"),"")
A68: =IFERROR(__xludf.DUMMYFUNCTION("""COMPUTED_VALUE"""),44795.90261518519) -> 44795.903 | B68: TRUE | C68: =IF(A68<>"", IFERROR(IF(MONTH(A68) < 6, "Spring ", "Fall ") & IF(MONTH(A68) < 6, YEAR(A68), YEAR(A68) + IF(MONTH(A68) = 12, 1, 0)), ""), "") -> Fall 2022 | D68: =IFERROR(__xludf.DUMMYFUNCTION("""COMPUTED_VALUE"""),"kendall.hendrix@mavs.uta.edu") -> kendall.hendrix@mavs.uta.edu | E68: =IFERROR(__xludf.DUMMYFUNCTION("""COMPUTED_VALUE"""),"Kendall Hendrix") -> Kendall Hendrix | F68: =IFERROR(__xludf.DUMMYFUNCTION("""COMPUTED_VALUE"""),"kendall#5965") -> kendall#5965 | H68: =IFERROR(__xludf.DUMMYFUNCTION("""COMPUTED_VALUE"""),"") | I68: =IFERROR(__xludf.DUMMYFUNCTION("""COMPUTED_VALUE"""),"Student") -> Student | J68: =IFERROR(__xludf.DUMMYFUNCTION("""COMPUTED_VALUE"""),"$15 Donation, Discord Verification") -> $15 Donation, Discord Verification | O68: =IFERROR(__xludf.DUMMYFUNCTION("""COMPUTED_VALUE"""),"Feeding, Shelter Maintenance") -> Feeding, Shelter Maintenance | P68: =IFERROR(__xludf.DUMMYFUNCTION("IFERROR( IMAGE( ""https://drive.google.com/uc?export=download&id=""&MID( IMPORTRANGE(""18RaQw448NnENcNftounuam8eQyPVXS6StgZUz-RLzHA"",""'UTA Cat Coalition Membership Application'!L""&ROW()-2) ,(FIND(""="", IMPORTRANGE(""18RaQw448NnENcNftounuam8eQyPVXS6St"&"gZUz-RLzHA"",""'UTA Cat Coalition Membership Application'!L""&ROW()-2) ))+1,LEN( IMPORTRANGE(""18RaQw448NnENcNftounuam8eQyPVXS6StgZUz-RLzHA"",""'UTA Cat Coalition Membership Application'!L""&ROW()-2) )-FIND(""="", IMPORTRANGE(""18RaQw448NnENcNftounuam8eQy"&"PVXS6StgZUz-RLzHA"",""'UTA Cat Coalition Membership Application'!L""&ROW()-2) )),1 ) , """")"),"")
A69: =IFERROR(__xludf.DUMMYFUNCTION("""COMPUTED_VALUE"""),44797.49308060185) -> 44797.493 | B69: TRUE | C69: =IF(A69<>"", IFERROR(IF(MONTH(A69) < 6, "Spring ", "Fall ") & IF(MONTH(A69) < 6, YEAR(A69), YEAR(A69) + IF(MONTH(A69) = 12, 1, 0)), ""), "") -> Fall 2022 | D69: =IFERROR(__xludf.DUMMYFUNCTION("""COMPUTED_VALUE"""),"eag1650@mavs.uta.edu") -> eag1650@mavs.uta.edu | E69: =IFERROR(__xludf.DUMMYFUNCTION("""COMPUTED_VALUE"""),"Emily Alicia Guadian") -> Emily Alicia Guadian | F69: =IFERROR(__xludf.DUMMYFUNCTION("""COMPUTED_VALUE"""),"medfast#0689") -> medfast#0689 | H69: =IFERROR(__xludf.DUMMYFUNCTION("""COMPUTED_VALUE"""),"(469) 845-5596") -> (469) 845-5596 | I69: =IFERROR(__xludf.DUMMYFUNCTION("""COMPUTED_VALUE"""),"Student") -> Student | J69: =IFERROR(__xludf.DUMMYFUNCTION("""COMPUTED_VALUE"""),"$15 Donation, Discord Verification") -> $15 Donation, Discord Verification | O69: =IFERROR(__xludf.DUMMYFUNCTION("""COMPUTED_VALUE"""),"Fundraising, Feeding, Shelter Maintenance") -> Fundraising, Feeding, Shelter Maintenance | P69: =IFERROR(__xludf.DUMMYFUNCTION("IFERROR( IMAGE( ""https://drive.google.com/uc?export=download&id=""&MID( IMPORTRANGE(""18RaQw448NnENcNftounuam8eQyPVXS6StgZUz-RLzHA"",""'UTA Cat Coalition Membership Application'!L""&ROW()-2) ,(FIND(""="", IMPORTRANGE(""18RaQw448NnENcNftounuam8eQyPVXS6St"&"gZUz-RLzHA"",""'UTA Cat Coalition Membership Application'!L""&ROW()-2) ))+1,LEN( IMPORTRANGE(""18RaQw448NnENcNftounuam8eQyPVXS6StgZUz-RLzHA"",""'UTA Cat Coalition Membership Application'!L""&ROW()-2) )-FIND(""="", IMPORTRANGE(""18RaQw448NnENcNftounuam8eQy"&"PVXS6StgZUz-RLzHA"",""'UTA Cat Coalition Membership Application'!L""&ROW()-2) )),1 ) , """")"),"")
A70: =IFERROR(__xludf.DUMMYFUNCTION("""COMPUTED_VALUE"""),44798.01854326389) -> 44798.019 | B70: TRUE | C70: =IF(A70<>"", IFERROR(IF(MONTH(A70) < 6, "Spring ", "Fall ") & IF(MONTH(A70) < 6, YEAR(A70), YEAR(A70) + IF(MONTH(A70) = 12, 1, 0)), ""), "") -> Fall 2022 | D70: =IFERROR(__xludf.DUMMYFUNCTION("""COMPUTED_VALUE"""),"tdi0557@mavs.uta.edu") -> tdi0557@mavs.uta.edu | E70: =IFERROR(__xludf.DUMMYFUNCTION("""COMPUTED_VALUE"""),"Tristan Inman") -> Tristan Inman | F70: =IFERROR(__xludf.DUMMYFUNCTION("""COMPUTED_VALUE"""),"Radicrane #8945") -> Radicrane #8945 | H70: =IFERROR(__xludf.DUMMYFUNCTION("""COMPUTED_VALUE"""),"(949) 554-9004") -> (949) 554-9004 | I70: =IFERROR(__xludf.DUMMYFUNCTION("""COMPUTED_VALUE"""),"Student") -> Student | J70: =IFERROR(__xludf.DUMMYFUNCTION("""COMPUTED_VALUE"""),"$15 Donation, Discord Verification") -> $15 Donation, Discord Verification | O70: =IFERROR(__xludf.DUMMYFUNCTION("""COMPUTED_VALUE"""),"Feeding") -> Feeding | P70: =IFERROR(__xludf.DUMMYFUNCTION("IFERROR( IMAGE( ""https://drive.google.com/uc?export=download&id=""&MID( IMPORTRANGE(""18RaQw448NnENcNftounuam8eQyPVXS6StgZUz-RLzHA"",""'UTA Cat Coalition Membership Application'!L""&ROW()-2) ,(FIND(""="", IMPORTRANGE(""18RaQw448NnENcNftounuam8eQyPVXS6St"&"gZUz-RLzHA"",""'UTA Cat Coalition Membership Application'!L""&ROW()-2) ))+1,LEN( IMPORTRANGE(""18RaQw448NnENcNftounuam8eQyPVXS6StgZUz-RLzHA"",""'UTA Cat Coalition Membership Application'!L""&ROW()-2) )-FIND(""="", IMPORTRANGE(""18RaQw448NnENcNftounuam8eQy"&"PVXS6StgZUz-RLzHA"",""'UTA Cat Coalition Membership Application'!L""&ROW()-2) )),1 ) , """")"),"")
A71: =IFERROR(__xludf.DUMMYFUNCTION("""COMPUTED_VALUE"""),44798.73595690972) -> 44798.736 | B71: TRUE | C71: =IF(A71<>"", IFERROR(IF(MONTH(A71) < 6, "Spring ", "Fall ") & IF(MONTH(A71) < 6, YEAR(A71), YEAR(A71) + IF(MONTH(A71) = 12, 1, 0)), ""), "") -> Fall 2022 | D71: =IFERROR(__xludf.DUMMYFUNCTION("""COMPUTED_VALUE"""),"ddh3117@mavs.uta.edu") -> ddh3117@mavs.uta.edu | E71: =IFERROR(__xludf.DUMMYFUNCTION("""COMPUTED_VALUE"""),"Delainey Huff") -> Delainey Huff | F71: =IFERROR(__xludf.DUMMYFUNCTION("""COMPUTED_VALUE"""),"Delainey#5149") -> Delainey#5149 | H71: =IFERROR(__xludf.DUMMYFUNCTION("""COMPUTED_VALUE"""),"(909) 91-2456") -> (909) 91-2456 | I71: =IFERROR(__xludf.DUMMYFUNCTION("""COMPUTED_VALUE"""),"Student") -> Student | J71: =IFERROR(__xludf.DUMMYFUNCTION("""COMPUTED_VALUE"""),"$15 Donation, Discord Verification") -> $15 Donation, Discord Verification | O71: =IFERROR(__xludf.DUMMYFUNCTION("""COMPUTED_VALUE"""),"TNR, Feeding, Shelter Maintenance") -> TNR, Feeding, Shelter Maintenance | P71: =IFERROR(__xludf.DUMMYFUNCTION("IFERROR( IMAGE( ""https://drive.google.com/uc?export=download&id=""&MID( IMPORTRANGE(""18RaQw448NnENcNftounuam8eQyPVXS6StgZUz-RLzHA"",""'UTA Cat Coalition Membership Application'!L""&ROW()-2) ,(FIND(""="", IMPORTRANGE(""18RaQw448NnENcNftounuam8eQyPVXS6St"&"gZUz-RLzHA"",""'UTA Cat Coalition Membership Application'!L""&ROW()-2) ))+1,LEN( IMPORTRANGE(""18RaQw448NnENcNftounuam8eQyPVXS6StgZUz-RLzHA"",""'UTA Cat Coalition Membership Application'!L""&ROW()-2) )-FIND(""="", IMPORTRANGE(""18RaQw448NnENcNftounuam8eQy"&"PVXS6StgZUz-RLzHA"",""'UTA Cat Coalition Membership Application'!L""&ROW()-2) )),1 ) , """")"),"")
A72: =IFERROR(__xludf.DUMMYFUNCTION("""COMPUTED_VALUE"""),44798.841774699074) -> 44798.842 | B72: TRUE | C72: =IF(A72<>"", IFERROR(IF(MONTH(A72) < 6, "Spring ", "Fall ") & IF(MONTH(A72) < 6, YEAR(A72), YEAR(A72) + IF(MONTH(A72) = 12, 1, 0)), ""), "") -> Fall 2022 | D72: =IFERROR(__xludf.DUMMYFUNCTION("""COMPUTED_VALUE"""),"axp7773@mavs.uta.edu") -> axp7773@mavs.uta.edu | E72: =IFERROR(__xludf.DUMMYFUNCTION("""COMPUTED_VALUE"""),"Alexis Pedraza") -> Alexis Pedraza | F72: =IFERROR(__xludf.DUMMYFUNCTION("""COMPUTED_VALUE"""),"☆*.｡.nyehhehheh .｡.*☆#6624") -> ☆*.｡.nyehhehheh .｡.*☆#6624 | H72: =IFERROR(__xludf.DUMMYFUNCTION("""COMPUTED_VALUE"""),"") | I72: =IFERROR(__xludf.DUMMYFUNCTION("""COMPUTED_VALUE"""),"Student") -> Student | J72: =IFERROR(__xludf.DUMMYFUNCTION("""COMPUTED_VALUE"""),"$15 Donation, Discord Verification") -> $15 Donation, Discord Verification | O72: =IFERROR(__xludf.DUMMYFUNCTION("""COMPUTED_VALUE"""),"Records Director (current position)") -> Records Director (current position) | P72: =IFERROR(__xludf.DUMMYFUNCTION("IFERROR( IMAGE( ""https://drive.google.com/uc?export=download&id=""&MID( IMPORTRANGE(""18RaQw448NnENcNftounuam8eQyPVXS6StgZUz-RLzHA"",""'UTA Cat Coalition Membership Application'!L""&ROW()-2) ,(FIND(""="", IMPORTRANGE(""18RaQw448NnENcNftounuam8eQyPVXS6St"&"gZUz-RLzHA"",""'UTA Cat Coalition Membership Application'!L""&ROW()-2) ))+1,LEN( IMPORTRANGE(""18RaQw448NnENcNftounuam8eQyPVXS6StgZUz-RLzHA"",""'UTA Cat Coalition Membership Application'!L""&ROW()-2) )-FIND(""="", IMPORTRANGE(""18RaQw448NnENcNftounuam8eQy"&"PVXS6StgZUz-RLzHA"",""'UTA Cat Coalition Membership Application'!L""&ROW()-2) )),1 ) , """")"),"")
A73: =IFERROR(__xludf.DUMMYFUNCTION("""COMPUTED_VALUE"""),44799.42293085648) -> 44799.423 | B73: TRUE | C73: =IF(A73<>"", IFERROR(IF(MONTH(A73) < 6, "Spring ", "Fall ") & IF(MONTH(A73) < 6, YEAR(A73), YEAR(A73) + IF(MONTH(A73) = 12, 1, 0)), ""), "") -> Fall 2022 | D73: =IFERROR(__xludf.DUMMYFUNCTION("""COMPUTED_VALUE"""),"mmm0956@mavs.uta.edu") -> mmm0956@mavs.uta.edu | E73: =IFERROR(__xludf.DUMMYFUNCTION("""COMPUTED_VALUE"""),"Madeline Narcisse Mendoza (Preferred first name: Min)") -> Madeline Narcisse Mendoza (Preferred first name: Min) | F73: =IFERROR(__xludf.DUMMYFUNCTION("""COMPUTED_VALUE"""),"nebuleii#0729") -> nebuleii#0729 | H73: =IFERROR(__xludf.DUMMYFUNCTION("""COMPUTED_VALUE"""),"(281) 606-9840") -> (281) 606-9840 | I73: =IFERROR(__xludf.DUMMYFUNCTION("""COMPUTED_VALUE"""),"Student") -> Student | J73: =IFERROR(__xludf.DUMMYFUNCTION("""COMPUTED_VALUE"""),"$15 Donation, Discord Verification") -> $15 Donation, Discord Verification | O73: =IFERROR(__xludf.DUMMYFUNCTION("""COMPUTED_VALUE"""),"PR, Feeding") -> PR, Feeding | P73: =IFERROR(__xludf.DUMMYFUNCTION("IFERROR( IMAGE( ""https://drive.google.com/uc?export=download&id=""&MID( IMPORTRANGE(""18RaQw448NnENcNftounuam8eQyPVXS6StgZUz-RLzHA"",""'UTA Cat Coalition Membership Application'!L""&ROW()-2) ,(FIND(""="", IMPORTRANGE(""18RaQw448NnENcNftounuam8eQyPVXS6St"&"gZUz-RLzHA"",""'UTA Cat Coalition Membership Application'!L""&ROW()-2) ))+1,LEN( IMPORTRANGE(""18RaQw448NnENcNftounuam8eQyPVXS6StgZUz-RLzHA"",""'UTA Cat Coalition Membership Application'!L""&ROW()-2) )-FIND(""="", IMPORTRANGE(""18RaQw448NnENcNftounuam8eQy"&"PVXS6StgZUz-RLzHA"",""'UTA Cat Coalition Membership Application'!L""&ROW()-2) )),1 ) , """")"),"")
A74: =IFERROR(__xludf.DUMMYFUNCTION("""COMPUTED_VALUE"""),44799.42531064815) -> 44799.425 | B74: TRUE | C74: =IF(A74<>"", IFERROR(IF(MONTH(A74) < 6, "Spring ", "Fall ") & IF(MONTH(A74) < 6, YEAR(A74), YEAR(A74) + IF(MONTH(A74) = 12, 1, 0)), ""), "") -> Fall 2022 | D74: =IFERROR(__xludf.DUMMYFUNCTION("""COMPUTED_VALUE"""),"mxh5508@mavs.uta.edu") -> mxh5508@mavs.uta.edu | E74: =IFERROR(__xludf.DUMMYFUNCTION("""COMPUTED_VALUE"""),"Maritza Hernandez") -> Maritza Hernandez | F74: =IFERROR(__xludf.DUMMYFUNCTION("""COMPUTED_VALUE"""),"Miiko #6767") -> Miiko #6767 | H74: =IFERROR(__xludf.DUMMYFUNCTION("""COMPUTED_VALUE"""),"(940) 503-7139") -> (940) 503-7139 | I74: =IFERROR(__xludf.DUMMYFUNCTION("""COMPUTED_VALUE"""),"Student") -> Student | J74: =IFERROR(__xludf.DUMMYFUNCTION("""COMPUTED_VALUE"""),"$15 Donation, Discord Verification") -> $15 Donation, Discord Verification | O74: =IFERROR(__xludf.DUMMYFUNCTION("""COMPUTED_VALUE"""),"Feeding") -> Feeding | P74: =IFERROR(__xludf.DUMMYFUNCTION("IFERROR( IMAGE( ""https://drive.google.com/uc?export=download&id=""&MID( IMPORTRANGE(""18RaQw448NnENcNftounuam8eQyPVXS6StgZUz-RLzHA"",""'UTA Cat Coalition Membership Application'!L""&ROW()-2) ,(FIND(""="", IMPORTRANGE(""18RaQw448NnENcNftounuam8eQyPVXS6St"&"gZUz-RLzHA"",""'UTA Cat Coalition Membership Application'!L""&ROW()-2) ))+1,LEN( IMPORTRANGE(""18RaQw448NnENcNftounuam8eQyPVXS6StgZUz-RLzHA"",""'UTA Cat Coalition Membership Application'!L""&ROW()-2) )-FIND(""="", IMPORTRANGE(""18RaQw448NnENcNftounuam8eQy"&"PVXS6StgZUz-RLzHA"",""'UTA Cat Coalition Membership Application'!L""&ROW()-2) )),1 ) , """")"),"")
A75: =IFERROR(__xludf.DUMMYFUNCTION("""COMPUTED_VALUE"""),44800.52422255787) -> 44800.524 | B75: TRUE | C75: =IF(A75<>"", IFERROR(IF(MONTH(A75) < 6, "Spring ", "Fall ") & IF(MONTH(A75) < 6, YEAR(A75), YEAR(A75) + IF(MONTH(A75) = 12, 1, 0)), ""), "") -> Fall 2022 | D75: =IFERROR(__xludf.DUMMYFUNCTION("""COMPUTED_VALUE"""),"rtp0957@mavs.uta.edu") -> rtp0957@mavs.uta.edu | E75: =IFERROR(__xludf.DUMMYFUNCTION("""COMPUTED_VALUE"""),"Rey Paolo Tolentino Pecson") -> Rey Paolo Tolentino Pecson | F75: =IFERROR(__xludf.DUMMYFUNCTION("""COMPUTED_VALUE"""),"tanuki #0729") -> tanuki #0729 | H75: =IFERROR(__xludf.DUMMYFUNCTION("""COMPUTED_VALUE"""),"(345) 955-4726") -> (345) 955-4726 | I75: =IFERROR(__xludf.DUMMYFUNCTION("""COMPUTED_VALUE"""),"Student") -> Student | J75: =IFERROR(__xludf.DUMMYFUNCTION("""COMPUTED_VALUE"""),"$15 Donation, Discord Verification") -> $15 Donation, Discord Verification | O75: =IFERROR(__xludf.DUMMYFUNCTION("""COMPUTED_VALUE"""),"PR, Feeding") -> PR, Feeding | P75: =IFERROR(__xludf.DUMMYFUNCTION("IFERROR( IMAGE( ""https://drive.google.com/uc?export=download&id=""&MID( IMPORTRANGE(""18RaQw448NnENcNftounuam8eQyPVXS6StgZUz-RLzHA"",""'UTA Cat Coalition Membership Application'!L""&ROW()-2) ,(FIND(""="", IMPORTRANGE(""18RaQw448NnENcNftounuam8eQyPVXS6St"&"gZUz-RLzHA"",""'UTA Cat Coalition Membership Application'!L""&ROW()-2) ))+1,LEN( IMPORTRANGE(""18RaQw448NnENcNftounuam8eQyPVXS6StgZUz-RLzHA"",""'UTA Cat Coalition Membership Application'!L""&ROW()-2) )-FIND(""="", IMPORTRANGE(""18RaQw448NnENcNftounuam8eQy"&"PVXS6StgZUz-RLzHA"",""'UTA Cat Coalition Membership Application'!L""&ROW()-2) )),1 ) , """")"),"")
A76: =IFERROR(__xludf.DUMMYFUNCTION("""COMPUTED_VALUE"""),44800.624772951385) -> 44800.625 | B76: TRUE | C76: =IF(A76<>"", IFERROR(IF(MONTH(A76) < 6, "Spring ", "Fall ") & IF(MONTH(A76) < 6, YEAR(A76), YEAR(A76) + IF(MONTH(A76) = 12, 1, 0)), ""), "") -> Fall 2022 | D76: =IFERROR(__xludf.DUMMYFUNCTION("""COMPUTED_VALUE"""),"ges2494@mavs.uta.edu") -> ges2494@mavs.uta.edu | E76: =IFERROR(__xludf.DUMMYFUNCTION("""COMPUTED_VALUE"""),"Garrett Schoen") -> Garrett Schoen | F76: =IFERROR(__xludf.DUMMYFUNCTION("""COMPUTED_VALUE"""),"Tex #4849") -> Tex #4849 | H76: =IFERROR(__xludf.DUMMYFUNCTION("""COMPUTED_VALUE"""),"(832) 603-0591") -> (832) 603-0591 | I76: =IFERROR(__xludf.DUMMYFUNCTION("""COMPUTED_VALUE"""),"Student") -> Student | J76: =IFERROR(__xludf.DUMMYFUNCTION("""COMPUTED_VALUE"""),"$15 Donation, Discord Verification") -> $15 Donation, Discord Verification | O76: =IFERROR(__xludf.DUMMYFUNCTION("""COMPUTED_VALUE"""),"PR, Overnight TNR, Feeding") -> PR, Overnight TNR, Feeding | P76: =IFERROR(__xludf.DUMMYFUNCTION("IFERROR( IMAGE( ""https://drive.google.com/uc?export=download&id=""&MID( IMPORTRANGE(""18RaQw448NnENcNftounuam8eQyPVXS6StgZUz-RLzHA"",""'UTA Cat Coalition Membership Application'!L""&ROW()-2) ,(FIND(""="", IMPORTRANGE(""18RaQw448NnENcNftounuam8eQyPVXS6St"&"gZUz-RLzHA"",""'UTA Cat Coalition Membership Application'!L""&ROW()-2) ))+1,LEN( IMPORTRANGE(""18RaQw448NnENcNftounuam8eQyPVXS6StgZUz-RLzHA"",""'UTA Cat Coalition Membership Application'!L""&ROW()-2) )-FIND(""="", IMPORTRANGE(""18RaQw448NnENcNftounuam8eQy"&"PVXS6StgZUz-RLzHA"",""'UTA Cat Coalition Membership Application'!L""&ROW()-2) )),1 ) , """")"),"")
A77: =IFERROR(__xludf.DUMMYFUNCTION("""COMPUTED_VALUE"""),44800.67831481481) -> 44800.678 | B77: TRUE | C77: =IF(A77<>"", IFERROR(IF(MONTH(A77) < 6, "Spring ", "Fall ") & IF(MONTH(A77) < 6, YEAR(A77), YEAR(A77) + IF(MONTH(A77) = 12, 1, 0)), ""), "") -> Fall 2022 | D77: =IFERROR(__xludf.DUMMYFUNCTION("""COMPUTED_VALUE"""),"djo4952@mavs.uta.edu") -> djo4952@mavs.uta.edu | E77: =IFERROR(__xludf.DUMMYFUNCTION("""COMPUTED_VALUE"""),"Kara Oldenhouse") -> Kara Oldenhouse | F77: =IFERROR(__xludf.DUMMYFUNCTION("""COMPUTED_VALUE"""),"Gracie_Fizz#9875") -> Gracie_Fizz#9875 | H77: =IFERROR(__xludf.DUMMYFUNCTION("""COMPUTED_VALUE"""),"(512) 608-5508") -> (512) 608-5508 | I77: =IFERROR(__xludf.DUMMYFUNCTION("""COMPUTED_VALUE"""),"Student") -> Student | J77: =IFERROR(__xludf.DUMMYFUNCTION("""COMPUTED_VALUE"""),"$15 Donation, Discord Verification") -> $15 Donation, Discord Verification | O77: =IFERROR(__xludf.DUMMYFUNCTION("""COMPUTED_VALUE"""),"Fundraising, PR, Membership, TNR, Overnight TNR, Feeding, Fostering, Shelter Maintenance") -> Fundraising, PR, Membership, TNR, Overnight TNR, Feeding, Fostering, Shelter Maintenance | P77: =IFERROR(__xludf.DUMMYFUNCTION("IFERROR( IMAGE( ""https://drive.google.com/uc?export=download&id=""&MID( IMPORTRANGE(""18RaQw448NnENcNftounuam8eQyPVXS6StgZUz-RLzHA"",""'UTA Cat Coalition Membership Application'!L""&ROW()-2) ,(FIND(""="", IMPORTRANGE(""18RaQw448NnENcNftounuam8eQyPVXS6St"&"gZUz-RLzHA"",""'UTA Cat Coalition Membership Application'!L""&ROW()-2) ))+1,LEN( IMPORTRANGE(""18RaQw448NnENcNftounuam8eQyPVXS6StgZUz-RLzHA"",""'UTA Cat Coalition Membership Application'!L""&ROW()-2) )-FIND(""="", IMPORTRANGE(""18RaQw448NnENcNftounuam8eQy"&"PVXS6StgZUz-RLzHA"",""'UTA Cat Coalition Membership Application'!L""&ROW()-2) )),1 ) , """")"),"")
A78: =IFERROR(__xludf.DUMMYFUNCTION("""COMPUTED_VALUE"""),44802.02894364583) -> 44802.029 | B78: TRUE | C78: =IF(A78<>"", IFERROR(IF(MONTH(A78) < 6, "Spring ", "Fall ") & IF(MONTH(A78) < 6, YEAR(A78), YEAR(A78) + IF(MONTH(A78) = 12, 1, 0)), ""), "") -> Fall 2022 | D78: =IFERROR(__xludf.DUMMYFUNCTION("""COMPUTED_VALUE"""),"ixn7783@mavs.uta.edu") -> ixn7783@mavs.uta.edu | E78: =IFERROR(__xludf.DUMMYFUNCTION("""COMPUTED_VALUE"""),"Ian Null") -> Ian Null | F78: =IFERROR(__xludf.DUMMYFUNCTION("""COMPUTED_VALUE"""),"Godshand#1044") -> Godshand#1044 | H78: =IFERROR(__xludf.DUMMYFUNCTION("""COMPUTED_VALUE"""),"(512) 591-3665") -> (512) 591-3665 | I78: =IFERROR(__xludf.DUMMYFUNCTION("""COMPUTED_VALUE"""),"Student") -> Student | J78: =IFERROR(__xludf.DUMMYFUNCTION("""COMPUTED_VALUE"""),"Food/Litter Donation") -> Food/Litter Donation | O78: =IFERROR(__xludf.DUMMYFUNCTION("""COMPUTED_VALUE"""),"Fundraising, PR, Membership") -> Fundraising, PR, Membership | P78: =IFERROR(__xludf.DUMMYFUNCTION("IFERROR( IMAGE( ""https://drive.google.com/uc?export=download&id=""&MID( IMPORTRANGE(""18RaQw448NnENcNftounuam8eQyPVXS6StgZUz-RLzHA"",""'UTA Cat Coalition Membership Application'!L""&ROW()-2) ,(FIND(""="", IMPORTRANGE(""18RaQw448NnENcNftounuam8eQyPVXS6St"&"gZUz-RLzHA"",""'UTA Cat Coalition Membership Application'!L""&ROW()-2) ))+1,LEN( IMPORTRANGE(""18RaQw448NnENcNftounuam8eQyPVXS6StgZUz-RLzHA"",""'UTA Cat Coalition Membership Application'!L""&ROW()-2) )-FIND(""="", IMPORTRANGE(""18RaQw448NnENcNftounuam8eQy"&"PVXS6StgZUz-RLzHA"",""'UTA Cat Coalition Membership Application'!L""&ROW()-2) )),1 ) , """")"),"")
A79: =IFERROR(__xludf.DUMMYFUNCTION("""COMPUTED_VALUE"""),44802.60263138889) -> 44802.603 | B79: TRUE | C79: =IF(A79<>"", IFERROR(IF(MONTH(A79) < 6, "Spring ", "Fall ") & IF(MONTH(A79) < 6, YEAR(A79), YEAR(A79) + IF(MONTH(A79) = 12, 1, 0)), ""), "") -> Fall 2022 | D79: =IFERROR(__xludf.DUMMYFUNCTION("""COMPUTED_VALUE"""),"zdm7610@mavs.uta.edu") -> zdm7610@mavs.uta.edu | E79: =IFERROR(__xludf.DUMMYFUNCTION("""COMPUTED_VALUE"""),"Zachary Markines") -> Zachary Markines | F79: =IFERROR(__xludf.DUMMYFUNCTION("""COMPUTED_VALUE"""),"mostlyasian#1627") -> mostlyasian#1627 | H79: =IFERROR(__xludf.DUMMYFUNCTION("""COMPUTED_VALUE"""),"(817) 223-0033") -> (817) 223-0033 | I79: =IFERROR(__xludf.DUMMYFUNCTION("""COMPUTED_VALUE"""),"Student") -> Student | J79: =IFERROR(__xludf.DUMMYFUNCTION("""COMPUTED_VALUE"""),"$15 Donation, Discord Verification") -> $15 Donation, Discord Verification | O79: =IFERROR(__xludf.DUMMYFUNCTION("""COMPUTED_VALUE"""),"Fundraising, PR, Membership, TNR, Overnight TNR, Feeding, Fostering, Shelter Maintenance") -> Fundraising, PR, Membership, TNR, Overnight TNR, Feeding, Fostering, Shelter Maintenance | P79: =IFERROR(__xludf.DUMMYFUNCTION("IFERROR( IMAGE( ""https://drive.google.com/uc?export=download&id=""&MID( IMPORTRANGE(""18RaQw448NnENcNftounuam8eQyPVXS6StgZUz-RLzHA"",""'UTA Cat Coalition Membership Application'!L""&ROW()-2) ,(FIND(""="", IMPORTRANGE(""18RaQw448NnENcNftounuam8eQyPVXS6St"&"gZUz-RLzHA"",""'UTA Cat Coalition Membership Application'!L""&ROW()-2) ))+1,LEN( IMPORTRANGE(""18RaQw448NnENcNftounuam8eQyPVXS6StgZUz-RLzHA"",""'UTA Cat Coalition Membership Application'!L""&ROW()-2) )-FIND(""="", IMPORTRANGE(""18RaQw448NnENcNftounuam8eQy"&"PVXS6StgZUz-RLzHA"",""'UTA Cat Coalition Membership Application'!L""&ROW()-2) )),1 ) , """")"),"")
A80: =IFERROR(__xludf.DUMMYFUNCTION("""COMPUTED_VALUE"""),44802.682296388884) -> 44802.682 | B80: TRUE | C80: =IF(A80<>"", IFERROR(IF(MONTH(A80) < 6, "Spring ", "Fall ") & IF(MONTH(A80) < 6, YEAR(A80), YEAR(A80) + IF(MONTH(A80) = 12, 1, 0)), ""), "") -> Fall 2022 | D80: =IFERROR(__xludf.DUMMYFUNCTION("""COMPUTED_VALUE"""),"jjm8571@mavs.uta.edu") -> jjm8571@mavs.uta.edu | E80: =IFERROR(__xludf.DUMMYFUNCTION("""COMPUTED_VALUE"""),"Jenifer Martinez ") -> Jenifer Martinez | F80: =IFERROR(__xludf.DUMMYFUNCTION("""COMPUTED_VALUE"""),"Jenna0614#1706") -> Jenna0614#1706 | H80: =IFERROR(__xludf.DUMMYFUNCTION("""COMPUTED_VALUE"""),"(214) 598-7031") -> (214) 598-7031 | I80: =IFERROR(__xludf.DUMMYFUNCTION("""COMPUTED_VALUE"""),"Student") -> Student | J80: =IFERROR(__xludf.DUMMYFUNCTION("""COMPUTED_VALUE"""),"$15 Donation, Discord Verification") -> $15 Donation, Discord Verification | O80: =IFERROR(__xludf.DUMMYFUNCTION("""COMPUTED_VALUE"""),"Fundraising, PR, Membership, Feeding") -> Fundraising, PR, Membership, Feeding | P80: =IFERROR(__xludf.DUMMYFUNCTION("IFERROR( IMAGE( ""https://drive.google.com/uc?export=download&id=""&MID( IMPORTRANGE(""18RaQw448NnENcNftounuam8eQyPVXS6StgZUz-RLzHA"",""'UTA Cat Coalition Membership Application'!L""&ROW()-2) ,(FIND(""="", IMPORTRANGE(""18RaQw448NnENcNftounuam8eQyPVXS6St"&"gZUz-RLzHA"",""'UTA Cat Coalition Membership Application'!L""&ROW()-2) ))+1,LEN( IMPORTRANGE(""18RaQw448NnENcNftounuam8eQyPVXS6StgZUz-RLzHA"",""'UTA Cat Coalition Membership Application'!L""&ROW()-2) )-FIND(""="", IMPORTRANGE(""18RaQw448NnENcNftounuam8eQy"&"PVXS6StgZUz-RLzHA"",""'UTA Cat Coalition Membership Application'!L""&ROW()-2) )),1 ) , """")"),"")
A81: =IFERROR(__xludf.DUMMYFUNCTION("""COMPUTED_VALUE"""),44803.997147268514) -> 44803.997 | B81: TRUE | C81: =IF(A81<>"", IFERROR(IF(MONTH(A81) < 6, "Spring ", "Fall ") & IF(MONTH(A81) < 6, YEAR(A81), YEAR(A81) + IF(MONTH(A81) = 12, 1, 0)), ""), "") -> Fall 2022 | D81: =IFERROR(__xludf.DUMMYFUNCTION("""COMPUTED_VALUE"""),"cindylou.skipper@mavs.uta.edu") -> cindylou.skipper@mavs.uta.edu | E81: =IFERROR(__xludf.DUMMYFUNCTION("""COMPUTED_VALUE"""),"Cindy Lou Skipper") -> Cindy Lou Skipper | F81: =IFERROR(__xludf.DUMMYFUNCTION("""COMPUTED_VALUE"""),"meiyingcinskip#2026") -> meiyingcinskip#2026 | H81: =IFERROR(__xludf.DUMMYFUNCTION("""COMPUTED_VALUE"""),"(682) 551-7350") -> (682) 551-7350 | I81: =IFERROR(__xludf.DUMMYFUNCTION("""COMPUTED_VALUE"""),"Student") -> Student | J81: =IFERROR(__xludf.DUMMYFUNCTION("""COMPUTED_VALUE"""),"Food/Litter Donation") -> Food/Litter Donation | O81: =IFERROR(__xludf.DUMMYFUNCTION("""COMPUTED_VALUE"""),"Feeding") -> Feeding | P81: =IFERROR(__xludf.DUMMYFUNCTION("IFERROR( IMAGE( ""https://drive.google.com/uc?export=download&id=""&MID( IMPORTRANGE(""18RaQw448NnENcNftounuam8eQyPVXS6StgZUz-RLzHA"",""'UTA Cat Coalition Membership Application'!L""&ROW()-2) ,(FIND(""="", IMPORTRANGE(""18RaQw448NnENcNftounuam8eQyPVXS6St"&"gZUz-RLzHA"",""'UTA Cat Coalition Membership Application'!L""&ROW()-2) ))+1,LEN( IMPORTRANGE(""18RaQw448NnENcNftounuam8eQyPVXS6StgZUz-RLzHA"",""'UTA Cat Coalition Membership Application'!L""&ROW()-2) )-FIND(""="", IMPORTRANGE(""18RaQw448NnENcNftounuam8eQy"&"PVXS6StgZUz-RLzHA"",""'UTA Cat Coalition Membership Application'!L""&ROW()-2) )),1 ) , """")"),"")
A82: =IFERROR(__xludf.DUMMYFUNCTION("""COMPUTED_VALUE"""),44804.4950583912) -> 44804.495 | B82: TRUE | C82: =IF(A82<>"", IFERROR(IF(MONTH(A82) < 6, "Spring ", "Fall ") & IF(MONTH(A82) < 6, YEAR(A82), YEAR(A82) + IF(MONTH(A82) = 12, 1, 0)), ""), "") -> Fall 2022 | D82: =IFERROR(__xludf.DUMMYFUNCTION("""COMPUTED_VALUE"""),"jlg6712@mavs.uta.edu") -> jlg6712@mavs.uta.edu | E82: =IFERROR(__xludf.DUMMYFUNCTION("""COMPUTED_VALUE"""),"Josie Geiogue") -> Josie Geiogue | F82: =IFERROR(__xludf.DUMMYFUNCTION("""COMPUTED_VALUE"""),"CanChanFish #9667") -> CanChanFish #9667 | H82: =IFERROR(__xludf.DUMMYFUNCTION("""COMPUTED_VALUE"""),"(214) 406-1058") -> (214) 406-1058 | I82: =IFERROR(__xludf.DUMMYFUNCTION("""COMPUTED_VALUE"""),"Student") -> Student | J82: =IFERROR(__xludf.DUMMYFUNCTION("""COMPUTED_VALUE"""),"$15 Donation, Discord Verification") -> $15 Donation, Discord Verification | O82: =IFERROR(__xludf.DUMMYFUNCTION("""COMPUTED_VALUE"""),"Fundraising, Feeding") -> Fundraising, Feeding | P82: =IFERROR(__xludf.DUMMYFUNCTION("IFERROR( IMAGE( ""https://drive.google.com/uc?export=download&id=""&MID( IMPORTRANGE(""18RaQw448NnENcNftounuam8eQyPVXS6StgZUz-RLzHA"",""'UTA Cat Coalition Membership Application'!L""&ROW()-2) ,(FIND(""="", IMPORTRANGE(""18RaQw448NnENcNftounuam8eQyPVXS6St"&"gZUz-RLzHA"",""'UTA Cat Coalition Membership Application'!L""&ROW()-2) ))+1,LEN( IMPORTRANGE(""18RaQw448NnENcNftounuam8eQyPVXS6StgZUz-RLzHA"",""'UTA Cat Coalition Membership Application'!L""&ROW()-2) )-FIND(""="", IMPORTRANGE(""18RaQw448NnENcNftounuam8eQy"&"PVXS6StgZUz-RLzHA"",""'UTA Cat Coalition Membership Application'!L""&ROW()-2) )),1 ) , """")"),"")
A83: =IFERROR(__xludf.DUMMYFUNCTION("""COMPUTED_VALUE"""),44804.547506504634) -> 44804.548 | B83: TRUE | C83: =IF(A83<>"", IFERROR(IF(MONTH(A83) < 6, "Spring ", "Fall ") & IF(MONTH(A83) < 6, YEAR(A83), YEAR(A83) + IF(MONTH(A83) = 12, 1, 0)), ""), "") -> Fall 2022 | D83: =IFERROR(__xludf.DUMMYFUNCTION("""COMPUTED_VALUE"""),"claire.harvey@mavs.uta.edu") -> claire.harvey@mavs.uta.edu | E83: =IFERROR(__xludf.DUMMYFUNCTION("""COMPUTED_VALUE"""),"Claire Harvey ") -> Claire Harvey | F83: =IFERROR(__xludf.DUMMYFUNCTION("""COMPUTED_VALUE"""),"Claire.harvey #8038") -> Claire.harvey #8038 | H83: =IFERROR(__xludf.DUMMYFUNCTION("""COMPUTED_VALUE"""),"(817) 471-6638") -> (817) 471-6638 | I83: =IFERROR(__xludf.DUMMYFUNCTION("""COMPUTED_VALUE"""),"Student") -> Student | J83: =IFERROR(__xludf.DUMMYFUNCTION("""COMPUTED_VALUE"""),"Food/Litter Donation") -> Food/Litter Donation | O83: =IFERROR(__xludf.DUMMYFUNCTION("""COMPUTED_VALUE"""),"TNR, Fostering, Door to door shot/ vet transportation ") -> TNR, Fostering, Door to door shot/ vet transportation | P83: =IFERROR(__xludf.DUMMYFUNCTION("IFERROR( IMAGE( ""https://drive.google.com/uc?export=download&id=""&MID( IMPORTRANGE(""18RaQw448NnENcNftounuam8eQyPVXS6StgZUz-RLzHA"",""'UTA Cat Coalition Membership Application'!L""&ROW()-2) ,(FIND(""="", IMPORTRANGE(""18RaQw448NnENcNftounuam8eQyPVXS6St"&"gZUz-RLzHA"",""'UTA Cat Coalition Membership Application'!L""&ROW()-2) ))+1,LEN( IMPORTRANGE(""18RaQw448NnENcNftounuam8eQyPVXS6StgZUz-RLzHA"",""'UTA Cat Coalition Membership Application'!L""&ROW()-2) )-FIND(""="", IMPORTRANGE(""18RaQw448NnENcNftounuam8eQy"&"PVXS6StgZUz-RLzHA"",""'UTA Cat Coalition Membership Application'!L""&ROW()-2) )),1 ) , """")"),"")
A84: =IFERROR(__xludf.DUMMYFUNCTION("""COMPUTED_VALUE"""),44804.57050202547) -> 44804.571 | B84: TRUE | C84: =IF(A84<>"", IFERROR(IF(MONTH(A84) < 6, "Spring ", "Fall ") & IF(MONTH(A84) < 6, YEAR(A84), YEAR(A84) + IF(MONTH(A84) = 12, 1, 0)), ""), "") -> Fall 2022 | D84: =IFERROR(__xludf.DUMMYFUNCTION("""COMPUTED_VALUE"""),"hnf0740@mavs.uta.edu") -> hnf0740@mavs.uta.edu | E84: =IFERROR(__xludf.DUMMYFUNCTION("""COMPUTED_VALUE"""),"Hannah Flores") -> Hannah Flores | F84: =IFERROR(__xludf.DUMMYFUNCTION("""COMPUTED_VALUE"""),"Hamcat #0665") -> Hamcat #0665 | H84: =IFERROR(__xludf.DUMMYFUNCTION("""COMPUTED_VALUE"""),"(361) 960-6665") -> (361) 960-6665 | I84: =IFERROR(__xludf.DUMMYFUNCTION("""COMPUTED_VALUE"""),"Student") -> Student | J84: =IFERROR(__xludf.DUMMYFUNCTION("""COMPUTED_VALUE"""),"$15 Donation, Discord Verification") -> $15 Donation, Discord Verification | O84: =IFERROR(__xludf.DUMMYFUNCTION("""COMPUTED_VALUE"""),"Fundraising, Feeding") -> Fundraising, Feeding | P84: =IFERROR(__xludf.DUMMYFUNCTION("IFERROR( IMAGE( ""https://drive.google.com/uc?export=download&id=""&MID( IMPORTRANGE(""18RaQw448NnENcNftounuam8eQyPVXS6StgZUz-RLzHA"",""'UTA Cat Coalition Membership Application'!L""&ROW()-2) ,(FIND(""="", IMPORTRANGE(""18RaQw448NnENcNftounuam8eQyPVXS6St"&"gZUz-RLzHA"",""'UTA Cat Coalition Membership Application'!L""&ROW()-2) ))+1,LEN( IMPORTRANGE(""18RaQw448NnENcNftounuam8eQyPVXS6StgZUz-RLzHA"",""'UTA Cat Coalition Membership Application'!L""&ROW()-2) )-FIND(""="", IMPORTRANGE(""18RaQw448NnENcNftounuam8eQy"&"PVXS6StgZUz-RLzHA"",""'UTA Cat Coalition Membership Application'!L""&ROW()-2) )),1 ) , """")"),"")
A85: =IFERROR(__xludf.DUMMYFUNCTION("""COMPUTED_VALUE"""),44804.583375138885) -> 44804.583 | B85: TRUE | C85: =IF(A85<>"", IFERROR(IF(MONTH(A85) < 6, "Spring ", "Fall ") & IF(MONTH(A85) < 6, YEAR(A85), YEAR(A85) + IF(MONTH(A85) = 12, 1, 0)), ""), "") -> Fall 2022 | D85: =IFERROR(__xludf.DUMMYFUNCTION("""COMPUTED_VALUE"""),"dmc9619@mavs.uta.edu") -> dmc9619@mavs.uta.edu | E85: =IFERROR(__xludf.DUMMYFUNCTION("""COMPUTED_VALUE"""),"Kat Cedullo") -> Kat Cedullo | F85: =IFERROR(__xludf.DUMMYFUNCTION("""COMPUTED_VALUE"""),"katlovescake#0461") -> katlovescake#0461 | H85: =IFERROR(__xludf.DUMMYFUNCTION("""COMPUTED_VALUE"""),"(978) 594-3163") -> (978) 594-3163 | I85: =IFERROR(__xludf.DUMMYFUNCTION("""COMPUTED_VALUE"""),"Student") -> Student | J85: =IFERROR(__xludf.DUMMYFUNCTION("""COMPUTED_VALUE"""),"$15 Donation, Discord Verification") -> $15 Donation, Discord Verification | O85: =IFERROR(__xludf.DUMMYFUNCTION("""COMPUTED_VALUE"""),"Fundraising, TNR, Feeding, Shelter Maintenance") -> Fundraising, TNR, Feeding, Shelter Maintenance | P85: =IFERROR(__xludf.DUMMYFUNCTION("IFERROR( IMAGE( ""https://drive.google.com/uc?export=download&id=""&MID( IMPORTRANGE(""18RaQw448NnENcNftounuam8eQyPVXS6StgZUz-RLzHA"",""'UTA Cat Coalition Membership Application'!L""&ROW()-2) ,(FIND(""="", IMPORTRANGE(""18RaQw448NnENcNftounuam8eQyPVXS6St"&"gZUz-RLzHA"",""'UTA Cat Coalition Membership Application'!L""&ROW()-2) ))+1,LEN( IMPORTRANGE(""18RaQw448NnENcNftounuam8eQyPVXS6StgZUz-RLzHA"",""'UTA Cat Coalition Membership Application'!L""&ROW()-2) )-FIND(""="", IMPORTRANGE(""18RaQw448NnENcNftounuam8eQy"&"PVXS6StgZUz-RLzHA"",""'UTA Cat Coalition Membership Application'!L""&ROW()-2) )),1 ) , """")"),"")
A86: =IFERROR(__xludf.DUMMYFUNCTION("""COMPUTED_VALUE"""),44804.638229178236) -> 44804.638 | B86: TRUE | C86: =IF(A86<>"", IFERROR(IF(MONTH(A86) < 6, "Spring ", "Fall ") & IF(MONTH(A86) < 6, YEAR(A86), YEAR(A86) + IF(MONTH(A86) = 12, 1, 0)), ""), "") -> Fall 2022 | D86: =IFERROR(__xludf.DUMMYFUNCTION("""COMPUTED_VALUE"""),"egf6930@mavs.uta.edu") -> egf6930@mavs.uta.edu | E86: =IFERROR(__xludf.DUMMYFUNCTION("""COMPUTED_VALUE"""),"Elli Ferren") -> Elli Ferren | F86: =IFERROR(__xludf.DUMMYFUNCTION("""COMPUTED_VALUE"""),"elli😼 #4888") -> elli😼 #4888 | H86: =IFERROR(__xludf.DUMMYFUNCTION("""COMPUTED_VALUE"""),"(214) 763-1495") -> (214) 763-1495 | I86: =IFERROR(__xludf.DUMMYFUNCTION("""COMPUTED_VALUE"""),"Student") -> Student | J86: =IFERROR(__xludf.DUMMYFUNCTION("""COMPUTED_VALUE"""),"$15 Donation, Discord Verification") -> $15 Donation, Discord Verification | O86: =IFERROR(__xludf.DUMMYFUNCTION("""COMPUTED_VALUE"""),"Fundraising, TNR, Feeding, Shelter Maintenance") -> Fundraising, TNR, Feeding, Shelter Maintenance | P86: =IFERROR(__xludf.DUMMYFUNCTION("IFERROR( IMAGE( ""https://drive.google.com/uc?export=download&id=""&MID( IMPORTRANGE(""18RaQw448NnENcNftounuam8eQyPVXS6StgZUz-RLzHA"",""'UTA Cat Coalition Membership Application'!L""&ROW()-2) ,(FIND(""="", IMPORTRANGE(""18RaQw448NnENcNftounuam8eQyPVXS6St"&"gZUz-RLzHA"",""'UTA Cat Coalition Membership Application'!L""&ROW()-2) ))+1,LEN( IMPORTRANGE(""18RaQw448NnENcNftounuam8eQyPVXS6StgZUz-RLzHA"",""'UTA Cat Coalition Membership Application'!L""&ROW()-2) )-FIND(""="", IMPORTRANGE(""18RaQw448NnENcNftounuam8eQy"&"PVXS6StgZUz-RLzHA"",""'UTA Cat Coalition Membership Application'!L""&ROW()-2) )),1 ) , """")"),"")
A87: =IFERROR(__xludf.DUMMYFUNCTION("""COMPUTED_VALUE"""),44804.6799708912) -> 44804.68 | B87: TRUE | C87: =IF(A87<>"", IFERROR(IF(MONTH(A87) < 6, "Spring ", "Fall ") & IF(MONTH(A87) < 6, YEAR(A87), YEAR(A87) + IF(MONTH(A87) = 12, 1, 0)), ""), "") -> Fall 2022 | D87: =IFERROR(__xludf.DUMMYFUNCTION("""COMPUTED_VALUE"""),"sydney.stumpf@mavs.uta.edu") -> sydney.stumpf@mavs.uta.edu | E87: =IFERROR(__xludf.DUMMYFUNCTION("""COMPUTED_VALUE"""),"Sydney Stumpf") -> Sydney Stumpf | F87: =IFERROR(__xludf.DUMMYFUNCTION("""COMPUTED_VALUE"""),"Sydneystumpf") -> Sydneystumpf | H87: =IFERROR(__xludf.DUMMYFUNCTION("""COMPUTED_VALUE"""),"(972) 571-0727") -> (972) 571-0727 | I87: =IFERROR(__xludf.DUMMYFUNCTION("""COMPUTED_VALUE"""),"Student") -> Student | J87: =IFERROR(__xludf.DUMMYFUNCTION("""COMPUTED_VALUE"""),"$15 Donation, Discord Verification") -> $15 Donation, Discord Verification | O87: =IFERROR(__xludf.DUMMYFUNCTION("""COMPUTED_VALUE"""),"Fundraising, PR, Feeding") -> Fundraising, PR, Feeding | P87: =IFERROR(__xludf.DUMMYFUNCTION("IFERROR( IMAGE( ""https://drive.google.com/uc?export=download&id=""&MID( IMPORTRANGE(""18RaQw448NnENcNftounuam8eQyPVXS6StgZUz-RLzHA"",""'UTA Cat Coalition Membership Application'!L""&ROW()-2) ,(FIND(""="", IMPORTRANGE(""18RaQw448NnENcNftounuam8eQyPVXS6St"&"gZUz-RLzHA"",""'UTA Cat Coalition Membership Application'!L""&ROW()-2) ))+1,LEN( IMPORTRANGE(""18RaQw448NnENcNftounuam8eQyPVXS6StgZUz-RLzHA"",""'UTA Cat Coalition Membership Application'!L""&ROW()-2) )-FIND(""="", IMPORTRANGE(""18RaQw448NnENcNftounuam8eQy"&"PVXS6StgZUz-RLzHA"",""'UTA Cat Coalition Membership Application'!L""&ROW()-2) )),1 ) , """")"),"")
A88: =IFERROR(__xludf.DUMMYFUNCTION("""COMPUTED_VALUE"""),44804.71232553241) -> 44804.712 | B88: TRUE | C88: =IF(A88<>"", IFERROR(IF(MONTH(A88) < 6, "Spring ", "Fall ") & IF(MONTH(A88) < 6, YEAR(A88), YEAR(A88) + IF(MONTH(A88) = 12, 1, 0)), ""), "") -> Fall 2022 | D88: =IFERROR(__xludf.DUMMYFUNCTION("""COMPUTED_VALUE"""),"njc0039@mavs.uta.edu") -> njc0039@mavs.uta.edu | E88: =IFERROR(__xludf.DUMMYFUNCTION("""COMPUTED_VALUE"""),"Naijha Coleman") -> Naijha Coleman | F88: =IFERROR(__xludf.DUMMYFUNCTION("""COMPUTED_VALUE"""),"Naijha Coleman") -> Naijha Coleman | H88: =IFERROR(__xludf.DUMMYFUNCTION("""COMPUTED_VALUE"""),"(219) 242-7348") -> (219) 242-7348 | I88: =IFERROR(__xludf.DUMMYFUNCTION("""COMPUTED_VALUE"""),"Student") -> Student | J88: =IFERROR(__xludf.DUMMYFUNCTION("""COMPUTED_VALUE"""),"$15 Donation, Discord Verification") -> $15 Donation, Discord Verification | O88: =IFERROR(__xludf.DUMMYFUNCTION("""COMPUTED_VALUE"""),"TNR, Overnight TNR, Feeding, Shelter Maintenance") -> TNR, Overnight TNR, Feeding, Shelter Maintenance | P88: =IFERROR(__xludf.DUMMYFUNCTION("IFERROR( IMAGE( ""https://drive.google.com/uc?export=download&id=""&MID( IMPORTRANGE(""18RaQw448NnENcNftounuam8eQyPVXS6StgZUz-RLzHA"",""'UTA Cat Coalition Membership Application'!L""&ROW()-2) ,(FIND(""="", IMPORTRANGE(""18RaQw448NnENcNftounuam8eQyPVXS6St"&"gZUz-RLzHA"",""'UTA Cat Coalition Membership Application'!L""&ROW()-2) ))+1,LEN( IMPORTRANGE(""18RaQw448NnENcNftounuam8eQyPVXS6StgZUz-RLzHA"",""'UTA Cat Coalition Membership Application'!L""&ROW()-2) )-FIND(""="", IMPORTRANGE(""18RaQw448NnENcNftounuam8eQy"&"PVXS6StgZUz-RLzHA"",""'UTA Cat Coalition Membership Application'!L""&ROW()-2) )),1 ) , """")"),"")
